Workbook

Sheet Настройка робота
A1: Оценка трудозатрат на настройку алгоритма робота (человеко-часов)
A2: № | B2: Наименование | C2: Тип задачи | D2: Сложность | E2: Оценка
E3: Автоматически | F3: Уточненно
A4: 1 | B4: Проверка новых писем в ящике заявок | C4: Почта/Outlook | D4: Легкая | E4: =(IF(C4='Оценка сложности задач'!$A$2,1,0)*IF(D4='Оценка сложности задач'!$B$2,1,0)*'Оценка сложности задач'!$G$2)+(IF(C4='Оценка сложности задач'!$A$3,1,0)*IF(D4='Оценка сложности задач'!$B$3,1,0)*'Оценка сложности задач'!$G$3)+(IF(C4='Оценка сложности задач'!$A$4,1,0)*IF(D4='Оценка сложности задач'!$B$4,1,0)*'Оценка сложности задач'!$G$4)+(IF(C4='Оценка сложности задач'!$A$5,1,0)*IF(D4='Оценка сложности задач'!$B$5,1,0)*'Оценка сложности задач'!$G$5)+(IF(C4='Оценка сложности задач'!$A$6,1,0)*IF(D4='Оценка сложности задач'!$B$6,1,0)*'Оценка сложности задач'!$G$6)+(IF(C4='Оценка сложности задач'!$A$7,1,0)*IF(D4='Оценка сложности задач'!$B$7,1,0)*'Оценка сложности задач'!$G$7)+(IF(C4='Оценка сложности задач'!$A$8,1,0)*IF(D4='Оценка сложности задач'!$B$8,1,0)*'Оценка сложности задач'!$G$8)+(IF(C4='Оценка сложности задач'!$A$10,1,0)*IF(D4='Оценка сложности задач'!$B$10,1,0)*'Оценка сложности задач'!$G$10)+(IF(C4='Оценка сложности задач'!$A$9,1,0)*IF(D4='Оценка сложности задач'!$B$9,1,0)*'Оценка сложности задач'!$G$9)+ (IF(C4='Оценка сложности задач'!$A$11,1,0)*IF(D4='Оценка сложности задач'!$B$11,1,0)*'Оценка сложности задач'!$G$11) + (IF(C4='Оценка сложности задач'!$A$12,1,0)*IF(D4='Оценка сложности задач'!$B$12,1,0)*'Оценка сложности задач'!$G$12) + (IF(C4='Оценка сложности задач'!$A$13,1,0)*IF(D4='Оценка сложности задач'!$B$13,1,0)*'Оценка сложности задач'!$G$13) + (IF(C4='Оценка сложности задач'!$A$14,1,0)*IF(D4='Оценка сложности задач'!$B$14,1,0)*'Оценка сложности задач'!$G$14) + (IF(C4='Оценка сложности задач'!$A$15,1,0)*IF(D4='Оценка сложности задач'!$B$15,1,0)*'Оценка сложности задач'!$G$15) + (IF(C4='Оценка сложности задач'!$A$16,1,0)*IF(D4='Оценка сложности задач'!$B$16,1,0)*'Оценка сложности задач'!$G$16) + (IF(C4='Оценка сложности задач'!$A$17,1,0)*IF(D4='Оценка сложности задач'!$B$17,1,0)*'Оценка сложности задач'!$G$17) + (IF(C4='Оценка сложности задач'!$A$18,1,0)*IF(D4='Оценка сложности задач'!$B$18,1,0)*'Оценка сложности задач'!$G$18) + (IF(C4='Оценка сложности задач'!$A$19,1,0)*IF(D4='Оценка сложности задач'!$B$19,1,0)*'Оценка сложности задач'!$G$19)+(IF(C4='Оценка сложности задач'!$A$20,1,0)*IF(D4='Оценка сложности задач'!$B$20,1,0)*'Оценка сложности задач'!$G$20)+(IF(C4='Оценка сложности задач'!$A$21,1,0)*IF(D4='Оценка сложности задач'!$B$21,1,0)*'Оценка сложности задач'!$G$21)+(IF(C4='Оценка сложности задач'!$A$22,1,0)*IF(D4='Оценка сложности задач'!$B$22,1,0)*'Оценка сложности задач'!$G$22)+(IF(C4='Оценка сложности задач'!$A$23,1,0)*IF(D4='Оценка сложности задач'!$B$23,1,0)*'Оценка сложности задач'!$G$23)+(IF(C4='Оценка сложности задач'!$A$24,1,0)*IF(D4='Оценка сложности задач'!$B$24,1,0)*'Оценка сложности задач'!$G$24)+(IF(C4='Оценка сложности задач'!$A$25,1,0)*IF(D4='Оценка сложности задач'!$B$25,1,0)*'Оценка сложности задач'!$G$25)+(IF(C4='Оценка сложности задач'!$A$26,1,0)*IF(D4='Оценка сложности задач'!$B$26,1,0)*'Оценка сложности задач'!$G$26)+(IF(C4='Оценка сложности задач'!$A$27,1,0)*IF(D4='Оценка сложности задач'!$B$27,1,0)*'Оценка сложности задач'!$G$27)+(IF(C4='Оценка сложности задач'!$A$28,1,0)*IF(D4='Оценка сложности задач'!$B$28,1,0)*'Оценка сложности задач'!$G$28)+(IF(C4='Оценка сложности задач'!$A$29,1,0)*IF(D4='Оценка сложности задач'!$B$29,1,0)*'Оценка сложности задач'!$G$29)+(IF(C4='Оценка сложности задач'!$A$30,1,0)*IF(D4='Оценка сложности задач'!$B$30,1,0)*'Оценка сложности задач'!$G$30)+(IF(C4='Оценка сложности задач'!$A$31,1,0)*IF(D4='Оценка сложности задач'!$B$31,1,0)*'Оценка сложности задач'!$G$31)+(IF(C4='Оценка сложности задач'!$A$32,1,0)*IF(D4='Оценка сложности задач'!$B$32,1,0)*'Оценка сложности задач'!$G$32)+(IF(C4='Оценка сложности задач'!$A$33,1,0)*IF(D4='Оценка сложности задач'!$B$33,1,0)*'Оценка сложности задач'!$G$33)+(IF(C4='Оценка сложности задач'!$A$34,1,0)*IF(D4='Оценка сложности задач'!$B$34,1,0)*'Оценка сложности задач'!$G$34)+(IF(C4='Оценка сложности задач'!$A$35,1,0)*IF(D4='Оценка сложности задач'!$B$35,1,0)*'Оценка сложности задач'!$G$35)+(IF(C4='Оценка сложности задач'!$A$36,1,0)*IF(D4='Оценка сложности задач'!$B$36,1,0)*'Оценка сложности задач'!$G$36)+(IF(C4='Оценка сложности задач'!$A$37,1,0)*IF(D4='Оценка сложности задач'!$B$37,1,0)*'Оценка сложности задач'!$G$37)+(IF(C4='Оценка сложности задач'!$A$38,1,0)*IF(D4='Оценка сложности задач'!$B$38,1,0)*'Оценка сложности задач'!$G$38)+(IF(C4='Оценка сложности задач'!$A$39,1,0)*IF(D4='Оценка сложности задач'!$B$39,1,0)*'Оценка сложности задач'!$G$39)+(IF(C4='Оценка сложности задач'!$A$40,1,0)*IF(D4='Оценка сложности задач'!$B$40,1,0)*'Оценка сложности задач'!$G$40) -> 6
A5: 2 | B5: Фильтрация писем: только заявки (по адресату/теме/метке) | C5: Настройка процесса | D5: Легкая | E5: =(IF(C5='Оценка сложности задач'!$A$2,1,0)*IF(D5='Оценка сложности задач'!$B$2,1,0)*'Оценка сложности задач'!$G$2)+(IF(C5='Оценка сложности задач'!$A$3,1,0)*IF(D5='Оценка сложности задач'!$B$3,1,0)*'Оценка сложности задач'!$G$3)+(IF(C5='Оценка сложности задач'!$A$4,1,0)*IF(D5='Оценка сложности задач'!$B$4,1,0)*'Оценка сложности задач'!$G$4)+(IF(C5='Оценка сложности задач'!$A$5,1,0)*IF(D5='Оценка сложности задач'!$B$5,1,0)*'Оценка сложности задач'!$G$5)+(IF(C5='Оценка сложности задач'!$A$6,1,0)*IF(D5='Оценка сложности задач'!$B$6,1,0)*'Оценка сложности задач'!$G$6)+(IF(C5='Оценка сложности задач'!$A$7,1,0)*IF(D5='Оценка сложности задач'!$B$7,1,0)*'Оценка сложности задач'!$G$7)+(IF(C5='Оценка сложности задач'!$A$8,1,0)*IF(D5='Оценка сложности задач'!$B$8,1,0)*'Оценка сложности задач'!$G$8)+(IF(C5='Оценка сложности задач'!$A$10,1,0)*IF(D5='Оценка сложности задач'!$B$10,1,0)*'Оценка сложности задач'!$G$10)+(IF(C5='Оценка сложности задач'!$A$9,1,0)*IF(D5='Оценка сложности задач'!$B$9,1,0)*'Оценка сложности задач'!$G$9)+ (IF(C5='Оценка сложности задач'!$A$11,1,0)*IF(D5='Оценка сложности задач'!$B$11,1,0)*'Оценка сложности задач'!$G$11) + (IF(C5='Оценка сложности задач'!$A$12,1,0)*IF(D5='Оценка сложности задач'!$B$12,1,0)*'Оценка сложности задач'!$G$12) + (IF(C5='Оценка сложности задач'!$A$13,1,0)*IF(D5='Оценка сложности задач'!$B$13,1,0)*'Оценка сложности задач'!$G$13) + (IF(C5='Оценка сложности задач'!$A$14,1,0)*IF(D5='Оценка сложности задач'!$B$14,1,0)*'Оценка сложности задач'!$G$14) + (IF(C5='Оценка сложности задач'!$A$15,1,0)*IF(D5='Оценка сложности задач'!$B$15,1,0)*'Оценка сложности задач'!$G$15) + (IF(C5='Оценка сложности задач'!$A$16,1,0)*IF(D5='Оценка сложности задач'!$B$16,1,0)*'Оценка сложности задач'!$G$16) + (IF(C5='Оценка сложности задач'!$A$17,1,0)*IF(D5='Оценка сложности задач'!$B$17,1,0)*'Оценка сложности задач'!$G$17) + (IF(C5='Оценка сложности задач'!$A$18,1,0)*IF(D5='Оценка сложности задач'!$B$18,1,0)*'Оценка сложности задач'!$G$18) + (IF(C5='Оценка сложности задач'!$A$19,1,0)*IF(D5='Оценка сложности задач'!$B$19,1,0)*'Оценка сложности задач'!$G$19)+(IF(C5='Оценка сложности задач'!$A$20,1,0)*IF(D5='Оценка сложности задач'!$B$20,1,0)*'Оценка сложности задач'!$G$20)+(IF(C5='Оценка сложности задач'!$A$21,1,0)*IF(D5='Оценка сложности задач'!$B$21,1,0)*'Оценка сложности задач'!$G$21)+(IF(C5='Оценка сложности задач'!$A$22,1,0)*IF(D5='Оценка сложности задач'!$B$22,1,0)*'Оценка сложности задач'!$G$22)+(IF(C5='Оценка сложности задач'!$A$23,1,0)*IF(D5='Оценка сложности задач'!$B$23,1,0)*'Оценка сложности задач'!$G$23)+(IF(C5='Оценка сложности задач'!$A$24,1,0)*IF(D5='Оценка сложности задач'!$B$24,1,0)*'Оценка сложности задач'!$G$24)+(IF(C5='Оценка сложности задач'!$A$25,1,0)*IF(D5='Оценка сложности задач'!$B$25,1,0)*'Оценка сложности задач'!$G$25)+(IF(C5='Оценка сложности задач'!$A$26,1,0)*IF(D5='Оценка сложности задач'!$B$26,1,0)*'Оценка сложности задач'!$G$26)+(IF(C5='Оценка сложности задач'!$A$27,1,0)*IF(D5='Оценка сложности задач'!$B$27,1,0)*'Оценка сложности задач'!$G$27)+(IF(C5='Оценка сложности задач'!$A$28,1,0)*IF(D5='Оценка сложности задач'!$B$28,1,0)*'Оценка сложности задач'!$G$28)+(IF(C5='Оценка сложности задач'!$A$29,1,0)*IF(D5='Оценка сложности задач'!$B$29,1,0)*'Оценка сложности задач'!$G$29)+(IF(C5='Оценка сложности задач'!$A$30,1,0)*IF(D5='Оценка сложности задач'!$B$30,1,0)*'Оценка сложности задач'!$G$30)+(IF(C5='Оценка сложности задач'!$A$31,1,0)*IF(D5='Оценка сложности задач'!$B$31,1,0)*'Оценка сложности задач'!$G$31)+(IF(C5='Оценка сложности задач'!$A$32,1,0)*IF(D5='Оценка сложности задач'!$B$32,1,0)*'Оценка сложности задач'!$G$32)+(IF(C5='Оценка сложности задач'!$A$33,1,0)*IF(D5='Оценка сложности задач'!$B$33,1,0)*'Оценка сложности задач'!$G$33)+(IF(C5='Оценка сложности задач'!$A$34,1,0)*IF(D5='Оценка сложности задач'!$B$34,1,0)*'Оценка сложности задач'!$G$34)+(IF(C5='Оценка сложности задач'!$A$35,1,0)*IF(D5='Оценка сложности задач'!$B$35,1,0)*'Оценка сложности задач'!$G$35)+(IF(C5='Оценка сложности задач'!$A$36,1,0)*IF(D5='Оценка сложности задач'!$B$36,1,0)*'Оценка сложности задач'!$G$36)+(IF(C5='Оценка сложности задач'!$A$37,1,0)*IF(D5='Оценка сложности задач'!$B$37,1,0)*'Оценка сложности задач'!$G$37)+(IF(C5='Оценка сложности задач'!$A$38,1,0)*IF(D5='Оценка сложности задач'!$B$38,1,0)*'Оценка сложности задач'!$G$38)+(IF(C5='Оценка сложности задач'!$A$39,1,0)*IF(D5='Оценка сложности задач'!$B$39,1,0)*'Оценка сложности задач'!$G$39)+(IF(C5='Оценка сложности задач'!$A$40,1,0)*IF(D5='Оценка сложности задач'!$B$40,1,0)*'Оценка сложности задач'!$G$40) -> 6
A6: 3 | B6: Сохранение письма и вложений во временную папку | C6: Файлы/Папки/FTP | D6: Средняя | E6: =(IF(C6='Оценка сложности задач'!$A$2,1,0)*IF(D6='Оценка сложности задач'!$B$2,1,0)*'Оценка сложности задач'!$G$2)+(IF(C6='Оценка сложности задач'!$A$3,1,0)*IF(D6='Оценка сложности задач'!$B$3,1,0)*'Оценка сложности задач'!$G$3)+(IF(C6='Оценка сложности задач'!$A$4,1,0)*IF(D6='Оценка сложности задач'!$B$4,1,0)*'Оценка сложности задач'!$G$4)+(IF(C6='Оценка сложности задач'!$A$5,1,0)*IF(D6='Оценка сложности задач'!$B$5,1,0)*'Оценка сложности задач'!$G$5)+(IF(C6='Оценка сложности задач'!$A$6,1,0)*IF(D6='Оценка сложности задач'!$B$6,1,0)*'Оценка сложности задач'!$G$6)+(IF(C6='Оценка сложности задач'!$A$7,1,0)*IF(D6='Оценка сложности задач'!$B$7,1,0)*'Оценка сложности задач'!$G$7)+(IF(C6='Оценка сложности задач'!$A$8,1,0)*IF(D6='Оценка сложности задач'!$B$8,1,0)*'Оценка сложности задач'!$G$8)+(IF(C6='Оценка сложности задач'!$A$10,1,0)*IF(D6='Оценка сложности задач'!$B$10,1,0)*'Оценка сложности задач'!$G$10)+(IF(C6='Оценка сложности задач'!$A$9,1,0)*IF(D6='Оценка сложности задач'!$B$9,1,0)*'Оценка сложности задач'!$G$9)+ (IF(C6='Оценка сложности задач'!$A$11,1,0)*IF(D6='Оценка сложности задач'!$B$11,1,0)*'Оценка сложности задач'!$G$11) + (IF(C6='Оценка сложности задач'!$A$12,1,0)*IF(D6='Оценка сложности задач'!$B$12,1,0)*'Оценка сложности задач'!$G$12) + (IF(C6='Оценка сложности задач'!$A$13,1,0)*IF(D6='Оценка сложности задач'!$B$13,1,0)*'Оценка сложности задач'!$G$13) + (IF(C6='Оценка сложности задач'!$A$14,1,0)*IF(D6='Оценка сложности задач'!$B$14,1,0)*'Оценка сложности задач'!$G$14) + (IF(C6='Оценка сложности задач'!$A$15,1,0)*IF(D6='Оценка сложности задач'!$B$15,1,0)*'Оценка сложности задач'!$G$15) + (IF(C6='Оценка сложности задач'!$A$16,1,0)*IF(D6='Оценка сложности задач'!$B$16,1,0)*'Оценка сложности задач'!$G$16) + (IF(C6='Оценка сложности задач'!$A$17,1,0)*IF(D6='Оценка сложности задач'!$B$17,1,0)*'Оценка сложности задач'!$G$17) + (IF(C6='Оценка сложности задач'!$A$18,1,0)*IF(D6='Оценка сложности задач'!$B$18,1,0)*'Оценка сложности задач'!$G$18) + (IF(C6='Оценка сложности задач'!$A$19,1,0)*IF(D6='Оценка сложности задач'!$B$19,1,0)*'Оценка сложности задач'!$G$19)+(IF(C6='Оценка сложности задач'!$A$20,1,0)*IF(D6='Оценка сложности задач'!$B$20,1,0)*'Оценка сложности задач'!$G$20)+(IF(C6='Оценка сложности задач'!$A$21,1,0)*IF(D6='Оценка сложности задач'!$B$21,1,0)*'Оценка сложности задач'!$G$21)+(IF(C6='Оценка сложности задач'!$A$22,1,0)*IF(D6='Оценка сложности задач'!$B$22,1,0)*'Оценка сложности задач'!$G$22)+(IF(C6='Оценка сложности задач'!$A$23,1,0)*IF(D6='Оценка сложности задач'!$B$23,1,0)*'Оценка сложности задач'!$G$23)+(IF(C6='Оценка сложности задач'!$A$24,1,0)*IF(D6='Оценка сложности задач'!$B$24,1,0)*'Оценка сложности задач'!$G$24)+(IF(C6='Оценка сложности задач'!$A$25,1,0)*IF(D6='Оценка сложности задач'!$B$25,1,0)*'Оценка сложности задач'!$G$25)+(IF(C6='Оценка сложности задач'!$A$26,1,0)*IF(D6='Оценка сложности задач'!$B$26,1,0)*'Оценка сложности задач'!$G$26)+(IF(C6='Оценка сложности задач'!$A$27,1,0)*IF(D6='Оценка сложности задач'!$B$27,1,0)*'Оценка сложности задач'!$G$27)+(IF(C6='Оценка сложности задач'!$A$28,1,0)*IF(D6='Оценка сложности задач'!$B$28,1,0)*'Оценка сложности задач'!$G$28)+(IF(C6='Оценка сложности задач'!$A$29,1,0)*IF(D6='Оценка сложности задач'!$B$29,1,0)*'Оценка сложности задач'!$G$29)+(IF(C6='Оценка сложности задач'!$A$30,1,0)*IF(D6='Оценка сложности задач'!$B$30,1,0)*'Оценка сложности задач'!$G$30)+(IF(C6='Оценка сложности задач'!$A$31,1,0)*IF(D6='Оценка сложности задач'!$B$31,1,0)*'Оценка сложности задач'!$G$31)+(IF(C6='Оценка сложности задач'!$A$32,1,0)*IF(D6='Оценка сложности задач'!$B$32,1,0)*'Оценка сложности задач'!$G$32)+(IF(C6='Оценка сложности задач'!$A$33,1,0)*IF(D6='Оценка сложности задач'!$B$33,1,0)*'Оценка сложности задач'!$G$33)+(IF(C6='Оценка сложности задач'!$A$34,1,0)*IF(D6='Оценка сложности задач'!$B$34,1,0)*'Оценка сложности задач'!$G$34)+(IF(C6='Оценка сложности задач'!$A$35,1,0)*IF(D6='Оценка сложности задач'!$B$35,1,0)*'Оценка сложности задач'!$G$35)+(IF(C6='Оценка сложности задач'!$A$36,1,0)*IF(D6='Оценка сложности задач'!$B$36,1,0)*'Оценка сложности задач'!$G$36)+(IF(C6='Оценка сложности задач'!$A$37,1,0)*IF(D6='Оценка сложности задач'!$B$37,1,0)*'Оценка сложности задач'!$G$37)+(IF(C6='Оценка сложности задач'!$A$38,1,0)*IF(D6='Оценка сложности задач'!$B$38,1,0)*'Оценка сложности задач'!$G$38)+(IF(C6='Оценка сложности задач'!$A$39,1,0)*IF(D6='Оценка сложности задач'!$B$39,1,0)*'Оценка сложности задач'!$G$39)+(IF(C6='Оценка сложности задач'!$A$40,1,0)*IF(D6='Оценка сложности задач'!$B$40,1,0)*'Оценка сложности задач'!$G$40) -> 11
A7: 4 | B7: Извлечение данных из письма: тема/тело/отправитель | C7: Обработка текста | D7: Средняя | E7: =(IF(C7='Оценка сложности задач'!$A$2,1,0)*IF(D7='Оценка сложности задач'!$B$2,1,0)*'Оценка сложности задач'!$G$2)+(IF(C7='Оценка сложности задач'!$A$3,1,0)*IF(D7='Оценка сложности задач'!$B$3,1,0)*'Оценка сложности задач'!$G$3)+(IF(C7='Оценка сложности задач'!$A$4,1,0)*IF(D7='Оценка сложности задач'!$B$4,1,0)*'Оценка сложности задач'!$G$4)+(IF(C7='Оценка сложности задач'!$A$5,1,0)*IF(D7='Оценка сложности задач'!$B$5,1,0)*'Оценка сложности задач'!$G$5)+(IF(C7='Оценка сложности задач'!$A$6,1,0)*IF(D7='Оценка сложности задач'!$B$6,1,0)*'Оценка сложности задач'!$G$6)+(IF(C7='Оценка сложности задач'!$A$7,1,0)*IF(D7='Оценка сложности задач'!$B$7,1,0)*'Оценка сложности задач'!$G$7)+(IF(C7='Оценка сложности задач'!$A$8,1,0)*IF(D7='Оценка сложности задач'!$B$8,1,0)*'Оценка сложности задач'!$G$8)+(IF(C7='Оценка сложности задач'!$A$10,1,0)*IF(D7='Оценка сложности задач'!$B$10,1,0)*'Оценка сложности задач'!$G$10)+(IF(C7='Оценка сложности задач'!$A$9,1,0)*IF(D7='Оценка сложности задач'!$B$9,1,0)*'Оценка сложности задач'!$G$9)+ (IF(C7='Оценка сложности задач'!$A$11,1,0)*IF(D7='Оценка сложности задач'!$B$11,1,0)*'Оценка сложности задач'!$G$11) + (IF(C7='Оценка сложности задач'!$A$12,1,0)*IF(D7='Оценка сложности задач'!$B$12,1,0)*'Оценка сложности задач'!$G$12) + (IF(C7='Оценка сложности задач'!$A$13,1,0)*IF(D7='Оценка сложности задач'!$B$13,1,0)*'Оценка сложности задач'!$G$13) + (IF(C7='Оценка сложности задач'!$A$14,1,0)*IF(D7='Оценка сложности задач'!$B$14,1,0)*'Оценка сложности задач'!$G$14) + (IF(C7='Оценка сложности задач'!$A$15,1,0)*IF(D7='Оценка сложности задач'!$B$15,1,0)*'Оценка сложности задач'!$G$15) + (IF(C7='Оценка сложности задач'!$A$16,1,0)*IF(D7='Оценка сложности задач'!$B$16,1,0)*'Оценка сложности задач'!$G$16) + (IF(C7='Оценка сложности задач'!$A$17,1,0)*IF(D7='Оценка сложности задач'!$B$17,1,0)*'Оценка сложности задач'!$G$17) + (IF(C7='Оценка сложности задач'!$A$18,1,0)*IF(D7='Оценка сложности задач'!$B$18,1,0)*'Оценка сложности задач'!$G$18) + (IF(C7='Оценка сложности задач'!$A$19,1,0)*IF(D7='Оценка сложности задач'!$B$19,1,0)*'Оценка сложности задач'!$G$19)+(IF(C7='Оценка сложности задач'!$A$20,1,0)*IF(D7='Оценка сложности задач'!$B$20,1,0)*'Оценка сложности задач'!$G$20)+(IF(C7='Оценка сложности задач'!$A$21,1,0)*IF(D7='Оценка сложности задач'!$B$21,1,0)*'Оценка сложности задач'!$G$21)+(IF(C7='Оценка сложности задач'!$A$22,1,0)*IF(D7='Оценка сложности задач'!$B$22,1,0)*'Оценка сложности задач'!$G$22)+(IF(C7='Оценка сложности задач'!$A$23,1,0)*IF(D7='Оценка сложности задач'!$B$23,1,0)*'Оценка сложности задач'!$G$23)+(IF(C7='Оценка сложности задач'!$A$24,1,0)*IF(D7='Оценка сложности задач'!$B$24,1,0)*'Оценка сложности задач'!$G$24)+(IF(C7='Оценка сложности задач'!$A$25,1,0)*IF(D7='Оценка сложности задач'!$B$25,1,0)*'Оценка сложности задач'!$G$25)+(IF(C7='Оценка сложности задач'!$A$26,1,0)*IF(D7='Оценка сложности задач'!$B$26,1,0)*'Оценка сложности задач'!$G$26)+(IF(C7='Оценка сложности задач'!$A$27,1,0)*IF(D7='Оценка сложности задач'!$B$27,1,0)*'Оценка сложности задач'!$G$27)+(IF(C7='Оценка сложности задач'!$A$28,1,0)*IF(D7='Оценка сложности задач'!$B$28,1,0)*'Оценка сложности задач'!$G$28)+(IF(C7='Оценка сложности задач'!$A$29,1,0)*IF(D7='Оценка сложности задач'!$B$29,1,0)*'Оценка сложности задач'!$G$29)+(IF(C7='Оценка сложности задач'!$A$30,1,0)*IF(D7='Оценка сложности задач'!$B$30,1,0)*'Оценка сложности задач'!$G$30)+(IF(C7='Оценка сложности задач'!$A$31,1,0)*IF(D7='Оценка сложности задач'!$B$31,1,0)*'Оценка сложности задач'!$G$31)+(IF(C7='Оценка сложности задач'!$A$32,1,0)*IF(D7='Оценка сложности задач'!$B$32,1,0)*'Оценка сложности задач'!$G$32)+(IF(C7='Оценка сложности задач'!$A$33,1,0)*IF(D7='Оценка сложности задач'!$B$33,1,0)*'Оценка сложности задач'!$G$33)+(IF(C7='Оценка сложности задач'!$A$34,1,0)*IF(D7='Оценка сложности задач'!$B$34,1,0)*'Оценка сложности задач'!$G$34)+(IF(C7='Оценка сложности задач'!$A$35,1,0)*IF(D7='Оценка сложности задач'!$B$35,1,0)*'Оценка сложности задач'!$G$35)+(IF(C7='Оценка сложности задач'!$A$36,1,0)*IF(D7='Оценка сложности задач'!$B$36,1,0)*'Оценка сложности задач'!$G$36)+(IF(C7='Оценка сложности задач'!$A$37,1,0)*IF(D7='Оценка сложности задач'!$B$37,1,0)*'Оценка сложности задач'!$G$37)+(IF(C7='Оценка сложности задач'!$A$38,1,0)*IF(D7='Оценка сложности задач'!$B$38,1,0)*'Оценка сложности задач'!$G$38)+(IF(C7='Оценка сложности задач'!$A$39,1,0)*IF(D7='Оценка сложности задач'!$B$39,1,0)*'Оценка сложности задач'!$G$39)+(IF(C7='Оценка сложности задач'!$A$40,1,0)*IF(D7='Оценка сложности задач'!$B$40,1,0)*'Оценка сложности задач'!$G$40) -> 6
A8: 5 | B8: Парсинг контактных данных из текста (ФИО, телефон, компания) | C8: Обработка текста | D8: Средняя | E8: =(IF(C8='Оценка сложности задач'!$A$2,1,0)*IF(D8='Оценка сложности задач'!$B$2,1,0)*'Оценка сложности задач'!$G$2)+(IF(C8='Оценка сложности задач'!$A$3,1,0)*IF(D8='Оценка сложности задач'!$B$3,1,0)*'Оценка сложности задач'!$G$3)+(IF(C8='Оценка сложности задач'!$A$4,1,0)*IF(D8='Оценка сложности задач'!$B$4,1,0)*'Оценка сложности задач'!$G$4)+(IF(C8='Оценка сложности задач'!$A$5,1,0)*IF(D8='Оценка сложности задач'!$B$5,1,0)*'Оценка сложности задач'!$G$5)+(IF(C8='Оценка сложности задач'!$A$6,1,0)*IF(D8='Оценка сложности задач'!$B$6,1,0)*'Оценка сложности задач'!$G$6)+(IF(C8='Оценка сложности задач'!$A$7,1,0)*IF(D8='Оценка сложности задач'!$B$7,1,0)*'Оценка сложности задач'!$G$7)+(IF(C8='Оценка сложности задач'!$A$8,1,0)*IF(D8='Оценка сложности задач'!$B$8,1,0)*'Оценка сложности задач'!$G$8)+(IF(C8='Оценка сложности задач'!$A$10,1,0)*IF(D8='Оценка сложности задач'!$B$10,1,0)*'Оценка сложности задач'!$G$10)+(IF(C8='Оценка сложности задач'!$A$9,1,0)*IF(D8='Оценка сложности задач'!$B$9,1,0)*'Оценка сложности задач'!$G$9)+ (IF(C8='Оценка сложности задач'!$A$11,1,0)*IF(D8='Оценка сложности задач'!$B$11,1,0)*'Оценка сложности задач'!$G$11) + (IF(C8='Оценка сложности задач'!$A$12,1,0)*IF(D8='Оценка сложности задач'!$B$12,1,0)*'Оценка сложности задач'!$G$12) + (IF(C8='Оценка сложности задач'!$A$13,1,0)*IF(D8='Оценка сложности задач'!$B$13,1,0)*'Оценка сложности задач'!$G$13) + (IF(C8='Оценка сложности задач'!$A$14,1,0)*IF(D8='Оценка сложности задач'!$B$14,1,0)*'Оценка сложности задач'!$G$14) + (IF(C8='Оценка сложности задач'!$A$15,1,0)*IF(D8='Оценка сложности задач'!$B$15,1,0)*'Оценка сложности задач'!$G$15) + (IF(C8='Оценка сложности задач'!$A$16,1,0)*IF(D8='Оценка сложности задач'!$B$16,1,0)*'Оценка сложности задач'!$G$16) + (IF(C8='Оценка сложности задач'!$A$17,1,0)*IF(D8='Оценка сложности задач'!$B$17,1,0)*'Оценка сложности задач'!$G$17) + (IF(C8='Оценка сложности задач'!$A$18,1,0)*IF(D8='Оценка сложности задач'!$B$18,1,0)*'Оценка сложности задач'!$G$18) + (IF(C8='Оценка сложности задач'!$A$19,1,0)*IF(D8='Оценка сложности задач'!$B$19,1,0)*'Оценка сложности задач'!$G$19)+(IF(C8='Оценка сложности задач'!$A$20,1,0)*IF(D8='Оценка сложности задач'!$B$20,1,0)*'Оценка сложности задач'!$G$20)+(IF(C8='Оценка сложности задач'!$A$21,1,0)*IF(D8='Оценка сложности задач'!$B$21,1,0)*'Оценка сложности задач'!$G$21)+(IF(C8='Оценка сложности задач'!$A$22,1,0)*IF(D8='Оценка сложности задач'!$B$22,1,0)*'Оценка сложности задач'!$G$22)+(IF(C8='Оценка сложности задач'!$A$23,1,0)*IF(D8='Оценка сложности задач'!$B$23,1,0)*'Оценка сложности задач'!$G$23)+(IF(C8='Оценка сложности задач'!$A$24,1,0)*IF(D8='Оценка сложности задач'!$B$24,1,0)*'Оценка сложности задач'!$G$24)+(IF(C8='Оценка сложности задач'!$A$25,1,0)*IF(D8='Оценка сложности задач'!$B$25,1,0)*'Оценка сложности задач'!$G$25)+(IF(C8='Оценка сложности задач'!$A$26,1,0)*IF(D8='Оценка сложности задач'!$B$26,1,0)*'Оценка сложности задач'!$G$26)+(IF(C8='Оценка сложности задач'!$A$27,1,0)*IF(D8='Оценка сложности задач'!$B$27,1,0)*'Оценка сложности задач'!$G$27)+(IF(C8='Оценка сложности задач'!$A$28,1,0)*IF(D8='Оценка сложности задач'!$B$28,1,0)*'Оценка сложности задач'!$G$28)+(IF(C8='Оценка сложности задач'!$A$29,1,0)*IF(D8='Оценка сложности задач'!$B$29,1,0)*'Оценка сложности задач'!$G$29)+(IF(C8='Оценка сложности задач'!$A$30,1,0)*IF(D8='Оценка сложности задач'!$B$30,1,0)*'Оценка сложности задач'!$G$30)+(IF(C8='Оценка сложности задач'!$A$31,1,0)*IF(D8='Оценка сложности задач'!$B$31,1,0)*'Оценка сложности задач'!$G$31)+(IF(C8='Оценка сложности задач'!$A$32,1,0)*IF(D8='Оценка сложности задач'!$B$32,1,0)*'Оценка сложности задач'!$G$32)+(IF(C8='Оценка сложности задач'!$A$33,1,0)*IF(D8='Оценка сложности задач'!$B$33,1,0)*'Оценка сложности задач'!$G$33)+(IF(C8='Оценка сложности задач'!$A$34,1,0)*IF(D8='Оценка сложности задач'!$B$34,1,0)*'Оценка сложности задач'!$G$34)+(IF(C8='Оценка сложности задач'!$A$35,1,0)*IF(D8='Оценка сложности задач'!$B$35,1,0)*'Оценка сложности задач'!$G$35)+(IF(C8='Оценка сложности задач'!$A$36,1,0)*IF(D8='Оценка сложности задач'!$B$36,1,0)*'Оценка сложности задач'!$G$36)+(IF(C8='Оценка сложности задач'!$A$37,1,0)*IF(D8='Оценка сложности задач'!$B$37,1,0)*'Оценка сложности задач'!$G$37)+(IF(C8='Оценка сложности задач'!$A$38,1,0)*IF(D8='Оценка сложности задач'!$B$38,1,0)*'Оценка сложности задач'!$G$38)+(IF(C8='Оценка сложности задач'!$A$39,1,0)*IF(D8='Оценка сложности задач'!$B$39,1,0)*'Оценка сложности задач'!$G$39)+(IF(C8='Оценка сложности задач'!$A$40,1,0)*IF(D8='Оценка сложности задач'!$B$40,1,0)*'Оценка сложности задач'!$G$40) -> 6
A9: 6 | B9: Проверка на дубликаты заявки (Message-ID/тема/отправитель) | C9: Базы данных | D9: Средняя | E9: =(IF(C9='Оценка сложности задач'!$A$2,1,0)*IF(D9='Оценка сложности задач'!$B$2,1,0)*'Оценка сложности задач'!$G$2)+(IF(C9='Оценка сложности задач'!$A$3,1,0)*IF(D9='Оценка сложности задач'!$B$3,1,0)*'Оценка сложности задач'!$G$3)+(IF(C9='Оценка сложности задач'!$A$4,1,0)*IF(D9='Оценка сложности задач'!$B$4,1,0)*'Оценка сложности задач'!$G$4)+(IF(C9='Оценка сложности задач'!$A$5,1,0)*IF(D9='Оценка сложности задач'!$B$5,1,0)*'Оценка сложности задач'!$G$5)+(IF(C9='Оценка сложности задач'!$A$6,1,0)*IF(D9='Оценка сложности задач'!$B$6,1,0)*'Оценка сложности задач'!$G$6)+(IF(C9='Оценка сложности задач'!$A$7,1,0)*IF(D9='Оценка сложности задач'!$B$7,1,0)*'Оценка сложности задач'!$G$7)+(IF(C9='Оценка сложности задач'!$A$8,1,0)*IF(D9='Оценка сложности задач'!$B$8,1,0)*'Оценка сложности задач'!$G$8)+(IF(C9='Оценка сложности задач'!$A$10,1,0)*IF(D9='Оценка сложности задач'!$B$10,1,0)*'Оценка сложности задач'!$G$10)+(IF(C9='Оценка сложности задач'!$A$9,1,0)*IF(D9='Оценка сложности задач'!$B$9,1,0)*'Оценка сложности задач'!$G$9)+ (IF(C9='Оценка сложности задач'!$A$11,1,0)*IF(D9='Оценка сложности задач'!$B$11,1,0)*'Оценка сложности задач'!$G$11) + (IF(C9='Оценка сложности задач'!$A$12,1,0)*IF(D9='Оценка сложности задач'!$B$12,1,0)*'Оценка сложности задач'!$G$12) + (IF(C9='Оценка сложности задач'!$A$13,1,0)*IF(D9='Оценка сложности задач'!$B$13,1,0)*'Оценка сложности задач'!$G$13) + (IF(C9='Оценка сложности задач'!$A$14,1,0)*IF(D9='Оценка сложности задач'!$B$14,1,0)*'Оценка сложности задач'!$G$14) + (IF(C9='Оценка сложности задач'!$A$15,1,0)*IF(D9='Оценка сложности задач'!$B$15,1,0)*'Оценка сложности задач'!$G$15) + (IF(C9='Оценка сложности задач'!$A$16,1,0)*IF(D9='Оценка сложности задач'!$B$16,1,0)*'Оценка сложности задач'!$G$16) + (IF(C9='Оценка сложности задач'!$A$17,1,0)*IF(D9='Оценка сложности задач'!$B$17,1,0)*'Оценка сложности задач'!$G$17) + (IF(C9='Оценка сложности задач'!$A$18,1,0)*IF(D9='Оценка сложности задач'!$B$18,1,0)*'Оценка сложности задач'!$G$18) + (IF(C9='Оценка сложности задач'!$A$19,1,0)*IF(D9='Оценка сложности задач'!$B$19,1,0)*'Оценка сложности задач'!$G$19)+(IF(C9='Оценка сложности задач'!$A$20,1,0)*IF(D9='Оценка сложности задач'!$B$20,1,0)*'Оценка сложности задач'!$G$20)+(IF(C9='Оценка сложности задач'!$A$21,1,0)*IF(D9='Оценка сложности задач'!$B$21,1,0)*'Оценка сложности задач'!$G$21)+(IF(C9='Оценка сложности задач'!$A$22,1,0)*IF(D9='Оценка сложности задач'!$B$22,1,0)*'Оценка сложности задач'!$G$22)+(IF(C9='Оценка сложности задач'!$A$23,1,0)*IF(D9='Оценка сложности задач'!$B$23,1,0)*'Оценка сложности задач'!$G$23)+(IF(C9='Оценка сложности задач'!$A$24,1,0)*IF(D9='Оценка сложности задач'!$B$24,1,0)*'Оценка сложности задач'!$G$24)+(IF(C9='Оценка сложности задач'!$A$25,1,0)*IF(D9='Оценка сложности задач'!$B$25,1,0)*'Оценка сложности задач'!$G$25)+(IF(C9='Оценка сложности задач'!$A$26,1,0)*IF(D9='Оценка сложности задач'!$B$26,1,0)*'Оценка сложности задач'!$G$26)+(IF(C9='Оценка сложности задач'!$A$27,1,0)*IF(D9='Оценка сложности задач'!$B$27,1,0)*'Оценка сложности задач'!$G$27)+(IF(C9='Оценка сложности задач'!$A$28,1,0)*IF(D9='Оценка сложности задач'!$B$28,1,0)*'Оценка сложности задач'!$G$28)+(IF(C9='Оценка сложности задач'!$A$29,1,0)*IF(D9='Оценка сложности задач'!$B$29,1,0)*'Оценка сложности задач'!$G$29)+(IF(C9='Оценка сложности задач'!$A$30,1,0)*IF(D9='Оценка сложности задач'!$B$30,1,0)*'Оценка сложности задач'!$G$30)+(IF(C9='Оценка сложности задач'!$A$31,1,0)*IF(D9='Оценка сложности задач'!$B$31,1,0)*'Оценка сложности задач'!$G$31)+(IF(C9='Оценка сложности задач'!$A$32,1,0)*IF(D9='Оценка сложности задач'!$B$32,1,0)*'Оценка сложности задач'!$G$32)+(IF(C9='Оценка сложности задач'!$A$33,1,0)*IF(D9='Оценка сложности задач'!$B$33,1,0)*'Оценка сложности задач'!$G$33)+(IF(C9='Оценка сложности задач'!$A$34,1,0)*IF(D9='Оценка сложности задач'!$B$34,1,0)*'Оценка сложности задач'!$G$34)+(IF(C9='Оценка сложности задач'!$A$35,1,0)*IF(D9='Оценка сложности задач'!$B$35,1,0)*'Оценка сложности задач'!$G$35)+(IF(C9='Оценка сложности задач'!$A$36,1,0)*IF(D9='Оценка сложности задач'!$B$36,1,0)*'Оценка сложности задач'!$G$36)+(IF(C9='Оценка сложности задач'!$A$37,1,0)*IF(D9='Оценка сложности задач'!$B$37,1,0)*'Оценка сложности задач'!$G$37)+(IF(C9='Оценка сложности задач'!$A$38,1,0)*IF(D9='Оценка сложности задач'!$B$38,1,0)*'Оценка сложности задач'!$G$38)+(IF(C9='Оценка сложности задач'!$A$39,1,0)*IF(D9='Оценка сложности задач'!$B$39,1,0)*'Оценка сложности задач'!$G$39)+(IF(C9='Оценка сложности задач'!$A$40,1,0)*IF(D9='Оценка сложности задач'!$B$40,1,0)*'Оценка сложности задач'!$G$40) -> 32
A10: 7 | B10: Создание задачи/карточки в YouGile через API | C10: REST/SOAP | D10: Средняя | E10: =(IF(C10='Оценка сложности задач'!$A$2,1,0)*IF(D10='Оценка сложности задач'!$B$2,1,0)*'Оценка сложности задач'!$G$2)+(IF(C10='Оценка сложности задач'!$A$3,1,0)*IF(D10='Оценка сложности задач'!$B$3,1,0)*'Оценка сложности задач'!$G$3)+(IF(C10='Оценка сложности задач'!$A$4,1,0)*IF(D10='Оценка сложности задач'!$B$4,1,0)*'Оценка сложности задач'!$G$4)+(IF(C10='Оценка сложности задач'!$A$5,1,0)*IF(D10='Оценка сложности задач'!$B$5,1,0)*'Оценка сложности задач'!$G$5)+(IF(C10='Оценка сложности задач'!$A$6,1,0)*IF(D10='Оценка сложности задач'!$B$6,1,0)*'Оценка сложности задач'!$G$6)+(IF(C10='Оценка сложности задач'!$A$7,1,0)*IF(D10='Оценка сложности задач'!$B$7,1,0)*'Оценка сложности задач'!$G$7)+(IF(C10='Оценка сложности задач'!$A$8,1,0)*IF(D10='Оценка сложности задач'!$B$8,1,0)*'Оценка сложности задач'!$G$8)+(IF(C10='Оценка сложности задач'!$A$10,1,0)*IF(D10='Оценка сложности задач'!$B$10,1,0)*'Оценка сложности задач'!$G$10)+(IF(C10='Оценка сложности задач'!$A$9,1,0)*IF(D10='Оценка сложности задач'!$B$9,1,0)*'Оценка сложности задач'!$G$9)+ (IF(C10='Оценка сложности задач'!$A$11,1,0)*IF(D10='Оценка сложности задач'!$B$11,1,0)*'Оценка сложности задач'!$G$11) + (IF(C10='Оценка сложности задач'!$A$12,1,0)*IF(D10='Оценка сложности задач'!$B$12,1,0)*'Оценка сложности задач'!$G$12) + (IF(C10='Оценка сложности задач'!$A$13,1,0)*IF(D10='Оценка сложности задач'!$B$13,1,0)*'Оценка сложности задач'!$G$13) + (IF(C10='Оценка сложности задач'!$A$14,1,0)*IF(D10='Оценка сложности задач'!$B$14,1,0)*'Оценка сложности задач'!$G$14) + (IF(C10='Оценка сложности задач'!$A$15,1,0)*IF(D10='Оценка сложности задач'!$B$15,1,0)*'Оценка сложности задач'!$G$15) + (IF(C10='Оценка сложности задач'!$A$16,1,0)*IF(D10='Оценка сложности задач'!$B$16,1,0)*'Оценка сложности задач'!$G$16) + (IF(C10='Оценка сложности задач'!$A$17,1,0)*IF(D10='Оценка сложности задач'!$B$17,1,0)*'Оценка сложности задач'!$G$17) + (IF(C10='Оценка сложности задач'!$A$18,1,0)*IF(D10='Оценка сложности задач'!$B$18,1,0)*'Оценка сложности задач'!$G$18) + (IF(C10='Оценка сложности задач'!$A$19,1,0)*IF(D10='Оценка сложности задач'!$B$19,1,0)*'Оценка сложности задач'!$G$19)+(IF(C10='Оценка сложности задач'!$A$20,1,0)*IF(D10='Оценка сложности задач'!$B$20,1,0)*'Оценка сложности задач'!$G$20)+(IF(C10='Оценка сложности задач'!$A$21,1,0)*IF(D10='Оценка сложности задач'!$B$21,1,0)*'Оценка сложности задач'!$G$21)+(IF(C10='Оценка сложности задач'!$A$22,1,0)*IF(D10='Оценка сложности задач'!$B$22,1,0)*'Оценка сложности задач'!$G$22)+(IF(C10='Оценка сложности задач'!$A$23,1,0)*IF(D10='Оценка сложности задач'!$B$23,1,0)*'Оценка сложности задач'!$G$23)+(IF(C10='Оценка сложности задач'!$A$24,1,0)*IF(D10='Оценка сложности задач'!$B$24,1,0)*'Оценка сложности задач'!$G$24)+(IF(C10='Оценка сложности задач'!$A$25,1,0)*IF(D10='Оценка сложности задач'!$B$25,1,0)*'Оценка сложности задач'!$G$25)+(IF(C10='Оценка сложности задач'!$A$26,1,0)*IF(D10='Оценка сложности задач'!$B$26,1,0)*'Оценка сложности задач'!$G$26)+(IF(C10='Оценка сложности задач'!$A$27,1,0)*IF(D10='Оценка сложности задач'!$B$27,1,0)*'Оценка сложности задач'!$G$27)+(IF(C10='Оценка сложности задач'!$A$28,1,0)*IF(D10='Оценка сложности задач'!$B$28,1,0)*'Оценка сложности задач'!$G$28)+(IF(C10='Оценка сложности задач'!$A$29,1,0)*IF(D10='Оценка сложности задач'!$B$29,1,0)*'Оценка сложности задач'!$G$29)+(IF(C10='Оценка сложности задач'!$A$30,1,0)*IF(D10='Оценка сложности задач'!$B$30,1,0)*'Оценка сложности задач'!$G$30)+(IF(C10='Оценка сложности задач'!$A$31,1,0)*IF(D10='Оценка сложности задач'!$B$31,1,0)*'Оценка сложности задач'!$G$31)+(IF(C10='Оценка сложности задач'!$A$32,1,0)*IF(D10='Оценка сложности задач'!$B$32,1,0)*'Оценка сложности задач'!$G$32)+(IF(C10='Оценка сложности задач'!$A$33,1,0)*IF(D10='Оценка сложности задач'!$B$33,1,0)*'Оценка сложности задач'!$G$33)+(IF(C10='Оценка сложности задач'!$A$34,1,0)*IF(D10='Оценка сложности задач'!$B$34,1,0)*'Оценка сложности задач'!$G$34)+(IF(C10='Оценка сложности задач'!$A$35,1,0)*IF(D10='Оценка сложности задач'!$B$35,1,0)*'Оценка сложности задач'!$G$35)+(IF(C10='Оценка сложности задач'!$A$36,1,0)*IF(D10='Оценка сложности задач'!$B$36,1,0)*'Оценка сложности задач'!$G$36)+(IF(C10='Оценка сложности задач'!$A$37,1,0)*IF(D10='Оценка сложности задач'!$B$37,1,0)*'Оценка сложности задач'!$G$37)+(IF(C10='Оценка сложности задач'!$A$38,1,0)*IF(D10='Оценка сложности задач'!$B$38,1,0)*'Оценка сложности задач'!$G$38)+(IF(C10='Оценка сложности задач'!$A$39,1,0)*IF(D10='Оценка сложности задач'!$B$39,1,0)*'Оценка сложности задач'!$G$39)+(IF(C10='Оценка сложности задач'!$A$40,1,0)*IF(D10='Оценка сложности задач'!$B$40,1,0)*'Оценка сложности задач'!$G$40) -> 32
A11: 8 | B11: Заполнение полей задачи: описание, контакты, теги, приоритет | C11: Интеграции | D11: Средняя | E11: =(IF(C11='Оценка сложности задач'!$A$2,1,0)*IF(D11='Оценка сложности задач'!$B$2,1,0)*'Оценка сложности задач'!$G$2)+(IF(C11='Оценка сложности задач'!$A$3,1,0)*IF(D11='Оценка сложности задач'!$B$3,1,0)*'Оценка сложности задач'!$G$3)+(IF(C11='Оценка сложности задач'!$A$4,1,0)*IF(D11='Оценка сложности задач'!$B$4,1,0)*'Оценка сложности задач'!$G$4)+(IF(C11='Оценка сложности задач'!$A$5,1,0)*IF(D11='Оценка сложности задач'!$B$5,1,0)*'Оценка сложности задач'!$G$5)+(IF(C11='Оценка сложности задач'!$A$6,1,0)*IF(D11='Оценка сложности задач'!$B$6,1,0)*'Оценка сложности задач'!$G$6)+(IF(C11='Оценка сложности задач'!$A$7,1,0)*IF(D11='Оценка сложности задач'!$B$7,1,0)*'Оценка сложности задач'!$G$7)+(IF(C11='Оценка сложности задач'!$A$8,1,0)*IF(D11='Оценка сложности задач'!$B$8,1,0)*'Оценка сложности задач'!$G$8)+(IF(C11='Оценка сложности задач'!$A$10,1,0)*IF(D11='Оценка сложности задач'!$B$10,1,0)*'Оценка сложности задач'!$G$10)+(IF(C11='Оценка сложности задач'!$A$9,1,0)*IF(D11='Оценка сложности задач'!$B$9,1,0)*'Оценка сложности задач'!$G$9)+ (IF(C11='Оценка сложности задач'!$A$11,1,0)*IF(D11='Оценка сложности задач'!$B$11,1,0)*'Оценка сложности задач'!$G$11) + (IF(C11='Оценка сложности задач'!$A$12,1,0)*IF(D11='Оценка сложности задач'!$B$12,1,0)*'Оценка сложности задач'!$G$12) + (IF(C11='Оценка сложности задач'!$A$13,1,0)*IF(D11='Оценка сложности задач'!$B$13,1,0)*'Оценка сложности задач'!$G$13) + (IF(C11='Оценка сложности задач'!$A$14,1,0)*IF(D11='Оценка сложности задач'!$B$14,1,0)*'Оценка сложности задач'!$G$14) + (IF(C11='Оценка сложности задач'!$A$15,1,0)*IF(D11='Оценка сложности задач'!$B$15,1,0)*'Оценка сложности задач'!$G$15) + (IF(C11='Оценка сложности задач'!$A$16,1,0)*IF(D11='Оценка сложности задач'!$B$16,1,0)*'Оценка сложности задач'!$G$16) + (IF(C11='Оценка сложности задач'!$A$17,1,0)*IF(D11='Оценка сложности задач'!$B$17,1,0)*'Оценка сложности задач'!$G$17) + (IF(C11='Оценка сложности задач'!$A$18,1,0)*IF(D11='Оценка сложности задач'!$B$18,1,0)*'Оценка сложности задач'!$G$18) + (IF(C11='Оценка сложности задач'!$A$19,1,0)*IF(D11='Оценка сложности задач'!$B$19,1,0)*'Оценка сложности задач'!$G$19)+(IF(C11='Оценка сложности задач'!$A$20,1,0)*IF(D11='Оценка сложности задач'!$B$20,1,0)*'Оценка сложности задач'!$G$20)+(IF(C11='Оценка сложности задач'!$A$21,1,0)*IF(D11='Оценка сложности задач'!$B$21,1,0)*'Оценка сложности задач'!$G$21)+(IF(C11='Оценка сложности задач'!$A$22,1,0)*IF(D11='Оценка сложности задач'!$B$22,1,0)*'Оценка сложности задач'!$G$22)+(IF(C11='Оценка сложности задач'!$A$23,1,0)*IF(D11='Оценка сложности задач'!$B$23,1,0)*'Оценка сложности задач'!$G$23)+(IF(C11='Оценка сложности задач'!$A$24,1,0)*IF(D11='Оценка сложности задач'!$B$24,1,0)*'Оценка сложности задач'!$G$24)+(IF(C11='Оценка сложности задач'!$A$25,1,0)*IF(D11='Оценка сложности задач'!$B$25,1,0)*'Оценка сложности задач'!$G$25)+(IF(C11='Оценка сложности задач'!$A$26,1,0)*IF(D11='Оценка сложности задач'!$B$26,1,0)*'Оценка сложности задач'!$G$26)+(IF(C11='Оценка сложности задач'!$A$27,1,0)*IF(D11='Оценка сложности задач'!$B$27,1,0)*'Оценка сложности задач'!$G$27)+(IF(C11='Оценка сложности задач'!$A$28,1,0)*IF(D11='Оценка сложности задач'!$B$28,1,0)*'Оценка сложности задач'!$G$28)+(IF(C11='Оценка сложности задач'!$A$29,1,0)*IF(D11='Оценка сложности задач'!$B$29,1,0)*'Оценка сложности задач'!$G$29)+(IF(C11='Оценка сложности задач'!$A$30,1,0)*IF(D11='Оценка сложности задач'!$B$30,1,0)*'Оценка сложности задач'!$G$30)+(IF(C11='Оценка сложности задач'!$A$31,1,0)*IF(D11='Оценка сложности задач'!$B$31,1,0)*'Оценка сложности задач'!$G$31)+(IF(C11='Оценка сложности задач'!$A$32,1,0)*IF(D11='Оценка сложности задач'!$B$32,1,0)*'Оценка сложности задач'!$G$32)+(IF(C11='Оценка сложности задач'!$A$33,1,0)*IF(D11='Оценка сложности задач'!$B$33,1,0)*'Оценка сложности задач'!$G$33)+(IF(C11='Оценка сложности задач'!$A$34,1,0)*IF(D11='Оценка сложности задач'!$B$34,1,0)*'Оценка сложности задач'!$G$34)+(IF(C11='Оценка сложности задач'!$A$35,1,0)*IF(D11='Оценка сложности задач'!$B$35,1,0)*'Оценка сложности задач'!$G$35)+(IF(C11='Оценка сложности задач'!$A$36,1,0)*IF(D11='Оценка сложности задач'!$B$36,1,0)*'Оценка сложности задач'!$G$36)+(IF(C11='Оценка сложности задач'!$A$37,1,0)*IF(D11='Оценка сложности задач'!$B$37,1,0)*'Оценка сложности задач'!$G$37)+(IF(C11='Оценка сложности задач'!$A$38,1,0)*IF(D11='Оценка сложности задач'!$B$38,1,0)*'Оценка сложности задач'!$G$38)+(IF(C11='Оценка сложности задач'!$A$39,1,0)*IF(D11='Оценка сложности задач'!$B$39,1,0)*'Оценка сложности задач'!$G$39)+(IF(C11='Оценка сложности задач'!$A$40,1,0)*IF(D11='Оценка сложности задач'!$B$40,1,0)*'Оценка сложности задач'!$G$40) -> 32
A12: 9 | B12: Прикрепление вложений к задаче (если есть) | C12: Файлы/Папки/FTP | D12: Средняя | E12: =(IF(C12='Оценка сложности задач'!$A$2,1,0)*IF(D12='Оценка сложности задач'!$B$2,1,0)*'Оценка сложности задач'!$G$2)+(IF(C12='Оценка сложности задач'!$A$3,1,0)*IF(D12='Оценка сложности задач'!$B$3,1,0)*'Оценка сложности задач'!$G$3)+(IF(C12='Оценка сложности задач'!$A$4,1,0)*IF(D12='Оценка сложности задач'!$B$4,1,0)*'Оценка сложности задач'!$G$4)+(IF(C12='Оценка сложности задач'!$A$5,1,0)*IF(D12='Оценка сложности задач'!$B$5,1,0)*'Оценка сложности задач'!$G$5)+(IF(C12='Оценка сложности задач'!$A$6,1,0)*IF(D12='Оценка сложности задач'!$B$6,1,0)*'Оценка сложности задач'!$G$6)+(IF(C12='Оценка сложности задач'!$A$7,1,0)*IF(D12='Оценка сложности задач'!$B$7,1,0)*'Оценка сложности задач'!$G$7)+(IF(C12='Оценка сложности задач'!$A$8,1,0)*IF(D12='Оценка сложности задач'!$B$8,1,0)*'Оценка сложности задач'!$G$8)+(IF(C12='Оценка сложности задач'!$A$10,1,0)*IF(D12='Оценка сложности задач'!$B$10,1,0)*'Оценка сложности задач'!$G$10)+(IF(C12='Оценка сложности задач'!$A$9,1,0)*IF(D12='Оценка сложности задач'!$B$9,1,0)*'Оценка сложности задач'!$G$9)+ (IF(C12='Оценка сложности задач'!$A$11,1,0)*IF(D12='Оценка сложности задач'!$B$11,1,0)*'Оценка сложности задач'!$G$11) + (IF(C12='Оценка сложности задач'!$A$12,1,0)*IF(D12='Оценка сложности задач'!$B$12,1,0)*'Оценка сложности задач'!$G$12) + (IF(C12='Оценка сложности задач'!$A$13,1,0)*IF(D12='Оценка сложности задач'!$B$13,1,0)*'Оценка сложности задач'!$G$13) + (IF(C12='Оценка сложности задач'!$A$14,1,0)*IF(D12='Оценка сложности задач'!$B$14,1,0)*'Оценка сложности задач'!$G$14) + (IF(C12='Оценка сложности задач'!$A$15,1,0)*IF(D12='Оценка сложности задач'!$B$15,1,0)*'Оценка сложности задач'!$G$15) + (IF(C12='Оценка сложности задач'!$A$16,1,0)*IF(D12='Оценка сложности задач'!$B$16,1,0)*'Оценка сложности задач'!$G$16) + (IF(C12='Оценка сложности задач'!$A$17,1,0)*IF(D12='Оценка сложности задач'!$B$17,1,0)*'Оценка сложности задач'!$G$17) + (IF(C12='Оценка сложности задач'!$A$18,1,0)*IF(D12='Оценка сложности задач'!$B$18,1,0)*'Оценка сложности задач'!$G$18) + (IF(C12='Оценка сложности задач'!$A$19,1,0)*IF(D12='Оценка сложности задач'!$B$19,1,0)*'Оценка сложности задач'!$G$19)+(IF(C12='Оценка сложности задач'!$A$20,1,0)*IF(D12='Оценка сложности задач'!$B$20,1,0)*'Оценка сложности задач'!$G$20)+(IF(C12='Оценка сложности задач'!$A$21,1,0)*IF(D12='Оценка сложности задач'!$B$21,1,0)*'Оценка сложности задач'!$G$21)+(IF(C12='Оценка сложности задач'!$A$22,1,0)*IF(D12='Оценка сложности задач'!$B$22,1,0)*'Оценка сложности задач'!$G$22)+(IF(C12='Оценка сложности задач'!$A$23,1,0)*IF(D12='Оценка сложности задач'!$B$23,1,0)*'Оценка сложности задач'!$G$23)+(IF(C12='Оценка сложности задач'!$A$24,1,0)*IF(D12='Оценка сложности задач'!$B$24,1,0)*'Оценка сложности задач'!$G$24)+(IF(C12='Оценка сложности задач'!$A$25,1,0)*IF(D12='Оценка сложности задач'!$B$25,1,0)*'Оценка сложности задач'!$G$25)+(IF(C12='Оценка сложности задач'!$A$26,1,0)*IF(D12='Оценка сложности задач'!$B$26,1,0)*'Оценка сложности задач'!$G$26)+(IF(C12='Оценка сложности задач'!$A$27,1,0)*IF(D12='Оценка сложности задач'!$B$27,1,0)*'Оценка сложности задач'!$G$27)+(IF(C12='Оценка сложности задач'!$A$28,1,0)*IF(D12='Оценка сложности задач'!$B$28,1,0)*'Оценка сложности задач'!$G$28)+(IF(C12='Оценка сложности задач'!$A$29,1,0)*IF(D12='Оценка сложности задач'!$B$29,1,0)*'Оценка сложности задач'!$G$29)+(IF(C12='Оценка сложности задач'!$A$30,1,0)*IF(D12='Оценка сложности задач'!$B$30,1,0)*'Оценка сложности задач'!$G$30)+(IF(C12='Оценка сложности задач'!$A$31,1,0)*IF(D12='Оценка сложности задач'!$B$31,1,0)*'Оценка сложности задач'!$G$31)+(IF(C12='Оценка сложности задач'!$A$32,1,0)*IF(D12='Оценка сложности задач'!$B$32,1,0)*'Оценка сложности задач'!$G$32)+(IF(C12='Оценка сложности задач'!$A$33,1,0)*IF(D12='Оценка сложности задач'!$B$33,1,0)*'Оценка сложности задач'!$G$33)+(IF(C12='Оценка сложности задач'!$A$34,1,0)*IF(D12='Оценка сложности задач'!$B$34,1,0)*'Оценка сложности задач'!$G$34)+(IF(C12='Оценка сложности задач'!$A$35,1,0)*IF(D12='Оценка сложности задач'!$B$35,1,0)*'Оценка сложности задач'!$G$35)+(IF(C12='Оценка сложности задач'!$A$36,1,0)*IF(D12='Оценка сложности задач'!$B$36,1,0)*'Оценка сложности задач'!$G$36)+(IF(C12='Оценка сложности задач'!$A$37,1,0)*IF(D12='Оценка сложности задач'!$B$37,1,0)*'Оценка сложности задач'!$G$37)+(IF(C12='Оценка сложности задач'!$A$38,1,0)*IF(D12='Оценка сложности задач'!$B$38,1,0)*'Оценка сложности задач'!$G$38)+(IF(C12='Оценка сложности задач'!$A$39,1,0)*IF(D12='Оценка сложности задач'!$B$39,1,0)*'Оценка сложности задач'!$G$39)+(IF(C12='Оценка сложности задач'!$A$40,1,0)*IF(D12='Оценка сложности задач'!$B$40,1,0)*'Оценка сложности задач'!$G$40) -> 11
A13: 10 | B13: Уведомление менеджера о созданной задаче | C13: Почта/Outlook | D13: Легкая | E13: =(IF(C13='Оценка сложности задач'!$A$2,1,0)*IF(D13='Оценка сложности задач'!$B$2,1,0)*'Оценка сложности задач'!$G$2)+(IF(C13='Оценка сложности задач'!$A$3,1,0)*IF(D13='Оценка сложности задач'!$B$3,1,0)*'Оценка сложности задач'!$G$3)+(IF(C13='Оценка сложности задач'!$A$4,1,0)*IF(D13='Оценка сложности задач'!$B$4,1,0)*'Оценка сложности задач'!$G$4)+(IF(C13='Оценка сложности задач'!$A$5,1,0)*IF(D13='Оценка сложности задач'!$B$5,1,0)*'Оценка сложности задач'!$G$5)+(IF(C13='Оценка сложности задач'!$A$6,1,0)*IF(D13='Оценка сложности задач'!$B$6,1,0)*'Оценка сложности задач'!$G$6)+(IF(C13='Оценка сложности задач'!$A$7,1,0)*IF(D13='Оценка сложности задач'!$B$7,1,0)*'Оценка сложности задач'!$G$7)+(IF(C13='Оценка сложности задач'!$A$8,1,0)*IF(D13='Оценка сложности задач'!$B$8,1,0)*'Оценка сложности задач'!$G$8)+(IF(C13='Оценка сложности задач'!$A$10,1,0)*IF(D13='Оценка сложности задач'!$B$10,1,0)*'Оценка сложности задач'!$G$10)+(IF(C13='Оценка сложности задач'!$A$9,1,0)*IF(D13='Оценка сложности задач'!$B$9,1,0)*'Оценка сложности задач'!$G$9)+ (IF(C13='Оценка сложности задач'!$A$11,1,0)*IF(D13='Оценка сложности задач'!$B$11,1,0)*'Оценка сложности задач'!$G$11) + (IF(C13='Оценка сложности задач'!$A$12,1,0)*IF(D13='Оценка сложности задач'!$B$12,1,0)*'Оценка сложности задач'!$G$12) + (IF(C13='Оценка сложности задач'!$A$13,1,0)*IF(D13='Оценка сложности задач'!$B$13,1,0)*'Оценка сложности задач'!$G$13) + (IF(C13='Оценка сложности задач'!$A$14,1,0)*IF(D13='Оценка сложности задач'!$B$14,1,0)*'Оценка сложности задач'!$G$14) + (IF(C13='Оценка сложности задач'!$A$15,1,0)*IF(D13='Оценка сложности задач'!$B$15,1,0)*'Оценка сложности задач'!$G$15) + (IF(C13='Оценка сложности задач'!$A$16,1,0)*IF(D13='Оценка сложности задач'!$B$16,1,0)*'Оценка сложности задач'!$G$16) + (IF(C13='Оценка сложности задач'!$A$17,1,0)*IF(D13='Оценка сложности задач'!$B$17,1,0)*'Оценка сложности задач'!$G$17) + (IF(C13='Оценка сложности задач'!$A$18,1,0)*IF(D13='Оценка сложности задач'!$B$18,1,0)*'Оценка сложности задач'!$G$18) + (IF(C13='Оценка сложности задач'!$A$19,1,0)*IF(D13='Оценка сложности задач'!$B$19,1,0)*'Оценка сложности задач'!$G$19)+(IF(C13='Оценка сложности задач'!$A$20,1,0)*IF(D13='Оценка сложности задач'!$B$20,1,0)*'Оценка сложности задач'!$G$20)+(IF(C13='Оценка сложности задач'!$A$21,1,0)*IF(D13='Оценка сложности задач'!$B$21,1,0)*'Оценка сложности задач'!$G$21)+(IF(C13='Оценка сложности задач'!$A$22,1,0)*IF(D13='Оценка сложности задач'!$B$22,1,0)*'Оценка сложности задач'!$G$22)+(IF(C13='Оценка сложности задач'!$A$23,1,0)*IF(D13='Оценка сложности задач'!$B$23,1,0)*'Оценка сложности задач'!$G$23)+(IF(C13='Оценка сложности задач'!$A$24,1,0)*IF(D13='Оценка сложности задач'!$B$24,1,0)*'Оценка сложности задач'!$G$24)+(IF(C13='Оценка сложности задач'!$A$25,1,0)*IF(D13='Оценка сложности задач'!$B$25,1,0)*'Оценка сложности задач'!$G$25)+(IF(C13='Оценка сложности задач'!$A$26,1,0)*IF(D13='Оценка сложности задач'!$B$26,1,0)*'Оценка сложности задач'!$G$26)+(IF(C13='Оценка сложности задач'!$A$27,1,0)*IF(D13='Оценка сложности задач'!$B$27,1,0)*'Оценка сложности задач'!$G$27)+(IF(C13='Оценка сложности задач'!$A$28,1,0)*IF(D13='Оценка сложности задач'!$B$28,1,0)*'Оценка сложности задач'!$G$28)+(IF(C13='Оценка сложности задач'!$A$29,1,0)*IF(D13='Оценка сложности задач'!$B$29,1,0)*'Оценка сложности задач'!$G$29)+(IF(C13='Оценка сложности задач'!$A$30,1,0)*IF(D13='Оценка сложности задач'!$B$30,1,0)*'Оценка сложности задач'!$G$30)+(IF(C13='Оценка сложности задач'!$A$31,1,0)*IF(D13='Оценка сложности задач'!$B$31,1,0)*'Оценка сложности задач'!$G$31)+(IF(C13='Оценка сложности задач'!$A$32,1,0)*IF(D13='Оценка сложности задач'!$B$32,1,0)*'Оценка сложности задач'!$G$32)+(IF(C13='Оценка сложности задач'!$A$33,1,0)*IF(D13='Оценка сложности задач'!$B$33,1,0)*'Оценка сложности задач'!$G$33)+(IF(C13='Оценка сложности задач'!$A$34,1,0)*IF(D13='Оценка сложности задач'!$B$34,1,0)*'Оценка сложности задач'!$G$34)+(IF(C13='Оценка сложности задач'!$A$35,1,0)*IF(D13='Оценка сложности задач'!$B$35,1,0)*'Оценка сложности задач'!$G$35)+(IF(C13='Оценка сложности задач'!$A$36,1,0)*IF(D13='Оценка сложности задач'!$B$36,1,0)*'Оценка сложности задач'!$G$36)+(IF(C13='Оценка сложности задач'!$A$37,1,0)*IF(D13='Оценка сложности задач'!$B$37,1,0)*'Оценка сложности задач'!$G$37)+(IF(C13='Оценка сложности задач'!$A$38,1,0)*IF(D13='Оценка сложности задач'!$B$38,1,0)*'Оценка сложности задач'!$G$38)+(IF(C13='Оценка сложности задач'!$A$39,1,0)*IF(D13='Оценка сложности задач'!$B$39,1,0)*'Оценка сложности задач'!$G$39)+(IF(C13='Оценка сложности задач'!$A$40,1,0)*IF(D13='Оценка сложности задач'!$B$40,1,0)*'Оценка сложности задач'!$G$40) -> 6
A14: 11 | B14: Логирование результата (журнал) и пометка письма | C14: Базы данных | D14: Легкая | E14: =(IF(C14='Оценка сложности задач'!$A$2,1,0)*IF(D14='Оценка сложности задач'!$B$2,1,0)*'Оценка сложности задач'!$G$2)+(IF(C14='Оценка сложности задач'!$A$3,1,0)*IF(D14='Оценка сложности задач'!$B$3,1,0)*'Оценка сложности задач'!$G$3)+(IF(C14='Оценка сложности задач'!$A$4,1,0)*IF(D14='Оценка сложности задач'!$B$4,1,0)*'Оценка сложности задач'!$G$4)+(IF(C14='Оценка сложности задач'!$A$5,1,0)*IF(D14='Оценка сложности задач'!$B$5,1,0)*'Оценка сложности задач'!$G$5)+(IF(C14='Оценка сложности задач'!$A$6,1,0)*IF(D14='Оценка сложности задач'!$B$6,1,0)*'Оценка сложности задач'!$G$6)+(IF(C14='Оценка сложности задач'!$A$7,1,0)*IF(D14='Оценка сложности задач'!$B$7,1,0)*'Оценка сложности задач'!$G$7)+(IF(C14='Оценка сложности задач'!$A$8,1,0)*IF(D14='Оценка сложности задач'!$B$8,1,0)*'Оценка сложности задач'!$G$8)+(IF(C14='Оценка сложности задач'!$A$10,1,0)*IF(D14='Оценка сложности задач'!$B$10,1,0)*'Оценка сложности задач'!$G$10)+(IF(C14='Оценка сложности задач'!$A$9,1,0)*IF(D14='Оценка сложности задач'!$B$9,1,0)*'Оценка сложности задач'!$G$9)+ (IF(C14='Оценка сложности задач'!$A$11,1,0)*IF(D14='Оценка сложности задач'!$B$11,1,0)*'Оценка сложности задач'!$G$11) + (IF(C14='Оценка сложности задач'!$A$12,1,0)*IF(D14='Оценка сложности задач'!$B$12,1,0)*'Оценка сложности задач'!$G$12) + (IF(C14='Оценка сложности задач'!$A$13,1,0)*IF(D14='Оценка сложности задач'!$B$13,1,0)*'Оценка сложности задач'!$G$13) + (IF(C14='Оценка сложности задач'!$A$14,1,0)*IF(D14='Оценка сложности задач'!$B$14,1,0)*'Оценка сложности задач'!$G$14) + (IF(C14='Оценка сложности задач'!$A$15,1,0)*IF(D14='Оценка сложности задач'!$B$15,1,0)*'Оценка сложности задач'!$G$15) + (IF(C14='Оценка сложности задач'!$A$16,1,0)*IF(D14='Оценка сложности задач'!$B$16,1,0)*'Оценка сложности задач'!$G$16) + (IF(C14='Оценка сложности задач'!$A$17,1,0)*IF(D14='Оценка сложности задач'!$B$17,1,0)*'Оценка сложности задач'!$G$17) + (IF(C14='Оценка сложности задач'!$A$18,1,0)*IF(D14='Оценка сложности задач'!$B$18,1,0)*'Оценка сложности задач'!$G$18) + (IF(C14='Оценка сложности задач'!$A$19,1,0)*IF(D14='Оценка сложности задач'!$B$19,1,0)*'Оценка сложности задач'!$G$19)+(IF(C14='Оценка сложности задач'!$A$20,1,0)*IF(D14='Оценка сложности задач'!$B$20,1,0)*'Оценка сложности задач'!$G$20)+(IF(C14='Оценка сложности задач'!$A$21,1,0)*IF(D14='Оценка сложности задач'!$B$21,1,0)*'Оценка сложности задач'!$G$21)+(IF(C14='Оценка сложности задач'!$A$22,1,0)*IF(D14='Оценка сложности задач'!$B$22,1,0)*'Оценка сложности задач'!$G$22)+(IF(C14='Оценка сложности задач'!$A$23,1,0)*IF(D14='Оценка сложности задач'!$B$23,1,0)*'Оценка сложности задач'!$G$23)+(IF(C14='Оценка сложности задач'!$A$24,1,0)*IF(D14='Оценка сложности задач'!$B$24,1,0)*'Оценка сложности задач'!$G$24)+(IF(C14='Оценка сложности задач'!$A$25,1,0)*IF(D14='Оценка сложности задач'!$B$25,1,0)*'Оценка сложности задач'!$G$25)+(IF(C14='Оценка сложности задач'!$A$26,1,0)*IF(D14='Оценка сложности задач'!$B$26,1,0)*'Оценка сложности задач'!$G$26)+(IF(C14='Оценка сложности задач'!$A$27,1,0)*IF(D14='Оценка сложности задач'!$B$27,1,0)*'Оценка сложности задач'!$G$27)+(IF(C14='Оценка сложности задач'!$A$28,1,0)*IF(D14='Оценка сложности задач'!$B$28,1,0)*'Оценка сложности задач'!$G$28)+(IF(C14='Оценка сложности задач'!$A$29,1,0)*IF(D14='Оценка сложности задач'!$B$29,1,0)*'Оценка сложности задач'!$G$29)+(IF(C14='Оценка сложности задач'!$A$30,1,0)*IF(D14='Оценка сложности задач'!$B$30,1,0)*'Оценка сложности задач'!$G$30)+(IF(C14='Оценка сложности задач'!$A$31,1,0)*IF(D14='Оценка сложности задач'!$B$31,1,0)*'Оценка сложности задач'!$G$31)+(IF(C14='Оценка сложности задач'!$A$32,1,0)*IF(D14='Оценка сложности задач'!$B$32,1,0)*'Оценка сложности задач'!$G$32)+(IF(C14='Оценка сложности задач'!$A$33,1,0)*IF(D14='Оценка сложности задач'!$B$33,1,0)*'Оценка сложности задач'!$G$33)+(IF(C14='Оценка сложности задач'!$A$34,1,0)*IF(D14='Оценка сложности задач'!$B$34,1,0)*'Оценка сложности задач'!$G$34)+(IF(C14='Оценка сложности задач'!$A$35,1,0)*IF(D14='Оценка сложности задач'!$B$35,1,0)*'Оценка сложности задач'!$G$35)+(IF(C14='Оценка сложности задач'!$A$36,1,0)*IF(D14='Оценка сложности задач'!$B$36,1,0)*'Оценка сложности задач'!$G$36)+(IF(C14='Оценка сложности задач'!$A$37,1,0)*IF(D14='Оценка сложности задач'!$B$37,1,0)*'Оценка сложности задач'!$G$37)+(IF(C14='Оценка сложности задач'!$A$38,1,0)*IF(D14='Оценка сложности задач'!$B$38,1,0)*'Оценка сложности задач'!$G$38)+(IF(C14='Оценка сложности задач'!$A$39,1,0)*IF(D14='Оценка сложности задач'!$B$39,1,0)*'Оценка сложности задач'!$G$39)+(IF(C14='Оценка сложности задач'!$A$40,1,0)*IF(D14='Оценка сложности задач'!$B$40,1,0)*'Оценка сложности задач'!$G$40) -> 22
A15: 12 | B15: Обработка ошибок и повторные попытки (ретраи/очередь) | C15: Настройка процесса | D15: Средняя | E15: =(IF(C15='Оценка сложности задач'!$A$2,1,0)*IF(D15='Оценка сложности задач'!$B$2,1,0)*'Оценка сложности задач'!$G$2)+(IF(C15='Оценка сложности задач'!$A$3,1,0)*IF(D15='Оценка сложности задач'!$B$3,1,0)*'Оценка сложности задач'!$G$3)+(IF(C15='Оценка сложности задач'!$A$4,1,0)*IF(D15='Оценка сложности задач'!$B$4,1,0)*'Оценка сложности задач'!$G$4)+(IF(C15='Оценка сложности задач'!$A$5,1,0)*IF(D15='Оценка сложности задач'!$B$5,1,0)*'Оценка сложности задач'!$G$5)+(IF(C15='Оценка сложности задач'!$A$6,1,0)*IF(D15='Оценка сложности задач'!$B$6,1,0)*'Оценка сложности задач'!$G$6)+(IF(C15='Оценка сложности задач'!$A$7,1,0)*IF(D15='Оценка сложности задач'!$B$7,1,0)*'Оценка сложности задач'!$G$7)+(IF(C15='Оценка сложности задач'!$A$8,1,0)*IF(D15='Оценка сложности задач'!$B$8,1,0)*'Оценка сложности задач'!$G$8)+(IF(C15='Оценка сложности задач'!$A$10,1,0)*IF(D15='Оценка сложности задач'!$B$10,1,0)*'Оценка сложности задач'!$G$10)+(IF(C15='Оценка сложности задач'!$A$9,1,0)*IF(D15='Оценка сложности задач'!$B$9,1,0)*'Оценка сложности задач'!$G$9)+ (IF(C15='Оценка сложности задач'!$A$11,1,0)*IF(D15='Оценка сложности задач'!$B$11,1,0)*'Оценка сложности задач'!$G$11) + (IF(C15='Оценка сложности задач'!$A$12,1,0)*IF(D15='Оценка сложности задач'!$B$12,1,0)*'Оценка сложности задач'!$G$12) + (IF(C15='Оценка сложности задач'!$A$13,1,0)*IF(D15='Оценка сложности задач'!$B$13,1,0)*'Оценка сложности задач'!$G$13) + (IF(C15='Оценка сложности задач'!$A$14,1,0)*IF(D15='Оценка сложности задач'!$B$14,1,0)*'Оценка сложности задач'!$G$14) + (IF(C15='Оценка сложности задач'!$A$15,1,0)*IF(D15='Оценка сложности задач'!$B$15,1,0)*'Оценка сложности задач'!$G$15) + (IF(C15='Оценка сложности задач'!$A$16,1,0)*IF(D15='Оценка сложности задач'!$B$16,1,0)*'Оценка сложности задач'!$G$16) + (IF(C15='Оценка сложности задач'!$A$17,1,0)*IF(D15='Оценка сложности задач'!$B$17,1,0)*'Оценка сложности задач'!$G$17) + (IF(C15='Оценка сложности задач'!$A$18,1,0)*IF(D15='Оценка сложности задач'!$B$18,1,0)*'Оценка сложности задач'!$G$18) + (IF(C15='Оценка сложности задач'!$A$19,1,0)*IF(D15='Оценка сложности задач'!$B$19,1,0)*'Оценка сложности задач'!$G$19)+(IF(C15='Оценка сложности задач'!$A$20,1,0)*IF(D15='Оценка сложности задач'!$B$20,1,0)*'Оценка сложности задач'!$G$20)+(IF(C15='Оценка сложности задач'!$A$21,1,0)*IF(D15='Оценка сложности задач'!$B$21,1,0)*'Оценка сложности задач'!$G$21)+(IF(C15='Оценка сложности задач'!$A$22,1,0)*IF(D15='Оценка сложности задач'!$B$22,1,0)*'Оценка сложности задач'!$G$22)+(IF(C15='Оценка сложности задач'!$A$23,1,0)*IF(D15='Оценка сложности задач'!$B$23,1,0)*'Оценка сложности задач'!$G$23)+(IF(C15='Оценка сложности задач'!$A$24,1,0)*IF(D15='Оценка сложности задач'!$B$24,1,0)*'Оценка сложности задач'!$G$24)+(IF(C15='Оценка сложности задач'!$A$25,1,0)*IF(D15='Оценка сложности задач'!$B$25,1,0)*'Оценка сложности задач'!$G$25)+(IF(C15='Оценка сложности задач'!$A$26,1,0)*IF(D15='Оценка сложности задач'!$B$26,1,0)*'Оценка сложности задач'!$G$26)+(IF(C15='Оценка сложности задач'!$A$27,1,0)*IF(D15='Оценка сложности задач'!$B$27,1,0)*'Оценка сложности задач'!$G$27)+(IF(C15='Оценка сложности задач'!$A$28,1,0)*IF(D15='Оценка сложности задач'!$B$28,1,0)*'Оценка сложности задач'!$G$28)+(IF(C15='Оценка сложности задач'!$A$29,1,0)*IF(D15='Оценка сложности задач'!$B$29,1,0)*'Оценка сложности задач'!$G$29)+(IF(C15='Оценка сложности задач'!$A$30,1,0)*IF(D15='Оценка сложности задач'!$B$30,1,0)*'Оценка сложности задач'!$G$30)+(IF(C15='Оценка сложности задач'!$A$31,1,0)*IF(D15='Оценка сложности задач'!$B$31,1,0)*'Оценка сложности задач'!$G$31)+(IF(C15='Оценка сложности задач'!$A$32,1,0)*IF(D15='Оценка сложности задач'!$B$32,1,0)*'Оценка сложности задач'!$G$32)+(IF(C15='Оценка сложности задач'!$A$33,1,0)*IF(D15='Оценка сложности задач'!$B$33,1,0)*'Оценка сложности задач'!$G$33)+(IF(C15='Оценка сложности задач'!$A$34,1,0)*IF(D15='Оценка сложности задач'!$B$34,1,0)*'Оценка сложности задач'!$G$34)+(IF(C15='Оценка сложности задач'!$A$35,1,0)*IF(D15='Оценка сложности задач'!$B$35,1,0)*'Оценка сложности задач'!$G$35)+(IF(C15='Оценка сложности задач'!$A$36,1,0)*IF(D15='Оценка сложности задач'!$B$36,1,0)*'Оценка сложности задач'!$G$36)+(IF(C15='Оценка сложности задач'!$A$37,1,0)*IF(D15='Оценка сложности задач'!$B$37,1,0)*'Оценка сложности задач'!$G$37)+(IF(C15='Оценка сложности задач'!$A$38,1,0)*IF(D15='Оценка сложности задач'!$B$38,1,0)*'Оценка сложности задач'!$G$38)+(IF(C15='Оценка сложности задач'!$A$39,1,0)*IF(D15='Оценка сложности задач'!$B$39,1,0)*'Оценка сложности задач'!$G$39)+(IF(C15='Оценка сложности задач'!$A$40,1,0)*IF(D15='Оценка сложности задач'!$B$40,1,0)*'Оценка сложности задач'!$G$40) -> 16
A16: 13 | E16: =(IF(C16='Оценка сложности задач'!$A$2,1,0)*IF(D16='Оценка сложности задач'!$B$2,1,0)*'Оценка сложности задач'!$G$2)+(IF(C16='Оценка сложности задач'!$A$3,1,0)*IF(D16='Оценка сложности задач'!$B$3,1,0)*'Оценка сложности задач'!$G$3)+(IF(C16='Оценка сложности задач'!$A$4,1,0)*IF(D16='Оценка сложности задач'!$B$4,1,0)*'Оценка сложности задач'!$G$4)+(IF(C16='Оценка сложности задач'!$A$5,1,0)*IF(D16='Оценка сложности задач'!$B$5,1,0)*'Оценка сложности задач'!$G$5)+(IF(C16='Оценка сложности задач'!$A$6,1,0)*IF(D16='Оценка сложности задач'!$B$6,1,0)*'Оценка сложности задач'!$G$6)+(IF(C16='Оценка сложности задач'!$A$7,1,0)*IF(D16='Оценка сложности задач'!$B$7,1,0)*'Оценка сложности задач'!$G$7)+(IF(C16='Оценка сложности задач'!$A$8,1,0)*IF(D16='Оценка сложности задач'!$B$8,1,0)*'Оценка сложности задач'!$G$8)+(IF(C16='Оценка сложности задач'!$A$10,1,0)*IF(D16='Оценка сложности задач'!$B$10,1,0)*'Оценка сложности задач'!$G$10)+(IF(C16='Оценка сложности задач'!$A$9,1,0)*IF(D16='Оценка сложности задач'!$B$9,1,0)*'Оценка сложности задач'!$G$9)+ (IF(C16='Оценка сложности задач'!$A$11,1,0)*IF(D16='Оценка сложности задач'!$B$11,1,0)*'Оценка сложности задач'!$G$11) + (IF(C16='Оценка сложности задач'!$A$12,1,0)*IF(D16='Оценка сложности задач'!$B$12,1,0)*'Оценка сложности задач'!$G$12) + (IF(C16='Оценка сложности задач'!$A$13,1,0)*IF(D16='Оценка сложности задач'!$B$13,1,0)*'Оценка сложности задач'!$G$13) + (IF(C16='Оценка сложности задач'!$A$14,1,0)*IF(D16='Оценка сложности задач'!$B$14,1,0)*'Оценка сложности задач'!$G$14) + (IF(C16='Оценка сложности задач'!$A$15,1,0)*IF(D16='Оценка сложности задач'!$B$15,1,0)*'Оценка сложности задач'!$G$15) + (IF(C16='Оценка сложности задач'!$A$16,1,0)*IF(D16='Оценка сложности задач'!$B$16,1,0)*'Оценка сложности задач'!$G$16) + (IF(C16='Оценка сложности задач'!$A$17,1,0)*IF(D16='Оценка сложности задач'!$B$17,1,0)*'Оценка сложности задач'!$G$17) + (IF(C16='Оценка сложности задач'!$A$18,1,0)*IF(D16='Оценка сложности задач'!$B$18,1,0)*'Оценка сложности задач'!$G$18) + (IF(C16='Оценка сложности задач'!$A$19,1,0)*IF(D16='Оценка сложности задач'!$B$19,1,0)*'Оценка сложности задач'!$G$19)+(IF(C16='Оценка сложности задач'!$A$20,1,0)*IF(D16='Оценка сложности задач'!$B$20,1,0)*'Оценка сложности задач'!$G$20)+(IF(C16='Оценка сложности задач'!$A$21,1,0)*IF(D16='Оценка сложности задач'!$B$21,1,0)*'Оценка сложности задач'!$G$21)+(IF(C16='Оценка сложности задач'!$A$22,1,0)*IF(D16='Оценка сложности задач'!$B$22,1,0)*'Оценка сложности задач'!$G$22)+(IF(C16='Оценка сложности задач'!$A$23,1,0)*IF(D16='Оценка сложности задач'!$B$23,1,0)*'Оценка сложности задач'!$G$23)+(IF(C16='Оценка сложности задач'!$A$24,1,0)*IF(D16='Оценка сложности задач'!$B$24,1,0)*'Оценка сложности задач'!$G$24)+(IF(C16='Оценка сложности задач'!$A$25,1,0)*IF(D16='Оценка сложности задач'!$B$25,1,0)*'Оценка сложности задач'!$G$25)+(IF(C16='Оценка сложности задач'!$A$26,1,0)*IF(D16='Оценка сложности задач'!$B$26,1,0)*'Оценка сложности задач'!$G$26)+(IF(C16='Оценка сложности задач'!$A$27,1,0)*IF(D16='Оценка сложности задач'!$B$27,1,0)*'Оценка сложности задач'!$G$27)+(IF(C16='Оценка сложности задач'!$A$28,1,0)*IF(D16='Оценка сложности задач'!$B$28,1,0)*'Оценка сложности задач'!$G$28)+(IF(C16='Оценка сложности задач'!$A$29,1,0)*IF(D16='Оценка сложности задач'!$B$29,1,0)*'Оценка сложности задач'!$G$29)+(IF(C16='Оценка сложности задач'!$A$30,1,0)*IF(D16='Оценка сложности задач'!$B$30,1,0)*'Оценка сложности задач'!$G$30)+(IF(C16='Оценка сложности задач'!$A$31,1,0)*IF(D16='Оценка сложности задач'!$B$31,1,0)*'Оценка сложности задач'!$G$31)+(IF(C16='Оценка сложности задач'!$A$32,1,0)*IF(D16='Оценка сложности задач'!$B$32,1,0)*'Оценка сложности задач'!$G$32)+(IF(C16='Оценка сложности задач'!$A$33,1,0)*IF(D16='Оценка сложности задач'!$B$33,1,0)*'Оценка сложности задач'!$G$33)+(IF(C16='Оценка сложности задач'!$A$34,1,0)*IF(D16='Оценка сложности задач'!$B$34,1,0)*'Оценка сложности задач'!$G$34)+(IF(C16='Оценка сложности задач'!$A$35,1,0)*IF(D16='Оценка сложности задач'!$B$35,1,0)*'Оценка сложности задач'!$G$35)+(IF(C16='Оценка сложности задач'!$A$36,1,0)*IF(D16='Оценка сложности задач'!$B$36,1,0)*'Оценка сложности задач'!$G$36)+(IF(C16='Оценка сложности задач'!$A$37,1,0)*IF(D16='Оценка сложности задач'!$B$37,1,0)*'Оценка сложности задач'!$G$37)+(IF(C16='Оценка сложности задач'!$A$38,1,0)*IF(D16='Оценка сложности задач'!$B$38,1,0)*'Оценка сложности задач'!$G$38)+(IF(C16='Оценка сложности задач'!$A$39,1,0)*IF(D16='Оценка сложности задач'!$B$39,1,0)*'Оценка сложности задач'!$G$39)+(IF(C16='Оценка сложности задач'!$A$40,1,0)*IF(D16='Оценка сложности задач'!$B$40,1,0)*'Оценка сложности задач'!$G$40) -> 0
A17: 14 | E17: =(IF(C17='Оценка сложности задач'!$A$2,1,0)*IF(D17='Оценка сложности задач'!$B$2,1,0)*'Оценка сложности задач'!$G$2)+(IF(C17='Оценка сложности задач'!$A$3,1,0)*IF(D17='Оценка сложности задач'!$B$3,1,0)*'Оценка сложности задач'!$G$3)+(IF(C17='Оценка сложности задач'!$A$4,1,0)*IF(D17='Оценка сложности задач'!$B$4,1,0)*'Оценка сложности задач'!$G$4)+(IF(C17='Оценка сложности задач'!$A$5,1,0)*IF(D17='Оценка сложности задач'!$B$5,1,0)*'Оценка сложности задач'!$G$5)+(IF(C17='Оценка сложности задач'!$A$6,1,0)*IF(D17='Оценка сложности задач'!$B$6,1,0)*'Оценка сложности задач'!$G$6)+(IF(C17='Оценка сложности задач'!$A$7,1,0)*IF(D17='Оценка сложности задач'!$B$7,1,0)*'Оценка сложности задач'!$G$7)+(IF(C17='Оценка сложности задач'!$A$8,1,0)*IF(D17='Оценка сложности задач'!$B$8,1,0)*'Оценка сложности задач'!$G$8)+(IF(C17='Оценка сложности задач'!$A$10,1,0)*IF(D17='Оценка сложности задач'!$B$10,1,0)*'Оценка сложности задач'!$G$10)+(IF(C17='Оценка сложности задач'!$A$9,1,0)*IF(D17='Оценка сложности задач'!$B$9,1,0)*'Оценка сложности задач'!$G$9)+ (IF(C17='Оценка сложности задач'!$A$11,1,0)*IF(D17='Оценка сложности задач'!$B$11,1,0)*'Оценка сложности задач'!$G$11) + (IF(C17='Оценка сложности задач'!$A$12,1,0)*IF(D17='Оценка сложности задач'!$B$12,1,0)*'Оценка сложности задач'!$G$12) + (IF(C17='Оценка сложности задач'!$A$13,1,0)*IF(D17='Оценка сложности задач'!$B$13,1,0)*'Оценка сложности задач'!$G$13) + (IF(C17='Оценка сложности задач'!$A$14,1,0)*IF(D17='Оценка сложности задач'!$B$14,1,0)*'Оценка сложности задач'!$G$14) + (IF(C17='Оценка сложности задач'!$A$15,1,0)*IF(D17='Оценка сложности задач'!$B$15,1,0)*'Оценка сложности задач'!$G$15) + (IF(C17='Оценка сложности задач'!$A$16,1,0)*IF(D17='Оценка сложности задач'!$B$16,1,0)*'Оценка сложности задач'!$G$16) + (IF(C17='Оценка сложности задач'!$A$17,1,0)*IF(D17='Оценка сложности задач'!$B$17,1,0)*'Оценка сложности задач'!$G$17) + (IF(C17='Оценка сложности задач'!$A$18,1,0)*IF(D17='Оценка сложности задач'!$B$18,1,0)*'Оценка сложности задач'!$G$18) + (IF(C17='Оценка сложности задач'!$A$19,1,0)*IF(D17='Оценка сложности задач'!$B$19,1,0)*'Оценка сложности задач'!$G$19)+(IF(C17='Оценка сложности задач'!$A$20,1,0)*IF(D17='Оценка сложности задач'!$B$20,1,0)*'Оценка сложности задач'!$G$20)+(IF(C17='Оценка сложности задач'!$A$21,1,0)*IF(D17='Оценка сложности задач'!$B$21,1,0)*'Оценка сложности задач'!$G$21)+(IF(C17='Оценка сложности задач'!$A$22,1,0)*IF(D17='Оценка сложности задач'!$B$22,1,0)*'Оценка сложности задач'!$G$22)+(IF(C17='Оценка сложности задач'!$A$23,1,0)*IF(D17='Оценка сложности задач'!$B$23,1,0)*'Оценка сложности задач'!$G$23)+(IF(C17='Оценка сложности задач'!$A$24,1,0)*IF(D17='Оценка сложности задач'!$B$24,1,0)*'Оценка сложности задач'!$G$24)+(IF(C17='Оценка сложности задач'!$A$25,1,0)*IF(D17='Оценка сложности задач'!$B$25,1,0)*'Оценка сложности задач'!$G$25)+(IF(C17='Оценка сложности задач'!$A$26,1,0)*IF(D17='Оценка сложности задач'!$B$26,1,0)*'Оценка сложности задач'!$G$26)+(IF(C17='Оценка сложности задач'!$A$27,1,0)*IF(D17='Оценка сложности задач'!$B$27,1,0)*'Оценка сложности задач'!$G$27)+(IF(C17='Оценка сложности задач'!$A$28,1,0)*IF(D17='Оценка сложности задач'!$B$28,1,0)*'Оценка сложности задач'!$G$28)+(IF(C17='Оценка сложности задач'!$A$29,1,0)*IF(D17='Оценка сложности задач'!$B$29,1,0)*'Оценка сложности задач'!$G$29)+(IF(C17='Оценка сложности задач'!$A$30,1,0)*IF(D17='Оценка сложности задач'!$B$30,1,0)*'Оценка сложности задач'!$G$30)+(IF(C17='Оценка сложности задач'!$A$31,1,0)*IF(D17='Оценка сложности задач'!$B$31,1,0)*'Оценка сложности задач'!$G$31)+(IF(C17='Оценка сложности задач'!$A$32,1,0)*IF(D17='Оценка сложности задач'!$B$32,1,0)*'Оценка сложности задач'!$G$32)+(IF(C17='Оценка сложности задач'!$A$33,1,0)*IF(D17='Оценка сложности задач'!$B$33,1,0)*'Оценка сложности задач'!$G$33)+(IF(C17='Оценка сложности задач'!$A$34,1,0)*IF(D17='Оценка сложности задач'!$B$34,1,0)*'Оценка сложности задач'!$G$34)+(IF(C17='Оценка сложности задач'!$A$35,1,0)*IF(D17='Оценка сложности задач'!$B$35,1,0)*'Оценка сложности задач'!$G$35)+(IF(C17='Оценка сложности задач'!$A$36,1,0)*IF(D17='Оценка сложности задач'!$B$36,1,0)*'Оценка сложности задач'!$G$36)+(IF(C17='Оценка сложности задач'!$A$37,1,0)*IF(D17='Оценка сложности задач'!$B$37,1,0)*'Оценка сложности задач'!$G$37)+(IF(C17='Оценка сложности задач'!$A$38,1,0)*IF(D17='Оценка сложности задач'!$B$38,1,0)*'Оценка сложности задач'!$G$38)+(IF(C17='Оценка сложности задач'!$A$39,1,0)*IF(D17='Оценка сложности задач'!$B$39,1,0)*'Оценка сложности задач'!$G$39)+(IF(C17='Оценка сложности задач'!$A$40,1,0)*IF(D17='Оценка сложности задач'!$B$40,1,0)*'Оценка сложности задач'!$G$40) -> 0
A18: 15 | E18: =(IF(C18='Оценка сложности задач'!$A$2,1,0)*IF(D18='Оценка сложности задач'!$B$2,1,0)*'Оценка сложности задач'!$G$2)+(IF(C18='Оценка сложности задач'!$A$3,1,0)*IF(D18='Оценка сложности задач'!$B$3,1,0)*'Оценка сложности задач'!$G$3)+(IF(C18='Оценка сложности задач'!$A$4,1,0)*IF(D18='Оценка сложности задач'!$B$4,1,0)*'Оценка сложности задач'!$G$4)+(IF(C18='Оценка сложности задач'!$A$5,1,0)*IF(D18='Оценка сложности задач'!$B$5,1,0)*'Оценка сложности задач'!$G$5)+(IF(C18='Оценка сложности задач'!$A$6,1,0)*IF(D18='Оценка сложности задач'!$B$6,1,0)*'Оценка сложности задач'!$G$6)+(IF(C18='Оценка сложности задач'!$A$7,1,0)*IF(D18='Оценка сложности задач'!$B$7,1,0)*'Оценка сложности задач'!$G$7)+(IF(C18='Оценка сложности задач'!$A$8,1,0)*IF(D18='Оценка сложности задач'!$B$8,1,0)*'Оценка сложности задач'!$G$8)+(IF(C18='Оценка сложности задач'!$A$10,1,0)*IF(D18='Оценка сложности задач'!$B$10,1,0)*'Оценка сложности задач'!$G$10)+(IF(C18='Оценка сложности задач'!$A$9,1,0)*IF(D18='Оценка сложности задач'!$B$9,1,0)*'Оценка сложности задач'!$G$9)+ (IF(C18='Оценка сложности задач'!$A$11,1,0)*IF(D18='Оценка сложности задач'!$B$11,1,0)*'Оценка сложности задач'!$G$11) + (IF(C18='Оценка сложности задач'!$A$12,1,0)*IF(D18='Оценка сложности задач'!$B$12,1,0)*'Оценка сложности задач'!$G$12) + (IF(C18='Оценка сложности задач'!$A$13,1,0)*IF(D18='Оценка сложности задач'!$B$13,1,0)*'Оценка сложности задач'!$G$13) + (IF(C18='Оценка сложности задач'!$A$14,1,0)*IF(D18='Оценка сложности задач'!$B$14,1,0)*'Оценка сложности задач'!$G$14) + (IF(C18='Оценка сложности задач'!$A$15,1,0)*IF(D18='Оценка сложности задач'!$B$15,1,0)*'Оценка сложности задач'!$G$15) + (IF(C18='Оценка сложности задач'!$A$16,1,0)*IF(D18='Оценка сложности задач'!$B$16,1,0)*'Оценка сложности задач'!$G$16) + (IF(C18='Оценка сложности задач'!$A$17,1,0)*IF(D18='Оценка сложности задач'!$B$17,1,0)*'Оценка сложности задач'!$G$17) + (IF(C18='Оценка сложности задач'!$A$18,1,0)*IF(D18='Оценка сложности задач'!$B$18,1,0)*'Оценка сложности задач'!$G$18) + (IF(C18='Оценка сложности задач'!$A$19,1,0)*IF(D18='Оценка сложности задач'!$B$19,1,0)*'Оценка сложности задач'!$G$19)+(IF(C18='Оценка сложности задач'!$A$20,1,0)*IF(D18='Оценка сложности задач'!$B$20,1,0)*'Оценка сложности задач'!$G$20)+(IF(C18='Оценка сложности задач'!$A$21,1,0)*IF(D18='Оценка сложности задач'!$B$21,1,0)*'Оценка сложности задач'!$G$21)+(IF(C18='Оценка сложности задач'!$A$22,1,0)*IF(D18='Оценка сложности задач'!$B$22,1,0)*'Оценка сложности задач'!$G$22)+(IF(C18='Оценка сложности задач'!$A$23,1,0)*IF(D18='Оценка сложности задач'!$B$23,1,0)*'Оценка сложности задач'!$G$23)+(IF(C18='Оценка сложности задач'!$A$24,1,0)*IF(D18='Оценка сложности задач'!$B$24,1,0)*'Оценка сложности задач'!$G$24)+(IF(C18='Оценка сложности задач'!$A$25,1,0)*IF(D18='Оценка сложности задач'!$B$25,1,0)*'Оценка сложности задач'!$G$25)+(IF(C18='Оценка сложности задач'!$A$26,1,0)*IF(D18='Оценка сложности задач'!$B$26,1,0)*'Оценка сложности задач'!$G$26)+(IF(C18='Оценка сложности задач'!$A$27,1,0)*IF(D18='Оценка сложности задач'!$B$27,1,0)*'Оценка сложности задач'!$G$27)+(IF(C18='Оценка сложности задач'!$A$28,1,0)*IF(D18='Оценка сложности задач'!$B$28,1,0)*'Оценка сложности задач'!$G$28)+(IF(C18='Оценка сложности задач'!$A$29,1,0)*IF(D18='Оценка сложности задач'!$B$29,1,0)*'Оценка сложности задач'!$G$29)+(IF(C18='Оценка сложности задач'!$A$30,1,0)*IF(D18='Оценка сложности задач'!$B$30,1,0)*'Оценка сложности задач'!$G$30)+(IF(C18='Оценка сложности задач'!$A$31,1,0)*IF(D18='Оценка сложности задач'!$B$31,1,0)*'Оценка сложности задач'!$G$31)+(IF(C18='Оценка сложности задач'!$A$32,1,0)*IF(D18='Оценка сложности задач'!$B$32,1,0)*'Оценка сложности задач'!$G$32)+(IF(C18='Оценка сложности задач'!$A$33,1,0)*IF(D18='Оценка сложности задач'!$B$33,1,0)*'Оценка сложности задач'!$G$33)+(IF(C18='Оценка сложности задач'!$A$34,1,0)*IF(D18='Оценка сложности задач'!$B$34,1,0)*'Оценка сложности задач'!$G$34)+(IF(C18='Оценка сложности задач'!$A$35,1,0)*IF(D18='Оценка сложности задач'!$B$35,1,0)*'Оценка сложности задач'!$G$35)+(IF(C18='Оценка сложности задач'!$A$36,1,0)*IF(D18='Оценка сложности задач'!$B$36,1,0)*'Оценка сложности задач'!$G$36)+(IF(C18='Оценка сложности задач'!$A$37,1,0)*IF(D18='Оценка сложности задач'!$B$37,1,0)*'Оценка сложности задач'!$G$37)+(IF(C18='Оценка сложности задач'!$A$38,1,0)*IF(D18='Оценка сложности задач'!$B$38,1,0)*'Оценка сложности задач'!$G$38)+(IF(C18='Оценка сложности задач'!$A$39,1,0)*IF(D18='Оценка сложности задач'!$B$39,1,0)*'Оценка сложности задач'!$G$39)+(IF(C18='Оценка сложности задач'!$A$40,1,0)*IF(D18='Оценка сложности задач'!$B$40,1,0)*'Оценка сложности задач'!$G$40) -> 0
A19: 16 | E19: =(IF(C19='Оценка сложности задач'!$A$2,1,0)*IF(D19='Оценка сложности задач'!$B$2,1,0)*'Оценка сложности задач'!$G$2)+(IF(C19='Оценка сложности задач'!$A$3,1,0)*IF(D19='Оценка сложности задач'!$B$3,1,0)*'Оценка сложности задач'!$G$3)+(IF(C19='Оценка сложности задач'!$A$4,1,0)*IF(D19='Оценка сложности задач'!$B$4,1,0)*'Оценка сложности задач'!$G$4)+(IF(C19='Оценка сложности задач'!$A$5,1,0)*IF(D19='Оценка сложности задач'!$B$5,1,0)*'Оценка сложности задач'!$G$5)+(IF(C19='Оценка сложности задач'!$A$6,1,0)*IF(D19='Оценка сложности задач'!$B$6,1,0)*'Оценка сложности задач'!$G$6)+(IF(C19='Оценка сложности задач'!$A$7,1,0)*IF(D19='Оценка сложности задач'!$B$7,1,0)*'Оценка сложности задач'!$G$7)+(IF(C19='Оценка сложности задач'!$A$8,1,0)*IF(D19='Оценка сложности задач'!$B$8,1,0)*'Оценка сложности задач'!$G$8)+(IF(C19='Оценка сложности задач'!$A$10,1,0)*IF(D19='Оценка сложности задач'!$B$10,1,0)*'Оценка сложности задач'!$G$10)+(IF(C19='Оценка сложности задач'!$A$9,1,0)*IF(D19='Оценка сложности задач'!$B$9,1,0)*'Оценка сложности задач'!$G$9)+ (IF(C19='Оценка сложности задач'!$A$11,1,0)*IF(D19='Оценка сложности задач'!$B$11,1,0)*'Оценка сложности задач'!$G$11) + (IF(C19='Оценка сложности задач'!$A$12,1,0)*IF(D19='Оценка сложности задач'!$B$12,1,0)*'Оценка сложности задач'!$G$12) + (IF(C19='Оценка сложности задач'!$A$13,1,0)*IF(D19='Оценка сложности задач'!$B$13,1,0)*'Оценка сложности задач'!$G$13) + (IF(C19='Оценка сложности задач'!$A$14,1,0)*IF(D19='Оценка сложности задач'!$B$14,1,0)*'Оценка сложности задач'!$G$14) + (IF(C19='Оценка сложности задач'!$A$15,1,0)*IF(D19='Оценка сложности задач'!$B$15,1,0)*'Оценка сложности задач'!$G$15) + (IF(C19='Оценка сложности задач'!$A$16,1,0)*IF(D19='Оценка сложности задач'!$B$16,1,0)*'Оценка сложности задач'!$G$16) + (IF(C19='Оценка сложности задач'!$A$17,1,0)*IF(D19='Оценка сложности задач'!$B$17,1,0)*'Оценка сложности задач'!$G$17) + (IF(C19='Оценка сложности задач'!$A$18,1,0)*IF(D19='Оценка сложности задач'!$B$18,1,0)*'Оценка сложности задач'!$G$18) + (IF(C19='Оценка сложности задач'!$A$19,1,0)*IF(D19='Оценка сложности задач'!$B$19,1,0)*'Оценка сложности задач'!$G$19)+(IF(C19='Оценка сложности задач'!$A$20,1,0)*IF(D19='Оценка сложности задач'!$B$20,1,0)*'Оценка сложности задач'!$G$20)+(IF(C19='Оценка сложности задач'!$A$21,1,0)*IF(D19='Оценка сложности задач'!$B$21,1,0)*'Оценка сложности задач'!$G$21)+(IF(C19='Оценка сложности задач'!$A$22,1,0)*IF(D19='Оценка сложности задач'!$B$22,1,0)*'Оценка сложности задач'!$G$22)+(IF(C19='Оценка сложности задач'!$A$23,1,0)*IF(D19='Оценка сложности задач'!$B$23,1,0)*'Оценка сложности задач'!$G$23)+(IF(C19='Оценка сложности задач'!$A$24,1,0)*IF(D19='Оценка сложности задач'!$B$24,1,0)*'Оценка сложности задач'!$G$24)+(IF(C19='Оценка сложности задач'!$A$25,1,0)*IF(D19='Оценка сложности задач'!$B$25,1,0)*'Оценка сложности задач'!$G$25)+(IF(C19='Оценка сложности задач'!$A$26,1,0)*IF(D19='Оценка сложности задач'!$B$26,1,0)*'Оценка сложности задач'!$G$26)+(IF(C19='Оценка сложности задач'!$A$27,1,0)*IF(D19='Оценка сложности задач'!$B$27,1,0)*'Оценка сложности задач'!$G$27)+(IF(C19='Оценка сложности задач'!$A$28,1,0)*IF(D19='Оценка сложности задач'!$B$28,1,0)*'Оценка сложности задач'!$G$28)+(IF(C19='Оценка сложности задач'!$A$29,1,0)*IF(D19='Оценка сложности задач'!$B$29,1,0)*'Оценка сложности задач'!$G$29)+(IF(C19='Оценка сложности задач'!$A$30,1,0)*IF(D19='Оценка сложности задач'!$B$30,1,0)*'Оценка сложности задач'!$G$30)+(IF(C19='Оценка сложности задач'!$A$31,1,0)*IF(D19='Оценка сложности задач'!$B$31,1,0)*'Оценка сложности задач'!$G$31)+(IF(C19='Оценка сложности задач'!$A$32,1,0)*IF(D19='Оценка сложности задач'!$B$32,1,0)*'Оценка сложности задач'!$G$32)+(IF(C19='Оценка сложности задач'!$A$33,1,0)*IF(D19='Оценка сложности задач'!$B$33,1,0)*'Оценка сложности задач'!$G$33)+(IF(C19='Оценка сложности задач'!$A$34,1,0)*IF(D19='Оценка сложности задач'!$B$34,1,0)*'Оценка сложности задач'!$G$34)+(IF(C19='Оценка сложности задач'!$A$35,1,0)*IF(D19='Оценка сложности задач'!$B$35,1,0)*'Оценка сложности задач'!$G$35)+(IF(C19='Оценка сложности задач'!$A$36,1,0)*IF(D19='Оценка сложности задач'!$B$36,1,0)*'Оценка сложности задач'!$G$36)+(IF(C19='Оценка сложности задач'!$A$37,1,0)*IF(D19='Оценка сложности задач'!$B$37,1,0)*'Оценка сложности задач'!$G$37)+(IF(C19='Оценка сложности задач'!$A$38,1,0)*IF(D19='Оценка сложности задач'!$B$38,1,0)*'Оценка сложности задач'!$G$38)+(IF(C19='Оценка сложности задач'!$A$39,1,0)*IF(D19='Оценка сложности задач'!$B$39,1,0)*'Оценка сложности задач'!$G$39)+(IF(C19='Оценка сложности задач'!$A$40,1,0)*IF(D19='Оценка сложности задач'!$B$40,1,0)*'Оценка сложности задач'!$G$40) -> 0
A20: 17 | E20: =(IF(C20='Оценка сложности задач'!$A$2,1,0)*IF(D20='Оценка сложности задач'!$B$2,1,0)*'Оценка сложности задач'!$G$2)+(IF(C20='Оценка сложности задач'!$A$3,1,0)*IF(D20='Оценка сложности задач'!$B$3,1,0)*'Оценка сложности задач'!$G$3)+(IF(C20='Оценка сложности задач'!$A$4,1,0)*IF(D20='Оценка сложности задач'!$B$4,1,0)*'Оценка сложности задач'!$G$4)+(IF(C20='Оценка сложности задач'!$A$5,1,0)*IF(D20='Оценка сложности задач'!$B$5,1,0)*'Оценка сложности задач'!$G$5)+(IF(C20='Оценка сложности задач'!$A$6,1,0)*IF(D20='Оценка сложности задач'!$B$6,1,0)*'Оценка сложности задач'!$G$6)+(IF(C20='Оценка сложности задач'!$A$7,1,0)*IF(D20='Оценка сложности задач'!$B$7,1,0)*'Оценка сложности задач'!$G$7)+(IF(C20='Оценка сложности задач'!$A$8,1,0)*IF(D20='Оценка сложности задач'!$B$8,1,0)*'Оценка сложности задач'!$G$8)+(IF(C20='Оценка сложности задач'!$A$10,1,0)*IF(D20='Оценка сложности задач'!$B$10,1,0)*'Оценка сложности задач'!$G$10)+(IF(C20='Оценка сложности задач'!$A$9,1,0)*IF(D20='Оценка сложности задач'!$B$9,1,0)*'Оценка сложности задач'!$G$9)+ (IF(C20='Оценка сложности задач'!$A$11,1,0)*IF(D20='Оценка сложности задач'!$B$11,1,0)*'Оценка сложности задач'!$G$11) + (IF(C20='Оценка сложности задач'!$A$12,1,0)*IF(D20='Оценка сложности задач'!$B$12,1,0)*'Оценка сложности задач'!$G$12) + (IF(C20='Оценка сложности задач'!$A$13,1,0)*IF(D20='Оценка сложности задач'!$B$13,1,0)*'Оценка сложности задач'!$G$13) + (IF(C20='Оценка сложности задач'!$A$14,1,0)*IF(D20='Оценка сложности задач'!$B$14,1,0)*'Оценка сложности задач'!$G$14) + (IF(C20='Оценка сложности задач'!$A$15,1,0)*IF(D20='Оценка сложности задач'!$B$15,1,0)*'Оценка сложности задач'!$G$15) + (IF(C20='Оценка сложности задач'!$A$16,1,0)*IF(D20='Оценка сложности задач'!$B$16,1,0)*'Оценка сложности задач'!$G$16) + (IF(C20='Оценка сложности задач'!$A$17,1,0)*IF(D20='Оценка сложности задач'!$B$17,1,0)*'Оценка сложности задач'!$G$17) + (IF(C20='Оценка сложности задач'!$A$18,1,0)*IF(D20='Оценка сложности задач'!$B$18,1,0)*'Оценка сложности задач'!$G$18) + (IF(C20='Оценка сложности задач'!$A$19,1,0)*IF(D20='Оценка сложности задач'!$B$19,1,0)*'Оценка сложности задач'!$G$19)+(IF(C20='Оценка сложности задач'!$A$20,1,0)*IF(D20='Оценка сложности задач'!$B$20,1,0)*'Оценка сложности задач'!$G$20)+(IF(C20='Оценка сложности задач'!$A$21,1,0)*IF(D20='Оценка сложности задач'!$B$21,1,0)*'Оценка сложности задач'!$G$21)+(IF(C20='Оценка сложности задач'!$A$22,1,0)*IF(D20='Оценка сложности задач'!$B$22,1,0)*'Оценка сложности задач'!$G$22)+(IF(C20='Оценка сложности задач'!$A$23,1,0)*IF(D20='Оценка сложности задач'!$B$23,1,0)*'Оценка сложности задач'!$G$23)+(IF(C20='Оценка сложности задач'!$A$24,1,0)*IF(D20='Оценка сложности задач'!$B$24,1,0)*'Оценка сложности задач'!$G$24)+(IF(C20='Оценка сложности задач'!$A$25,1,0)*IF(D20='Оценка сложности задач'!$B$25,1,0)*'Оценка сложности задач'!$G$25)+(IF(C20='Оценка сложности задач'!$A$26,1,0)*IF(D20='Оценка сложности задач'!$B$26,1,0)*'Оценка сложности задач'!$G$26)+(IF(C20='Оценка сложности задач'!$A$27,1,0)*IF(D20='Оценка сложности задач'!$B$27,1,0)*'Оценка сложности задач'!$G$27)+(IF(C20='Оценка сложности задач'!$A$28,1,0)*IF(D20='Оценка сложности задач'!$B$28,1,0)*'Оценка сложности задач'!$G$28)+(IF(C20='Оценка сложности задач'!$A$29,1,0)*IF(D20='Оценка сложности задач'!$B$29,1,0)*'Оценка сложности задач'!$G$29)+(IF(C20='Оценка сложности задач'!$A$30,1,0)*IF(D20='Оценка сложности задач'!$B$30,1,0)*'Оценка сложности задач'!$G$30)+(IF(C20='Оценка сложности задач'!$A$31,1,0)*IF(D20='Оценка сложности задач'!$B$31,1,0)*'Оценка сложности задач'!$G$31)+(IF(C20='Оценка сложности задач'!$A$32,1,0)*IF(D20='Оценка сложности задач'!$B$32,1,0)*'Оценка сложности задач'!$G$32)+(IF(C20='Оценка сложности задач'!$A$33,1,0)*IF(D20='Оценка сложности задач'!$B$33,1,0)*'Оценка сложности задач'!$G$33)+(IF(C20='Оценка сложности задач'!$A$34,1,0)*IF(D20='Оценка сложности задач'!$B$34,1,0)*'Оценка сложности задач'!$G$34)+(IF(C20='Оценка сложности задач'!$A$35,1,0)*IF(D20='Оценка сложности задач'!$B$35,1,0)*'Оценка сложности задач'!$G$35)+(IF(C20='Оценка сложности задач'!$A$36,1,0)*IF(D20='Оценка сложности задач'!$B$36,1,0)*'Оценка сложности задач'!$G$36)+(IF(C20='Оценка сложности задач'!$A$37,1,0)*IF(D20='Оценка сложности задач'!$B$37,1,0)*'Оценка сложности задач'!$G$37)+(IF(C20='Оценка сложности задач'!$A$38,1,0)*IF(D20='Оценка сложности задач'!$B$38,1,0)*'Оценка сложности задач'!$G$38)+(IF(C20='Оценка сложности задач'!$A$39,1,0)*IF(D20='Оценка сложности задач'!$B$39,1,0)*'Оценка сложности задач'!$G$39)+(IF(C20='Оценка сложности задач'!$A$40,1,0)*IF(D20='Оценка сложности задач'!$B$40,1,0)*'Оценка сложности задач'!$G$40) -> 0
A21: 18 | E21: =(IF(C21='Оценка сложности задач'!$A$2,1,0)*IF(D21='Оценка сложности задач'!$B$2,1,0)*'Оценка сложности задач'!$G$2)+(IF(C21='Оценка сложности задач'!$A$3,1,0)*IF(D21='Оценка сложности задач'!$B$3,1,0)*'Оценка сложности задач'!$G$3)+(IF(C21='Оценка сложности задач'!$A$4,1,0)*IF(D21='Оценка сложности задач'!$B$4,1,0)*'Оценка сложности задач'!$G$4)+(IF(C21='Оценка сложности задач'!$A$5,1,0)*IF(D21='Оценка сложности задач'!$B$5,1,0)*'Оценка сложности задач'!$G$5)+(IF(C21='Оценка сложности задач'!$A$6,1,0)*IF(D21='Оценка сложности задач'!$B$6,1,0)*'Оценка сложности задач'!$G$6)+(IF(C21='Оценка сложности задач'!$A$7,1,0)*IF(D21='Оценка сложности задач'!$B$7,1,0)*'Оценка сложности задач'!$G$7)+(IF(C21='Оценка сложности задач'!$A$8,1,0)*IF(D21='Оценка сложности задач'!$B$8,1,0)*'Оценка сложности задач'!$G$8)+(IF(C21='Оценка сложности задач'!$A$10,1,0)*IF(D21='Оценка сложности задач'!$B$10,1,0)*'Оценка сложности задач'!$G$10)+(IF(C21='Оценка сложности задач'!$A$9,1,0)*IF(D21='Оценка сложности задач'!$B$9,1,0)*'Оценка сложности задач'!$G$9)+ (IF(C21='Оценка сложности задач'!$A$11,1,0)*IF(D21='Оценка сложности задач'!$B$11,1,0)*'Оценка сложности задач'!$G$11) + (IF(C21='Оценка сложности задач'!$A$12,1,0)*IF(D21='Оценка сложности задач'!$B$12,1,0)*'Оценка сложности задач'!$G$12) + (IF(C21='Оценка сложности задач'!$A$13,1,0)*IF(D21='Оценка сложности задач'!$B$13,1,0)*'Оценка сложности задач'!$G$13) + (IF(C21='Оценка сложности задач'!$A$14,1,0)*IF(D21='Оценка сложности задач'!$B$14,1,0)*'Оценка сложности задач'!$G$14) + (IF(C21='Оценка сложности задач'!$A$15,1,0)*IF(D21='Оценка сложности задач'!$B$15,1,0)*'Оценка сложности задач'!$G$15) + (IF(C21='Оценка сложности задач'!$A$16,1,0)*IF(D21='Оценка сложности задач'!$B$16,1,0)*'Оценка сложности задач'!$G$16) + (IF(C21='Оценка сложности задач'!$A$17,1,0)*IF(D21='Оценка сложности задач'!$B$17,1,0)*'Оценка сложности задач'!$G$17) + (IF(C21='Оценка сложности задач'!$A$18,1,0)*IF(D21='Оценка сложности задач'!$B$18,1,0)*'Оценка сложности задач'!$G$18) + (IF(C21='Оценка сложности задач'!$A$19,1,0)*IF(D21='Оценка сложности задач'!$B$19,1,0)*'Оценка сложности задач'!$G$19)+(IF(C21='Оценка сложности задач'!$A$20,1,0)*IF(D21='Оценка сложности задач'!$B$20,1,0)*'Оценка сложности задач'!$G$20)+(IF(C21='Оценка сложности задач'!$A$21,1,0)*IF(D21='Оценка сложности задач'!$B$21,1,0)*'Оценка сложности задач'!$G$21)+(IF(C21='Оценка сложности задач'!$A$22,1,0)*IF(D21='Оценка сложности задач'!$B$22,1,0)*'Оценка сложности задач'!$G$22)+(IF(C21='Оценка сложности задач'!$A$23,1,0)*IF(D21='Оценка сложности задач'!$B$23,1,0)*'Оценка сложности задач'!$G$23)+(IF(C21='Оценка сложности задач'!$A$24,1,0)*IF(D21='Оценка сложности задач'!$B$24,1,0)*'Оценка сложности задач'!$G$24)+(IF(C21='Оценка сложности задач'!$A$25,1,0)*IF(D21='Оценка сложности задач'!$B$25,1,0)*'Оценка сложности задач'!$G$25)+(IF(C21='Оценка сложности задач'!$A$26,1,0)*IF(D21='Оценка сложности задач'!$B$26,1,0)*'Оценка сложности задач'!$G$26)+(IF(C21='Оценка сложности задач'!$A$27,1,0)*IF(D21='Оценка сложности задач'!$B$27,1,0)*'Оценка сложности задач'!$G$27)+(IF(C21='Оценка сложности задач'!$A$28,1,0)*IF(D21='Оценка сложности задач'!$B$28,1,0)*'Оценка сложности задач'!$G$28)+(IF(C21='Оценка сложности задач'!$A$29,1,0)*IF(D21='Оценка сложности задач'!$B$29,1,0)*'Оценка сложности задач'!$G$29)+(IF(C21='Оценка сложности задач'!$A$30,1,0)*IF(D21='Оценка сложности задач'!$B$30,1,0)*'Оценка сложности задач'!$G$30)+(IF(C21='Оценка сложности задач'!$A$31,1,0)*IF(D21='Оценка сложности задач'!$B$31,1,0)*'Оценка сложности задач'!$G$31)+(IF(C21='Оценка сложности задач'!$A$32,1,0)*IF(D21='Оценка сложности задач'!$B$32,1,0)*'Оценка сложности задач'!$G$32)+(IF(C21='Оценка сложности задач'!$A$33,1,0)*IF(D21='Оценка сложности задач'!$B$33,1,0)*'Оценка сложности задач'!$G$33)+(IF(C21='Оценка сложности задач'!$A$34,1,0)*IF(D21='Оценка сложности задач'!$B$34,1,0)*'Оценка сложности задач'!$G$34)+(IF(C21='Оценка сложности задач'!$A$35,1,0)*IF(D21='Оценка сложности задач'!$B$35,1,0)*'Оценка сложности задач'!$G$35)+(IF(C21='Оценка сложности задач'!$A$36,1,0)*IF(D21='Оценка сложности задач'!$B$36,1,0)*'Оценка сложности задач'!$G$36)+(IF(C21='Оценка сложности задач'!$A$37,1,0)*IF(D21='Оценка сложности задач'!$B$37,1,0)*'Оценка сложности задач'!$G$37)+(IF(C21='Оценка сложности задач'!$A$38,1,0)*IF(D21='Оценка сложности задач'!$B$38,1,0)*'Оценка сложности задач'!$G$38)+(IF(C21='Оценка сложности задач'!$A$39,1,0)*IF(D21='Оценка сложности задач'!$B$39,1,0)*'Оценка сложности задач'!$G$39)+(IF(C21='Оценка сложности задач'!$A$40,1,0)*IF(D21='Оценка сложности задач'!$B$40,1,0)*'Оценка сложности задач'!$G$40) -> 0
A22: 19 | E22: =(IF(C22='Оценка сложности задач'!$A$2,1,0)*IF(D22='Оценка сложности задач'!$B$2,1,0)*'Оценка сложности задач'!$G$2)+(IF(C22='Оценка сложности задач'!$A$3,1,0)*IF(D22='Оценка сложности задач'!$B$3,1,0)*'Оценка сложности задач'!$G$3)+(IF(C22='Оценка сложности задач'!$A$4,1,0)*IF(D22='Оценка сложности задач'!$B$4,1,0)*'Оценка сложности задач'!$G$4)+(IF(C22='Оценка сложности задач'!$A$5,1,0)*IF(D22='Оценка сложности задач'!$B$5,1,0)*'Оценка сложности задач'!$G$5)+(IF(C22='Оценка сложности задач'!$A$6,1,0)*IF(D22='Оценка сложности задач'!$B$6,1,0)*'Оценка сложности задач'!$G$6)+(IF(C22='Оценка сложности задач'!$A$7,1,0)*IF(D22='Оценка сложности задач'!$B$7,1,0)*'Оценка сложности задач'!$G$7)+(IF(C22='Оценка сложности задач'!$A$8,1,0)*IF(D22='Оценка сложности задач'!$B$8,1,0)*'Оценка сложности задач'!$G$8)+(IF(C22='Оценка сложности задач'!$A$10,1,0)*IF(D22='Оценка сложности задач'!$B$10,1,0)*'Оценка сложности задач'!$G$10)+(IF(C22='Оценка сложности задач'!$A$9,1,0)*IF(D22='Оценка сложности задач'!$B$9,1,0)*'Оценка сложности задач'!$G$9)+ (IF(C22='Оценка сложности задач'!$A$11,1,0)*IF(D22='Оценка сложности задач'!$B$11,1,0)*'Оценка сложности задач'!$G$11) + (IF(C22='Оценка сложности задач'!$A$12,1,0)*IF(D22='Оценка сложности задач'!$B$12,1,0)*'Оценка сложности задач'!$G$12) + (IF(C22='Оценка сложности задач'!$A$13,1,0)*IF(D22='Оценка сложности задач'!$B$13,1,0)*'Оценка сложности задач'!$G$13) + (IF(C22='Оценка сложности задач'!$A$14,1,0)*IF(D22='Оценка сложности задач'!$B$14,1,0)*'Оценка сложности задач'!$G$14) + (IF(C22='Оценка сложности задач'!$A$15,1,0)*IF(D22='Оценка сложности задач'!$B$15,1,0)*'Оценка сложности задач'!$G$15) + (IF(C22='Оценка сложности задач'!$A$16,1,0)*IF(D22='Оценка сложности задач'!$B$16,1,0)*'Оценка сложности задач'!$G$16) + (IF(C22='Оценка сложности задач'!$A$17,1,0)*IF(D22='Оценка сложности задач'!$B$17,1,0)*'Оценка сложности задач'!$G$17) + (IF(C22='Оценка сложности задач'!$A$18,1,0)*IF(D22='Оценка сложности задач'!$B$18,1,0)*'Оценка сложности задач'!$G$18) + (IF(C22='Оценка сложности задач'!$A$19,1,0)*IF(D22='Оценка сложности задач'!$B$19,1,0)*'Оценка сложности задач'!$G$19)+(IF(C22='Оценка сложности задач'!$A$20,1,0)*IF(D22='Оценка сложности задач'!$B$20,1,0)*'Оценка сложности задач'!$G$20)+(IF(C22='Оценка сложности задач'!$A$21,1,0)*IF(D22='Оценка сложности задач'!$B$21,1,0)*'Оценка сложности задач'!$G$21)+(IF(C22='Оценка сложности задач'!$A$22,1,0)*IF(D22='Оценка сложности задач'!$B$22,1,0)*'Оценка сложности задач'!$G$22)+(IF(C22='Оценка сложности задач'!$A$23,1,0)*IF(D22='Оценка сложности задач'!$B$23,1,0)*'Оценка сложности задач'!$G$23)+(IF(C22='Оценка сложности задач'!$A$24,1,0)*IF(D22='Оценка сложности задач'!$B$24,1,0)*'Оценка сложности задач'!$G$24)+(IF(C22='Оценка сложности задач'!$A$25,1,0)*IF(D22='Оценка сложности задач'!$B$25,1,0)*'Оценка сложности задач'!$G$25)+(IF(C22='Оценка сложности задач'!$A$26,1,0)*IF(D22='Оценка сложности задач'!$B$26,1,0)*'Оценка сложности задач'!$G$26)+(IF(C22='Оценка сложности задач'!$A$27,1,0)*IF(D22='Оценка сложности задач'!$B$27,1,0)*'Оценка сложности задач'!$G$27)+(IF(C22='Оценка сложности задач'!$A$28,1,0)*IF(D22='Оценка сложности задач'!$B$28,1,0)*'Оценка сложности задач'!$G$28)+(IF(C22='Оценка сложности задач'!$A$29,1,0)*IF(D22='Оценка сложности задач'!$B$29,1,0)*'Оценка сложности задач'!$G$29)+(IF(C22='Оценка сложности задач'!$A$30,1,0)*IF(D22='Оценка сложности задач'!$B$30,1,0)*'Оценка сложности задач'!$G$30)+(IF(C22='Оценка сложности задач'!$A$31,1,0)*IF(D22='Оценка сложности задач'!$B$31,1,0)*'Оценка сложности задач'!$G$31)+(IF(C22='Оценка сложности задач'!$A$32,1,0)*IF(D22='Оценка сложности задач'!$B$32,1,0)*'Оценка сложности задач'!$G$32)+(IF(C22='Оценка сложности задач'!$A$33,1,0)*IF(D22='Оценка сложности задач'!$B$33,1,0)*'Оценка сложности задач'!$G$33)+(IF(C22='Оценка сложности задач'!$A$34,1,0)*IF(D22='Оценка сложности задач'!$B$34,1,0)*'Оценка сложности задач'!$G$34)+(IF(C22='Оценка сложности задач'!$A$35,1,0)*IF(D22='Оценка сложности задач'!$B$35,1,0)*'Оценка сложности задач'!$G$35)+(IF(C22='Оценка сложности задач'!$A$36,1,0)*IF(D22='Оценка сложности задач'!$B$36,1,0)*'Оценка сложности задач'!$G$36)+(IF(C22='Оценка сложности задач'!$A$37,1,0)*IF(D22='Оценка сложности задач'!$B$37,1,0)*'Оценка сложности задач'!$G$37)+(IF(C22='Оценка сложности задач'!$A$38,1,0)*IF(D22='Оценка сложности задач'!$B$38,1,0)*'Оценка сложности задач'!$G$38)+(IF(C22='Оценка сложности задач'!$A$39,1,0)*IF(D22='Оценка сложности задач'!$B$39,1,0)*'Оценка сложности задач'!$G$39)+(IF(C22='Оценка сложности задач'!$A$40,1,0)*IF(D22='Оценка сложности задач'!$B$40,1,0)*'Оценка сложности задач'!$G$40) -> 0
A23: 20 | E23: =(IF(C23='Оценка сложности задач'!$A$2,1,0)*IF(D23='Оценка сложности задач'!$B$2,1,0)*'Оценка сложности задач'!$G$2)+(IF(C23='Оценка сложности задач'!$A$3,1,0)*IF(D23='Оценка сложности задач'!$B$3,1,0)*'Оценка сложности задач'!$G$3)+(IF(C23='Оценка сложности задач'!$A$4,1,0)*IF(D23='Оценка сложности задач'!$B$4,1,0)*'Оценка сложности задач'!$G$4)+(IF(C23='Оценка сложности задач'!$A$5,1,0)*IF(D23='Оценка сложности задач'!$B$5,1,0)*'Оценка сложности задач'!$G$5)+(IF(C23='Оценка сложности задач'!$A$6,1,0)*IF(D23='Оценка сложности задач'!$B$6,1,0)*'Оценка сложности задач'!$G$6)+(IF(C23='Оценка сложности задач'!$A$7,1,0)*IF(D23='Оценка сложности задач'!$B$7,1,0)*'Оценка сложности задач'!$G$7)+(IF(C23='Оценка сложности задач'!$A$8,1,0)*IF(D23='Оценка сложности задач'!$B$8,1,0)*'Оценка сложности задач'!$G$8)+(IF(C23='Оценка сложности задач'!$A$10,1,0)*IF(D23='Оценка сложности задач'!$B$10,1,0)*'Оценка сложности задач'!$G$10)+(IF(C23='Оценка сложности задач'!$A$9,1,0)*IF(D23='Оценка сложности задач'!$B$9,1,0)*'Оценка сложности задач'!$G$9)+ (IF(C23='Оценка сложности задач'!$A$11,1,0)*IF(D23='Оценка сложности задач'!$B$11,1,0)*'Оценка сложности задач'!$G$11) + (IF(C23='Оценка сложности задач'!$A$12,1,0)*IF(D23='Оценка сложности задач'!$B$12,1,0)*'Оценка сложности задач'!$G$12) + (IF(C23='Оценка сложности задач'!$A$13,1,0)*IF(D23='Оценка сложности задач'!$B$13,1,0)*'Оценка сложности задач'!$G$13) + (IF(C23='Оценка сложности задач'!$A$14,1,0)*IF(D23='Оценка сложности задач'!$B$14,1,0)*'Оценка сложности задач'!$G$14) + (IF(C23='Оценка сложности задач'!$A$15,1,0)*IF(D23='Оценка сложности задач'!$B$15,1,0)*'Оценка сложности задач'!$G$15) + (IF(C23='Оценка сложности задач'!$A$16,1,0)*IF(D23='Оценка сложности задач'!$B$16,1,0)*'Оценка сложности задач'!$G$16) + (IF(C23='Оценка сложности задач'!$A$17,1,0)*IF(D23='Оценка сложности задач'!$B$17,1,0)*'Оценка сложности задач'!$G$17) + (IF(C23='Оценка сложности задач'!$A$18,1,0)*IF(D23='Оценка сложности задач'!$B$18,1,0)*'Оценка сложности задач'!$G$18) + (IF(C23='Оценка сложности задач'!$A$19,1,0)*IF(D23='Оценка сложности задач'!$B$19,1,0)*'Оценка сложности задач'!$G$19)+(IF(C23='Оценка сложности задач'!$A$20,1,0)*IF(D23='Оценка сложности задач'!$B$20,1,0)*'Оценка сложности задач'!$G$20)+(IF(C23='Оценка сложности задач'!$A$21,1,0)*IF(D23='Оценка сложности задач'!$B$21,1,0)*'Оценка сложности задач'!$G$21)+(IF(C23='Оценка сложности задач'!$A$22,1,0)*IF(D23='Оценка сложности задач'!$B$22,1,0)*'Оценка сложности задач'!$G$22)+(IF(C23='Оценка сложности задач'!$A$23,1,0)*IF(D23='Оценка сложности задач'!$B$23,1,0)*'Оценка сложности задач'!$G$23)+(IF(C23='Оценка сложности задач'!$A$24,1,0)*IF(D23='Оценка сложности задач'!$B$24,1,0)*'Оценка сложности задач'!$G$24)+(IF(C23='Оценка сложности задач'!$A$25,1,0)*IF(D23='Оценка сложности задач'!$B$25,1,0)*'Оценка сложности задач'!$G$25)+(IF(C23='Оценка сложности задач'!$A$26,1,0)*IF(D23='Оценка сложности задач'!$B$26,1,0)*'Оценка сложности задач'!$G$26)+(IF(C23='Оценка сложности задач'!$A$27,1,0)*IF(D23='Оценка сложности задач'!$B$27,1,0)*'Оценка сложности задач'!$G$27)+(IF(C23='Оценка сложности задач'!$A$28,1,0)*IF(D23='Оценка сложности задач'!$B$28,1,0)*'Оценка сложности задач'!$G$28)+(IF(C23='Оценка сложности задач'!$A$29,1,0)*IF(D23='Оценка сложности задач'!$B$29,1,0)*'Оценка сложности задач'!$G$29)+(IF(C23='Оценка сложности задач'!$A$30,1,0)*IF(D23='Оценка сложности задач'!$B$30,1,0)*'Оценка сложности задач'!$G$30)+(IF(C23='Оценка сложности задач'!$A$31,1,0)*IF(D23='Оценка сложности задач'!$B$31,1,0)*'Оценка сложности задач'!$G$31)+(IF(C23='Оценка сложности задач'!$A$32,1,0)*IF(D23='Оценка сложности задач'!$B$32,1,0)*'Оценка сложности задач'!$G$32)+(IF(C23='Оценка сложности задач'!$A$33,1,0)*IF(D23='Оценка сложности задач'!$B$33,1,0)*'Оценка сложности задач'!$G$33)+(IF(C23='Оценка сложности задач'!$A$34,1,0)*IF(D23='Оценка сложности задач'!$B$34,1,0)*'Оценка сложности задач'!$G$34)+(IF(C23='Оценка сложности задач'!$A$35,1,0)*IF(D23='Оценка сложности задач'!$B$35,1,0)*'Оценка сложности задач'!$G$35)+(IF(C23='Оценка сложности задач'!$A$36,1,0)*IF(D23='Оценка сложности задач'!$B$36,1,0)*'Оценка сложности задач'!$G$36)+(IF(C23='Оценка сложности задач'!$A$37,1,0)*IF(D23='Оценка сложности задач'!$B$37,1,0)*'Оценка сложности задач'!$G$37)+(IF(C23='Оценка сложности задач'!$A$38,1,0)*IF(D23='Оценка сложности задач'!$B$38,1,0)*'Оценка сложности задач'!$G$38)+(IF(C23='Оценка сложности задач'!$A$39,1,0)*IF(D23='Оценка сложности задач'!$B$39,1,0)*'Оценка сложности задач'!$G$39)+(IF(C23='Оценка сложности задач'!$A$40,1,0)*IF(D23='Оценка сложности задач'!$B$40,1,0)*'Оценка сложности задач'!$G$40) -> 0
A24: 21 | E24: =(IF(C24='Оценка сложности задач'!$A$2,1,0)*IF(D24='Оценка сложности задач'!$B$2,1,0)*'Оценка сложности задач'!$G$2)+(IF(C24='Оценка сложности задач'!$A$3,1,0)*IF(D24='Оценка сложности задач'!$B$3,1,0)*'Оценка сложности задач'!$G$3)+(IF(C24='Оценка сложности задач'!$A$4,1,0)*IF(D24='Оценка сложности задач'!$B$4,1,0)*'Оценка сложности задач'!$G$4)+(IF(C24='Оценка сложности задач'!$A$5,1,0)*IF(D24='Оценка сложности задач'!$B$5,1,0)*'Оценка сложности задач'!$G$5)+(IF(C24='Оценка сложности задач'!$A$6,1,0)*IF(D24='Оценка сложности задач'!$B$6,1,0)*'Оценка сложности задач'!$G$6)+(IF(C24='Оценка сложности задач'!$A$7,1,0)*IF(D24='Оценка сложности задач'!$B$7,1,0)*'Оценка сложности задач'!$G$7)+(IF(C24='Оценка сложности задач'!$A$8,1,0)*IF(D24='Оценка сложности задач'!$B$8,1,0)*'Оценка сложности задач'!$G$8)+(IF(C24='Оценка сложности задач'!$A$10,1,0)*IF(D24='Оценка сложности задач'!$B$10,1,0)*'Оценка сложности задач'!$G$10)+(IF(C24='Оценка сложности задач'!$A$9,1,0)*IF(D24='Оценка сложности задач'!$B$9,1,0)*'Оценка сложности задач'!$G$9)+ (IF(C24='Оценка сложности задач'!$A$11,1,0)*IF(D24='Оценка сложности задач'!$B$11,1,0)*'Оценка сложности задач'!$G$11) + (IF(C24='Оценка сложности задач'!$A$12,1,0)*IF(D24='Оценка сложности задач'!$B$12,1,0)*'Оценка сложности задач'!$G$12) + (IF(C24='Оценка сложности задач'!$A$13,1,0)*IF(D24='Оценка сложности задач'!$B$13,1,0)*'Оценка сложности задач'!$G$13) + (IF(C24='Оценка сложности задач'!$A$14,1,0)*IF(D24='Оценка сложности задач'!$B$14,1,0)*'Оценка сложности задач'!$G$14) + (IF(C24='Оценка сложности задач'!$A$15,1,0)*IF(D24='Оценка сложности задач'!$B$15,1,0)*'Оценка сложности задач'!$G$15) + (IF(C24='Оценка сложности задач'!$A$16,1,0)*IF(D24='Оценка сложности задач'!$B$16,1,0)*'Оценка сложности задач'!$G$16) + (IF(C24='Оценка сложности задач'!$A$17,1,0)*IF(D24='Оценка сложности задач'!$B$17,1,0)*'Оценка сложности задач'!$G$17) + (IF(C24='Оценка сложности задач'!$A$18,1,0)*IF(D24='Оценка сложности задач'!$B$18,1,0)*'Оценка сложности задач'!$G$18) + (IF(C24='Оценка сложности задач'!$A$19,1,0)*IF(D24='Оценка сложности задач'!$B$19,1,0)*'Оценка сложности задач'!$G$19)+(IF(C24='Оценка сложности задач'!$A$20,1,0)*IF(D24='Оценка сложности задач'!$B$20,1,0)*'Оценка сложности задач'!$G$20)+(IF(C24='Оценка сложности задач'!$A$21,1,0)*IF(D24='Оценка сложности задач'!$B$21,1,0)*'Оценка сложности задач'!$G$21)+(IF(C24='Оценка сложности задач'!$A$22,1,0)*IF(D24='Оценка сложности задач'!$B$22,1,0)*'Оценка сложности задач'!$G$22)+(IF(C24='Оценка сложности задач'!$A$23,1,0)*IF(D24='Оценка сложности задач'!$B$23,1,0)*'Оценка сложности задач'!$G$23)+(IF(C24='Оценка сложности задач'!$A$24,1,0)*IF(D24='Оценка сложности задач'!$B$24,1,0)*'Оценка сложности задач'!$G$24)+(IF(C24='Оценка сложности задач'!$A$25,1,0)*IF(D24='Оценка сложности задач'!$B$25,1,0)*'Оценка сложности задач'!$G$25)+(IF(C24='Оценка сложности задач'!$A$26,1,0)*IF(D24='Оценка сложности задач'!$B$26,1,0)*'Оценка сложности задач'!$G$26)+(IF(C24='Оценка сложности задач'!$A$27,1,0)*IF(D24='Оценка сложности задач'!$B$27,1,0)*'Оценка сложности задач'!$G$27)+(IF(C24='Оценка сложности задач'!$A$28,1,0)*IF(D24='Оценка сложности задач'!$B$28,1,0)*'Оценка сложности задач'!$G$28)+(IF(C24='Оценка сложности задач'!$A$29,1,0)*IF(D24='Оценка сложности задач'!$B$29,1,0)*'Оценка сложности задач'!$G$29)+(IF(C24='Оценка сложности задач'!$A$30,1,0)*IF(D24='Оценка сложности задач'!$B$30,1,0)*'Оценка сложности задач'!$G$30)+(IF(C24='Оценка сложности задач'!$A$31,1,0)*IF(D24='Оценка сложности задач'!$B$31,1,0)*'Оценка сложности задач'!$G$31)+(IF(C24='Оценка сложности задач'!$A$32,1,0)*IF(D24='Оценка сложности задач'!$B$32,1,0)*'Оценка сложности задач'!$G$32)+(IF(C24='Оценка сложности задач'!$A$33,1,0)*IF(D24='Оценка сложности задач'!$B$33,1,0)*'Оценка сложности задач'!$G$33)+(IF(C24='Оценка сложности задач'!$A$34,1,0)*IF(D24='Оценка сложности задач'!$B$34,1,0)*'Оценка сложности задач'!$G$34)+(IF(C24='Оценка сложности задач'!$A$35,1,0)*IF(D24='Оценка сложности задач'!$B$35,1,0)*'Оценка сложности задач'!$G$35)+(IF(C24='Оценка сложности задач'!$A$36,1,0)*IF(D24='Оценка сложности задач'!$B$36,1,0)*'Оценка сложности задач'!$G$36)+(IF(C24='Оценка сложности задач'!$A$37,1,0)*IF(D24='Оценка сложности задач'!$B$37,1,0)*'Оценка сложности задач'!$G$37)+(IF(C24='Оценка сложности задач'!$A$38,1,0)*IF(D24='Оценка сложности задач'!$B$38,1,0)*'Оценка сложности задач'!$G$38)+(IF(C24='Оценка сложности задач'!$A$39,1,0)*IF(D24='Оценка сложности задач'!$B$39,1,0)*'Оценка сложности задач'!$G$39)+(IF(C24='Оценка сложности задач'!$A$40,1,0)*IF(D24='Оценка сложности задач'!$B$40,1,0)*'Оценка сложности задач'!$G$40) -> 0
A25: 22 | E25: =(IF(C25='Оценка сложности задач'!$A$2,1,0)*IF(D25='Оценка сложности задач'!$B$2,1,0)*'Оценка сложности задач'!$G$2)+(IF(C25='Оценка сложности задач'!$A$3,1,0)*IF(D25='Оценка сложности задач'!$B$3,1,0)*'Оценка сложности задач'!$G$3)+(IF(C25='Оценка сложности задач'!$A$4,1,0)*IF(D25='Оценка сложности задач'!$B$4,1,0)*'Оценка сложности задач'!$G$4)+(IF(C25='Оценка сложности задач'!$A$5,1,0)*IF(D25='Оценка сложности задач'!$B$5,1,0)*'Оценка сложности задач'!$G$5)+(IF(C25='Оценка сложности задач'!$A$6,1,0)*IF(D25='Оценка сложности задач'!$B$6,1,0)*'Оценка сложности задач'!$G$6)+(IF(C25='Оценка сложности задач'!$A$7,1,0)*IF(D25='Оценка сложности задач'!$B$7,1,0)*'Оценка сложности задач'!$G$7)+(IF(C25='Оценка сложности задач'!$A$8,1,0)*IF(D25='Оценка сложности задач'!$B$8,1,0)*'Оценка сложности задач'!$G$8)+(IF(C25='Оценка сложности задач'!$A$10,1,0)*IF(D25='Оценка сложности задач'!$B$10,1,0)*'Оценка сложности задач'!$G$10)+(IF(C25='Оценка сложности задач'!$A$9,1,0)*IF(D25='Оценка сложности задач'!$B$9,1,0)*'Оценка сложности задач'!$G$9)+ (IF(C25='Оценка сложности задач'!$A$11,1,0)*IF(D25='Оценка сложности задач'!$B$11,1,0)*'Оценка сложности задач'!$G$11) + (IF(C25='Оценка сложности задач'!$A$12,1,0)*IF(D25='Оценка сложности задач'!$B$12,1,0)*'Оценка сложности задач'!$G$12) + (IF(C25='Оценка сложности задач'!$A$13,1,0)*IF(D25='Оценка сложности задач'!$B$13,1,0)*'Оценка сложности задач'!$G$13) + (IF(C25='Оценка сложности задач'!$A$14,1,0)*IF(D25='Оценка сложности задач'!$B$14,1,0)*'Оценка сложности задач'!$G$14) + (IF(C25='Оценка сложности задач'!$A$15,1,0)*IF(D25='Оценка сложности задач'!$B$15,1,0)*'Оценка сложности задач'!$G$15) + (IF(C25='Оценка сложности задач'!$A$16,1,0)*IF(D25='Оценка сложности задач'!$B$16,1,0)*'Оценка сложности задач'!$G$16) + (IF(C25='Оценка сложности задач'!$A$17,1,0)*IF(D25='Оценка сложности задач'!$B$17,1,0)*'Оценка сложности задач'!$G$17) + (IF(C25='Оценка сложности задач'!$A$18,1,0)*IF(D25='Оценка сложности задач'!$B$18,1,0)*'Оценка сложности задач'!$G$18) + (IF(C25='Оценка сложности задач'!$A$19,1,0)*IF(D25='Оценка сложности задач'!$B$19,1,0)*'Оценка сложности задач'!$G$19)+(IF(C25='Оценка сложности задач'!$A$20,1,0)*IF(D25='Оценка сложности задач'!$B$20,1,0)*'Оценка сложности задач'!$G$20)+(IF(C25='Оценка сложности задач'!$A$21,1,0)*IF(D25='Оценка сложности задач'!$B$21,1,0)*'Оценка сложности задач'!$G$21)+(IF(C25='Оценка сложности задач'!$A$22,1,0)*IF(D25='Оценка сложности задач'!$B$22,1,0)*'Оценка сложности задач'!$G$22)+(IF(C25='Оценка сложности задач'!$A$23,1,0)*IF(D25='Оценка сложности задач'!$B$23,1,0)*'Оценка сложности задач'!$G$23)+(IF(C25='Оценка сложности задач'!$A$24,1,0)*IF(D25='Оценка сложности задач'!$B$24,1,0)*'Оценка сложности задач'!$G$24)+(IF(C25='Оценка сложности задач'!$A$25,1,0)*IF(D25='Оценка сложности задач'!$B$25,1,0)*'Оценка сложности задач'!$G$25)+(IF(C25='Оценка сложности задач'!$A$26,1,0)*IF(D25='Оценка сложности задач'!$B$26,1,0)*'Оценка сложности задач'!$G$26)+(IF(C25='Оценка сложности задач'!$A$27,1,0)*IF(D25='Оценка сложности задач'!$B$27,1,0)*'Оценка сложности задач'!$G$27)+(IF(C25='Оценка сложности задач'!$A$28,1,0)*IF(D25='Оценка сложности задач'!$B$28,1,0)*'Оценка сложности задач'!$G$28)+(IF(C25='Оценка сложности задач'!$A$29,1,0)*IF(D25='Оценка сложности задач'!$B$29,1,0)*'Оценка сложности задач'!$G$29)+(IF(C25='Оценка сложности задач'!$A$30,1,0)*IF(D25='Оценка сложности задач'!$B$30,1,0)*'Оценка сложности задач'!$G$30)+(IF(C25='Оценка сложности задач'!$A$31,1,0)*IF(D25='Оценка сложности задач'!$B$31,1,0)*'Оценка сложности задач'!$G$31)+(IF(C25='Оценка сложности задач'!$A$32,1,0)*IF(D25='Оценка сложности задач'!$B$32,1,0)*'Оценка сложности задач'!$G$32)+(IF(C25='Оценка сложности задач'!$A$33,1,0)*IF(D25='Оценка сложности задач'!$B$33,1,0)*'Оценка сложности задач'!$G$33)+(IF(C25='Оценка сложности задач'!$A$34,1,0)*IF(D25='Оценка сложности задач'!$B$34,1,0)*'Оценка сложности задач'!$G$34)+(IF(C25='Оценка сложности задач'!$A$35,1,0)*IF(D25='Оценка сложности задач'!$B$35,1,0)*'Оценка сложности задач'!$G$35)+(IF(C25='Оценка сложности задач'!$A$36,1,0)*IF(D25='Оценка сложности задач'!$B$36,1,0)*'Оценка сложности задач'!$G$36)+(IF(C25='Оценка сложности задач'!$A$37,1,0)*IF(D25='Оценка сложности задач'!$B$37,1,0)*'Оценка сложности задач'!$G$37)+(IF(C25='Оценка сложности задач'!$A$38,1,0)*IF(D25='Оценка сложности задач'!$B$38,1,0)*'Оценка сложности задач'!$G$38)+(IF(C25='Оценка сложности задач'!$A$39,1,0)*IF(D25='Оценка сложности задач'!$B$39,1,0)*'Оценка сложности задач'!$G$39)+(IF(C25='Оценка сложности задач'!$A$40,1,0)*IF(D25='Оценка сложности задач'!$B$40,1,0)*'Оценка сложности задач'!$G$40) -> 0
A26: 23 | E26: =(IF(C26='Оценка сложности задач'!$A$2,1,0)*IF(D26='Оценка сложности задач'!$B$2,1,0)*'Оценка сложности задач'!$G$2)+(IF(C26='Оценка сложности задач'!$A$3,1,0)*IF(D26='Оценка сложности задач'!$B$3,1,0)*'Оценка сложности задач'!$G$3)+(IF(C26='Оценка сложности задач'!$A$4,1,0)*IF(D26='Оценка сложности задач'!$B$4,1,0)*'Оценка сложности задач'!$G$4)+(IF(C26='Оценка сложности задач'!$A$5,1,0)*IF(D26='Оценка сложности задач'!$B$5,1,0)*'Оценка сложности задач'!$G$5)+(IF(C26='Оценка сложности задач'!$A$6,1,0)*IF(D26='Оценка сложности задач'!$B$6,1,0)*'Оценка сложности задач'!$G$6)+(IF(C26='Оценка сложности задач'!$A$7,1,0)*IF(D26='Оценка сложности задач'!$B$7,1,0)*'Оценка сложности задач'!$G$7)+(IF(C26='Оценка сложности задач'!$A$8,1,0)*IF(D26='Оценка сложности задач'!$B$8,1,0)*'Оценка сложности задач'!$G$8)+(IF(C26='Оценка сложности задач'!$A$10,1,0)*IF(D26='Оценка сложности задач'!$B$10,1,0)*'Оценка сложности задач'!$G$10)+(IF(C26='Оценка сложности задач'!$A$9,1,0)*IF(D26='Оценка сложности задач'!$B$9,1,0)*'Оценка сложности задач'!$G$9)+ (IF(C26='Оценка сложности задач'!$A$11,1,0)*IF(D26='Оценка сложности задач'!$B$11,1,0)*'Оценка сложности задач'!$G$11) + (IF(C26='Оценка сложности задач'!$A$12,1,0)*IF(D26='Оценка сложности задач'!$B$12,1,0)*'Оценка сложности задач'!$G$12) + (IF(C26='Оценка сложности задач'!$A$13,1,0)*IF(D26='Оценка сложности задач'!$B$13,1,0)*'Оценка сложности задач'!$G$13) + (IF(C26='Оценка сложности задач'!$A$14,1,0)*IF(D26='Оценка сложности задач'!$B$14,1,0)*'Оценка сложности задач'!$G$14) + (IF(C26='Оценка сложности задач'!$A$15,1,0)*IF(D26='Оценка сложности задач'!$B$15,1,0)*'Оценка сложности задач'!$G$15) + (IF(C26='Оценка сложности задач'!$A$16,1,0)*IF(D26='Оценка сложности задач'!$B$16,1,0)*'Оценка сложности задач'!$G$16) + (IF(C26='Оценка сложности задач'!$A$17,1,0)*IF(D26='Оценка сложности задач'!$B$17,1,0)*'Оценка сложности задач'!$G$17) + (IF(C26='Оценка сложности задач'!$A$18,1,0)*IF(D26='Оценка сложности задач'!$B$18,1,0)*'Оценка сложности задач'!$G$18) + (IF(C26='Оценка сложности задач'!$A$19,1,0)*IF(D26='Оценка сложности задач'!$B$19,1,0)*'Оценка сложности задач'!$G$19)+(IF(C26='Оценка сложности задач'!$A$20,1,0)*IF(D26='Оценка сложности задач'!$B$20,1,0)*'Оценка сложности задач'!$G$20)+(IF(C26='Оценка сложности задач'!$A$21,1,0)*IF(D26='Оценка сложности задач'!$B$21,1,0)*'Оценка сложности задач'!$G$21)+(IF(C26='Оценка сложности задач'!$A$22,1,0)*IF(D26='Оценка сложности задач'!$B$22,1,0)*'Оценка сложности задач'!$G$22)+(IF(C26='Оценка сложности задач'!$A$23,1,0)*IF(D26='Оценка сложности задач'!$B$23,1,0)*'Оценка сложности задач'!$G$23)+(IF(C26='Оценка сложности задач'!$A$24,1,0)*IF(D26='Оценка сложности задач'!$B$24,1,0)*'Оценка сложности задач'!$G$24)+(IF(C26='Оценка сложности задач'!$A$25,1,0)*IF(D26='Оценка сложности задач'!$B$25,1,0)*'Оценка сложности задач'!$G$25)+(IF(C26='Оценка сложности задач'!$A$26,1,0)*IF(D26='Оценка сложности задач'!$B$26,1,0)*'Оценка сложности задач'!$G$26)+(IF(C26='Оценка сложности задач'!$A$27,1,0)*IF(D26='Оценка сложности задач'!$B$27,1,0)*'Оценка сложности задач'!$G$27)+(IF(C26='Оценка сложности задач'!$A$28,1,0)*IF(D26='Оценка сложности задач'!$B$28,1,0)*'Оценка сложности задач'!$G$28)+(IF(C26='Оценка сложности задач'!$A$29,1,0)*IF(D26='Оценка сложности задач'!$B$29,1,0)*'Оценка сложности задач'!$G$29)+(IF(C26='Оценка сложности задач'!$A$30,1,0)*IF(D26='Оценка сложности задач'!$B$30,1,0)*'Оценка сложности задач'!$G$30)+(IF(C26='Оценка сложности задач'!$A$31,1,0)*IF(D26='Оценка сложности задач'!$B$31,1,0)*'Оценка сложности задач'!$G$31)+(IF(C26='Оценка сложности задач'!$A$32,1,0)*IF(D26='Оценка сложности задач'!$B$32,1,0)*'Оценка сложности задач'!$G$32)+(IF(C26='Оценка сложности задач'!$A$33,1,0)*IF(D26='Оценка сложности задач'!$B$33,1,0)*'Оценка сложности задач'!$G$33)+(IF(C26='Оценка сложности задач'!$A$34,1,0)*IF(D26='Оценка сложности задач'!$B$34,1,0)*'Оценка сложности задач'!$G$34)+(IF(C26='Оценка сложности задач'!$A$35,1,0)*IF(D26='Оценка сложности задач'!$B$35,1,0)*'Оценка сложности задач'!$G$35)+(IF(C26='Оценка сложности задач'!$A$36,1,0)*IF(D26='Оценка сложности задач'!$B$36,1,0)*'Оценка сложности задач'!$G$36)+(IF(C26='Оценка сложности задач'!$A$37,1,0)*IF(D26='Оценка сложности задач'!$B$37,1,0)*'Оценка сложности задач'!$G$37)+(IF(C26='Оценка сложности задач'!$A$38,1,0)*IF(D26='Оценка сложности задач'!$B$38,1,0)*'Оценка сложности задач'!$G$38)+(IF(C26='Оценка сложности задач'!$A$39,1,0)*IF(D26='Оценка сложности задач'!$B$39,1,0)*'Оценка сложности задач'!$G$39)+(IF(C26='Оценка сложности задач'!$A$40,1,0)*IF(D26='Оценка сложности задач'!$B$40,1,0)*'Оценка сложности задач'!$G$40) -> 0
A27: 24 | E27: =(IF(C27='Оценка сложности задач'!$A$2,1,0)*IF(D27='Оценка сложности задач'!$B$2,1,0)*'Оценка сложности задач'!$G$2)+(IF(C27='Оценка сложности задач'!$A$3,1,0)*IF(D27='Оценка сложности задач'!$B$3,1,0)*'Оценка сложности задач'!$G$3)+(IF(C27='Оценка сложности задач'!$A$4,1,0)*IF(D27='Оценка сложности задач'!$B$4,1,0)*'Оценка сложности задач'!$G$4)+(IF(C27='Оценка сложности задач'!$A$5,1,0)*IF(D27='Оценка сложности задач'!$B$5,1,0)*'Оценка сложности задач'!$G$5)+(IF(C27='Оценка сложности задач'!$A$6,1,0)*IF(D27='Оценка сложности задач'!$B$6,1,0)*'Оценка сложности задач'!$G$6)+(IF(C27='Оценка сложности задач'!$A$7,1,0)*IF(D27='Оценка сложности задач'!$B$7,1,0)*'Оценка сложности задач'!$G$7)+(IF(C27='Оценка сложности задач'!$A$8,1,0)*IF(D27='Оценка сложности задач'!$B$8,1,0)*'Оценка сложности задач'!$G$8)+(IF(C27='Оценка сложности задач'!$A$10,1,0)*IF(D27='Оценка сложности задач'!$B$10,1,0)*'Оценка сложности задач'!$G$10)+(IF(C27='Оценка сложности задач'!$A$9,1,0)*IF(D27='Оценка сложности задач'!$B$9,1,0)*'Оценка сложности задач'!$G$9)+ (IF(C27='Оценка сложности задач'!$A$11,1,0)*IF(D27='Оценка сложности задач'!$B$11,1,0)*'Оценка сложности задач'!$G$11) + (IF(C27='Оценка сложности задач'!$A$12,1,0)*IF(D27='Оценка сложности задач'!$B$12,1,0)*'Оценка сложности задач'!$G$12) + (IF(C27='Оценка сложности задач'!$A$13,1,0)*IF(D27='Оценка сложности задач'!$B$13,1,0)*'Оценка сложности задач'!$G$13) + (IF(C27='Оценка сложности задач'!$A$14,1,0)*IF(D27='Оценка сложности задач'!$B$14,1,0)*'Оценка сложности задач'!$G$14) + (IF(C27='Оценка сложности задач'!$A$15,1,0)*IF(D27='Оценка сложности задач'!$B$15,1,0)*'Оценка сложности задач'!$G$15) + (IF(C27='Оценка сложности задач'!$A$16,1,0)*IF(D27='Оценка сложности задач'!$B$16,1,0)*'Оценка сложности задач'!$G$16) + (IF(C27='Оценка сложности задач'!$A$17,1,0)*IF(D27='Оценка сложности задач'!$B$17,1,0)*'Оценка сложности задач'!$G$17) + (IF(C27='Оценка сложности задач'!$A$18,1,0)*IF(D27='Оценка сложности задач'!$B$18,1,0)*'Оценка сложности задач'!$G$18) + (IF(C27='Оценка сложности задач'!$A$19,1,0)*IF(D27='Оценка сложности задач'!$B$19,1,0)*'Оценка сложности задач'!$G$19)+(IF(C27='Оценка сложности задач'!$A$20,1,0)*IF(D27='Оценка сложности задач'!$B$20,1,0)*'Оценка сложности задач'!$G$20)+(IF(C27='Оценка сложности задач'!$A$21,1,0)*IF(D27='Оценка сложности задач'!$B$21,1,0)*'Оценка сложности задач'!$G$21)+(IF(C27='Оценка сложности задач'!$A$22,1,0)*IF(D27='Оценка сложности задач'!$B$22,1,0)*'Оценка сложности задач'!$G$22)+(IF(C27='Оценка сложности задач'!$A$23,1,0)*IF(D27='Оценка сложности задач'!$B$23,1,0)*'Оценка сложности задач'!$G$23)+(IF(C27='Оценка сложности задач'!$A$24,1,0)*IF(D27='Оценка сложности задач'!$B$24,1,0)*'Оценка сложности задач'!$G$24)+(IF(C27='Оценка сложности задач'!$A$25,1,0)*IF(D27='Оценка сложности задач'!$B$25,1,0)*'Оценка сложности задач'!$G$25)+(IF(C27='Оценка сложности задач'!$A$26,1,0)*IF(D27='Оценка сложности задач'!$B$26,1,0)*'Оценка сложности задач'!$G$26)+(IF(C27='Оценка сложности задач'!$A$27,1,0)*IF(D27='Оценка сложности задач'!$B$27,1,0)*'Оценка сложности задач'!$G$27)+(IF(C27='Оценка сложности задач'!$A$28,1,0)*IF(D27='Оценка сложности задач'!$B$28,1,0)*'Оценка сложности задач'!$G$28)+(IF(C27='Оценка сложности задач'!$A$29,1,0)*IF(D27='Оценка сложности задач'!$B$29,1,0)*'Оценка сложности задач'!$G$29)+(IF(C27='Оценка сложности задач'!$A$30,1,0)*IF(D27='Оценка сложности задач'!$B$30,1,0)*'Оценка сложности задач'!$G$30)+(IF(C27='Оценка сложности задач'!$A$31,1,0)*IF(D27='Оценка сложности задач'!$B$31,1,0)*'Оценка сложности задач'!$G$31)+(IF(C27='Оценка сложности задач'!$A$32,1,0)*IF(D27='Оценка сложности задач'!$B$32,1,0)*'Оценка сложности задач'!$G$32)+(IF(C27='Оценка сложности задач'!$A$33,1,0)*IF(D27='Оценка сложности задач'!$B$33,1,0)*'Оценка сложности задач'!$G$33)+(IF(C27='Оценка сложности задач'!$A$34,1,0)*IF(D27='Оценка сложности задач'!$B$34,1,0)*'Оценка сложности задач'!$G$34)+(IF(C27='Оценка сложности задач'!$A$35,1,0)*IF(D27='Оценка сложности задач'!$B$35,1,0)*'Оценка сложности задач'!$G$35)+(IF(C27='Оценка сложности задач'!$A$36,1,0)*IF(D27='Оценка сложности задач'!$B$36,1,0)*'Оценка сложности задач'!$G$36)+(IF(C27='Оценка сложности задач'!$A$37,1,0)*IF(D27='Оценка сложности задач'!$B$37,1,0)*'Оценка сложности задач'!$G$37)+(IF(C27='Оценка сложности задач'!$A$38,1,0)*IF(D27='Оценка сложности задач'!$B$38,1,0)*'Оценка сложности задач'!$G$38)+(IF(C27='Оценка сложности задач'!$A$39,1,0)*IF(D27='Оценка сложности задач'!$B$39,1,0)*'Оценка сложности задач'!$G$39)+(IF(C27='Оценка сложности задач'!$A$40,1,0)*IF(D27='Оценка сложности задач'!$B$40,1,0)*'Оценка сложности задач'!$G$40) -> 0
... A54: 51 | E54: =(IF(C54='Оценка сложности задач'!$A$2,1,0)*IF(D54='Оценка сложности задач'!$B$2,1,0)*'Оценка сложности задач'!$G$2)+(IF(C54='Оценка сложности задач'!$A$3,1,0)*IF(D54='Оценка сложности задач'!$B$3,1,0)*'Оценка сложности задач'!$G$3)+(IF(C54='Оценка сложности задач'!$A$4,1,0)*IF(D54='Оценка сложности задач'!$B$4,1,0)*'Оценка сложности задач'!$G$4)+(IF(C54='Оценка сложности задач'!$A$5,1,0)*IF(D54='Оценка сложности задач'!$B$5,1,0)*'Оценка сложности задач'!$G$5)+(IF(C54='Оценка сложности задач'!$A$6,1,0)*IF(D54='Оценка сложности задач'!$B$6,1,0)*'Оценка сложности задач'!$G$6)+(IF(C54='Оценка сложности задач'!$A$7,1,0)*IF(D54='Оценка сложности задач'!$B$7,1,0)*'Оценка сложности задач'!$G$7)+(IF(C54='Оценка сложности задач'!$A$8,1,0)*IF(D54='Оценка сложности задач'!$B$8,1,0)*'Оценка сложности задач'!$G$8)+(IF(C54='Оценка сложности задач'!$A$10,1,0)*IF(D54='Оценка сложности задач'!$B$10,1,0)*'Оценка сложности задач'!$G$10)+(IF(C54='Оценка сложности задач'!$A$9,1,0)*IF(D54='Оценка сложности задач'!$B$9,1,0)*'Оценка сложности задач'!$G$9)+ (IF(C54='Оценка сложности задач'!$A$11,1,0)*IF(D54='Оценка сложности задач'!$B$11,1,0)*'Оценка сложности задач'!$G$11) + (IF(C54='Оценка сложности задач'!$A$12,1,0)*IF(D54='Оценка сложности задач'!$B$12,1,0)*'Оценка сложности задач'!$G$12) + (IF(C54='Оценка сложности задач'!$A$13,1,0)*IF(D54='Оценка сложности задач'!$B$13,1,0)*'Оценка сложности задач'!$G$13) + (IF(C54='Оценка сложности задач'!$A$14,1,0)*IF(D54='Оценка сложности задач'!$B$14,1,0)*'Оценка сложности задач'!$G$14) + (IF(C54='Оценка сложности задач'!$A$15,1,0)*IF(D54='Оценка сложности задач'!$B$15,1,0)*'Оценка сложности задач'!$G$15) + (IF(C54='Оценка сложности задач'!$A$16,1,0)*IF(D54='Оценка сложности задач'!$B$16,1,0)*'Оценка сложности задач'!$G$16) + (IF(C54='Оценка сложности задач'!$A$17,1,0)*IF(D54='Оценка сложности задач'!$B$17,1,0)*'Оценка сложности задач'!$G$17) + (IF(C54='Оценка сложности задач'!$A$18,1,0)*IF(D54='Оценка сложности задач'!$B$18,1,0)*'Оценка сложности задач'!$G$18) + (IF(C54='Оценка сложности задач'!$A$19,1,0)*IF(D54='Оценка сложности задач'!$B$19,1,0)*'Оценка сложности задач'!$G$19)+(IF(C54='Оценка сложности задач'!$A$20,1,0)*IF(D54='Оценка сложности задач'!$B$20,1,0)*'Оценка сложности задач'!$G$20)+(IF(C54='Оценка сложности задач'!$A$21,1,0)*IF(D54='Оценка сложности задач'!$B$21,1,0)*'Оценка сложности задач'!$G$21)+(IF(C54='Оценка сложности задач'!$A$22,1,0)*IF(D54='Оценка сложности задач'!$B$22,1,0)*'Оценка сложности задач'!$G$22)+(IF(C54='Оценка сложности задач'!$A$23,1,0)*IF(D54='Оценка сложности задач'!$B$23,1,0)*'Оценка сложности задач'!$G$23)+(IF(C54='Оценка сложности задач'!$A$24,1,0)*IF(D54='Оценка сложности задач'!$B$24,1,0)*'Оценка сложности задач'!$G$24)+(IF(C54='Оценка сложности задач'!$A$25,1,0)*IF(D54='Оценка сложности задач'!$B$25,1,0)*'Оценка сложности задач'!$G$25)+(IF(C54='Оценка сложности задач'!$A$26,1,0)*IF(D54='Оценка сложности задач'!$B$26,1,0)*'Оценка сложности задач'!$G$26)+(IF(C54='Оценка сложности задач'!$A$27,1,0)*IF(D54='Оценка сложности задач'!$B$27,1,0)*'Оценка сложности задач'!$G$27)+(IF(C54='Оценка сложности задач'!$A$28,1,0)*IF(D54='Оценка сложности задач'!$B$28,1,0)*'Оценка сложности задач'!$G$28)+(IF(C54='Оценка сложности задач'!$A$29,1,0)*IF(D54='Оценка сложности задач'!$B$29,1,0)*'Оценка сложности задач'!$G$29)+(IF(C54='Оценка сложности задач'!$A$30,1,0)*IF(D54='Оценка сложности задач'!$B$30,1,0)*'Оценка сложности задач'!$G$30)+(IF(C54='Оценка сложности задач'!$A$31,1,0)*IF(D54='Оценка сложности задач'!$B$31,1,0)*'Оценка сложности задач'!$G$31)+(IF(C54='Оценка сложности задач'!$A$32,1,0)*IF(D54='Оценка сложности задач'!$B$32,1,0)*'Оценка сложности задач'!$G$32)+(IF(C54='Оценка сложности задач'!$A$33,1,0)*IF(D54='Оценка сложности задач'!$B$33,1,0)*'Оценка сложности задач'!$G$33)+(IF(C54='Оценка сложности задач'!$A$34,1,0)*IF(D54='Оценка сложности задач'!$B$34,1,0)*'Оценка сложности задач'!$G$34)+(IF(C54='Оценка сложности задач'!$A$35,1,0)*IF(D54='Оценка сложности задач'!$B$35,1,0)*'Оценка сложности задач'!$G$35)+(IF(C54='Оценка сложности задач'!$A$36,1,0)*IF(D54='Оценка сложности задач'!$B$36,1,0)*'Оценка сложности задач'!$G$36)+(IF(C54='Оценка сложности задач'!$A$37,1,0)*IF(D54='Оценка сложности задач'!$B$37,1,0)*'Оценка сложности задач'!$G$37)+(IF(C54='Оценка сложности задач'!$A$38,1,0)*IF(D54='Оценка сложности задач'!$B$38,1,0)*'Оценка сложности задач'!$G$38)+(IF(C54='Оценка сложности задач'!$A$39,1,0)*IF(D54='Оценка сложности задач'!$B$39,1,0)*'Оценка сложности задач'!$G$39)+(IF(C54='Оценка сложности задач'!$A$40,1,0)*IF(D54='Оценка сложности задач'!$B$40,1,0)*'Оценка сложности задач'!$G$40) -> 0
A55: ИТОГО: | E55: =SUM(E4:E54) -> 186 | F55: =SUM(F4:F54) -> 0

Sheet Оценка Middle
A1: Расчет стоимости разработки и внедрения программного робота на процесс
A3: Автоматическое создание задач в YouGile по заявкам клиентов из почты — ООО «ИнфоСервис»
A4: Средняя ставка руб./чел-час* | F4: 3950
A5: № | B5: Наименование работ | C5: Состав работ | E5: Трудозатраты, чел-час | F5: Стоимость работ, руб. без НДС | G5: Сроки, раб. дней
A6: 1 | B6: Разработка и согласование ЧТЗ на создание робота | C6: Уточнение требований к роботизации процесса с владельцем процесса | E6: 6 | F6: =E6*$F$4 -> 23700 | G6: 3
C7: Разработка и согласование ЧТЗ на создание робота | E7: 10 | F7: =E7*$F$4 -> 39500
A8: 2 | B8: Настройка алгоритма робота | C8: Настройка алгоритма робота по шагам процесса: | E8: =SUM(E9:E33) -> 64 | F8: =E8*$F$4 -> 252800 | G8: 8
C9: 1 | D9: Настроить доступ к почтовому ящику заявок и правила отбора писем | E9: 6
C10: 2 | D10: Считывание письма (тема/тело/отправитель) и вложений | E10: 6
C11: 3 | D11: Парсинг данных заявки и контактов (email, телефон, имя, компания) | E11: 10
C12: 4 | D12: Проверка дубликатов и контроль повторной обработки | E12: 6
C13: 5 | D13: Подключение к YouGile (токен/API) и выбор проекта/доски | E13: 6
C14: 6 | D14: Создание задачи и заполнение полей (название, описание, контакты, теги) | E14: 10
C15: 7 | D15: Прикрепление вложений к задаче | E15: 6
C16: 8 | D16: Уведомление менеджера / комментарий в задаче | E16: 4
C17: 9 | D17: Логирование результата (журнал + ссылка) и маркировка письма | E17: 4
C18: 10 | D18: Обработка ошибок и повторные попытки (ретраи) | E18: 6
C19: 11
C20: 12
C21: 13
C22: 14
C23: 15
C24: 16
C25: 17
C26: 18
C27: 19
C28: 20
C29: 21
C30: 22
... C33: 25
A34: 3 | B34: Настройка робота в промышленной среде | C34: Настройка робота на продуктовом стенде, с отработкой взаимодействия с участвующими системами в постоянной (промышленной) эксплуатации | E34: 8 | F34: =E34*$F$4 -> 31600 | G34: 13
C35: Разработка эксплуатационной документации (Инструкция по работе с роботом) | E35: 6 | F35: =E35*$F$4 -> 23700
C36: Консультационная поддержка пользователей робота в течение 10 раб. Дней | E36: 10 | F36: =E36*$F$4 -> 39500
A37: Итого: | F37: =SUM(F6:F36) -> 410800 | G37: =SUM(G6:G36) -> 24

Sheet Оценка High
A1: Расчет стоимости разработки и внедрения программного робота на процесс
A3: Автоматическое создание задач в YouGile по заявкам клиентов из почты — ООО «ИнфоСервис»
A4: Средняя ставка руб./чел-час* | F4: 3950
A5: № | B5: Наименование работ | C5: Состав работ | E5: Трудозатраты, чел-час | F5: Стоимость работ, руб. без НДС | G5: Сроки, раб. дней
A6: 1 | B6: Разработка и согласование ЧТЗ на программного робота | C6: Уточнение требований к роботизации процесса с владельцем процесса | E6: 6 | F6: =E6*$F$4 -> 23700 | G6: 3
C7: Разработка и согласование ЧТЗ на программного робота | E7: 10 | F7: =E7*$F$4 -> 39500
A8: 2 | B8: Настройка алгоритма программного робота. Подготовка программного робота к опытно-промышленной эксплуатации (ОПЭ) | C8: Настройка алгоритма программного робота на стенде разработки и тестирования по шагам процесса: | E8: =SUM(E9:E33) -> 64 | F8: =E8*$F$4 -> 252800 | G8: 12
C9: 1 | D9: Настроить доступ к почтовому ящику заявок и правила отбора писем | E9: 6
C10: 2 | D10: Считывание письма (тема/тело/отправитель) и вложений | E10: 6
C11: 3 | D11: Парсинг данных заявки и контактов (email, телефон, имя, компания) | E11: 10
C12: 4 | D12: Проверка дубликатов и контроль повторной обработки | E12: 6
C13: 5 | D13: Подключение к YouGile (токен/API) и выбор проекта/доски | E13: 6
C14: 6 | D14: Создание задачи и заполнение полей (название, описание, контакты, теги) | E14: 10
C15: 7 | D15: Прикрепление вложений к задаче | E15: 6
C16: 8 | D16: Уведомление менеджера / комментарий в задаче | E16: 4
C17: 9 | D17: Логирование результата (журнал + ссылка) и маркировка письма | E17: 4
C18: 10 | D18: Обработка ошибок и повторные попытки (ретраи) | E18: 6
C19: 11
C20: 12
C21: 13
C22: 14
C23: 15
C24: 16
C25: 17
C26: 18
C27: 19
C28: 20
C29: 21
C30: 22
... C33: 25
C34: Настройка программного робота на продуктовом стенде, с отработкой взаимодействия с участвующими системами в постоянной (промышленной) эксплуатации | E34: 8 | F34: =E34*$F$4 -> 31600
C35: Разработка эксплуатационной документации | E35: 6 | F35: =E35*$F$4 -> 23700
C36: Разработка программы и методики испытаний для сдачи в ОПЭ | E36: 4 | F36: =E36*$F$4 -> 15800
A37: 3 | B37: Опытно-промышленная эксплуатация и сдача в постоянную эксплуатацию программного робота | C37: Консультационная поддержка пользователей программного робота в период ОПЭ | E37: 0 | F37: =E37*$F$4 -> 0 | G37: 0
C38: Устранение неисправностей программного робота выявленных в результате ОПЭ | E38: 0 | F38: =E38*$F$4 -> 0
C39: Проведение приемо-сдаточных испытаний для сдачи в постоянную (промышленную) эксплуатацию | E39: 0 | F39: =E39*$F$4 -> 0
A40: Итого стоимость работ по процессу: | F40: =SUM(F6:F39) -> 387100 | G40: =SUM(G6:G39) -> 15

Sheet Лист1
A1: Вход в систему | B1: 11 | E1: 11
A2: Ввод дат | B2: 22 | E2: 22
A3: Управление формой (выбор версии для отчета) | B3: 22 | E3: 22
A4: Выгрузка по железным дорогам по первому отчту | B4: 32 | E4: 32
A5: Выгрузка по филиалам по первому отчету | E5: 32
A6: Выгрузка отчетов третьего типа | B6: 22 | E6: 32
A7: Сопоставление данных из очета с документом с полями (word) | B7: 32 | E7: 32
A8: Внесение данных в отчет таблицу Исторических данных | B8: 11 | E8: 32
B9: 0 | E9: 32
B10: =SUM(B1:B9) -> 152 | E10: 32
E11: =SUM(E1:E10) -> 279
A18: 367 | B18: =A18/8 -> 45.875
B20: Наименование процесса | C20: Часы на настройку робота | D20: Часы на отработку робота
B21: 1. Выгрузка всех трех отчетов в одном роботе | C21: 367 часов | D21: 140 часов
B22: 2. Выгрузка отчета первого вида | C22: 183 часа | D22: 47 часов
B23: 3. Выгрузка отчета второго вида | C23: 119 часов | D23: 40 часов
B24: 4. Выгрузка отчета третьего вида | C24: 120 часов | D24: 53 часа
B25: 5. Выгрузка отчета первого и второго вида | C25: 271 час | D25: 87 часов

Sheet Чек-лист
A1: Общие параметры проекта
A2: Сбор требований для оценки затрат
A3: № | B3: Вопрос | C3: Ответ | D3: Дополнительная информация
A4: 1 | B4: Общие сведения
A5: 1.1 | B5: Наименование Заказчика | C5: ООО «ИнфоСервис»
A6: 1.2 | B6: Адрес Заказчика | C6: 115280, г. Москва, ул. Ленинская Слобода, д. 19, офис 305
A7: 1.3 | B7: Наименование процесса (процессов) | C7: Автоматическое создание задач в YouGile по заявкам клиентов из спец. почтовых ящиков
A10: 1 | B10: Организационные вопросы
A11: 1.1. | B11: Возможна ли разработка и сдача робота(ов) удаленно? | C11: Да | D11: Команда исполнителя и Заказчик работают удаленно; коммуникации — Teams/Zoom.
A12: 1.2 | B12: Есть ли подробное описание процесса? | C12: Да | D12: Есть регламент обработки заявок и текущий шаблон задачи в YouGile.
A13: 1.1. | B13: Готов Заказчик показать подробно процесс через ВКС? | C13: Да | D13: Покажем процесс обработки письма и создания задачи в YouGile.
A14: 1.3 | B14: Готов ли Заказчик предоставить сейчас все входные данные, участвующие в процессе (шаблоны, образцы, наборы данных и пр.)? Если да, то какие? | C14: Да | D14: Предоставим 20–30 примеров писем-заявок, структуру полей YouGile, доступ к тестовой доске/проекту.
A15: 1.1. | B15: Есть ли требования к срокам разработки? Если да, то какие? | C15: Да | D15: Желаемый запуск MVP — в течение 2 недель с момента старта работ.
A16: 1.4 | B16: Есть ли особые требования к информационной безопасности? Если да, то какие? | C16: Да | D16: Работа в корпоративном контуре; доступы по учетным записям; логирование действий; без передачи данных во внешние сервисы.
A17: 1.1. | B17: Требуется ли опытно-промышленная эксплуатация робота? Если да, то с каким сроком? | C17: Нет | D17: Достаточно тестового контура и приемочных испытаний. При необходимости — пилот 1 неделя.
A18: 1.5 | B18: Требуется ли авторская поддержка робота (доработка, консультации и пр.)? Не путать с гарантийной поддержкой робота и/или лицензионнной подержкой платформы | C18: Да | D18: Авторская поддержка 1 месяц после запуска; далее — сопровождение по SLA/заявкам.
A19: 2 | B19: Параметры процесса
A20: 2.1 | B20: Есть ли необходимость работать с сайтом\приложением через API? | C20: Да | D20: YouGile: REST API. Почта: Microsoft 365/Outlook (Graph API/IMAP).
A21: 2.2 | B21: Присутствует ли при авторизации функционал распознавания Captcha? Если да, то охарактерезуййте его сложность (буквы/цифры либо фото) | C21: Нет | D21: CAPTCHA не используется.
A22: 2.3 | B22: Требуется ли извлечение данных из изображений (сканов) документов? Если да, то ответьте на следующие вопросы: | C22: Нет | D22: Извлечение из сканов/изображений не требуется (работаем с текстом письма).
A23: 2.3.1 | B23: Какие документы обрабатываются, сколько типов? (счета фактуры, паспорта, СНИЛС и тд) | C23: Не применимо (обработка документов/сканов не требуется)
A24: 2.3.2 | B24: Документы попадают из одного источника? Если нет, нужна ли классификация документов? | C24: Да | D24: Источник один — спец. почтовые ящики. Классификация писем по правилам/тегам.
A25: 2.3.3 | B25: Какие сущности необходимо извлекать из документов? | C25: Из текста письма: ФИО/имя, телефон, email, компания, описание заявки, приоритет (если указан). | D25: Если контакты не найдены — берем из поля «От» и добавляем пометку «контакты не извлечены».
A26: 2.3.4 | B26: Предполагается ли ручная верификация распознанных документов? Если да, то коротко опишите состав верифицируемых данных | C26: Нет | D26: Ручная верификация не требуется. При сомнении робот помечает задачу тегом «нужна проверка».
A27: 2.3.5 | B27: Нужна ли пакетная обработка документов (сверка данных между различными документами в пакете)? Если да, то коротко опишите виды сверяемых данных | C27: Нет | D27: Пакетная сверка не требуется.
A28: 2.3.6 | B28: Может ли клиент предоставить документы для анализа? (до 5 примеров каждого типа) | C28: Да | D28: Предоставим примеры писем и вложений (до 5 типов вложений).
A29: 2.3.7 | B29: Документы какого качества попадают в обработку (сканы, фото, присылают по whatsapp и т.д.)? | C29: Текстовые письма; иногда вложения PDF/изображения (прикрепляем к задаче без распознавания).
A30: 2.3.8 | B30: Какой объем обрабатываемых документов (страниц в месяц/год) | C30: ≈ 100–150 заявок в месяц (в пиковые месяцы до 250).
A31: 2.4 | B31: Есть ли в процессе действия работы с локальными прикладными системами (настольными приложениями)? Если да, то какие? | C31: Нет | D31: Настольные приложения не используются.
A32: 2.5 | B32: Необходима ли в процессе работа с почтой? Если да, то через какой интерфейс? | C32: Да | D32: Через Outlook/Microsoft 365: ящики заявки@… и support@…; робот работает по API.
A33: 2.6 | B33: Требуется работа с окнами RDP? Если да, требуется ли обмен инфомацией между основным и удаленным рабочим столом? | C33: Нет | D33: RDP не требуется.
A34: 2.7 | B34: Требуется ли в процессе применение технологий AI: классификация документов, распознавание именованных сущностей (например Дата, ФИО, адрес и пр.)? Если да, то какие? | C34: Нет | D34: AI/ML не требуется. Используем правила и парсинг текста.
A35: 2.8 | B35: Требуется ли в процессе chat-bot? Если да, то кратко изложите его функции | C35: Нет | D35: Chat-bot не требуется.
A36: 2.9 | B36: Используются в процессе базы данных? Если да, то какие? | C36: Да | D36: Для логирования: Excel/Google Sheets или SQL (по согласованию). На первом этапе — Excel.
A37: 2.10 | B37: Используются в процессе офисные программы? Если да, то какие? ( MsOffice, Р7 офис, МойОфис, Google сервисы) | C37: Нет | D37: MS Office не требуется (кроме ведения журнала в Excel при необходимости).
A38: 2.11 | B38: Нужно формировать отчет по результатам выполнения робота? Если да, какие основные данные этого отчета? | C38: Да | D38: Журнал: дата/время, отправитель, тема, статус, ссылка на задачу YouGile. Ежедневная сводка на email.
A39: 3 | B39: Документирование
A40: 3.1 | B40: Требуется ли программа и методика испытаний для сдачи робота? | C40: Да | D40: Нужен краткий сценарий/чек-лист приемочных испытаний (UAT).
A41: 3.2 | B41: Требуются ли другие проектные/технические/рабочие документы, кроме стандартной инструкции работы с роботом? Если да, то какие? | C41: Да | D41: Инструкция пользователя/админа, описание алгоритма, список настроек и зависимостей.
A42: 3.3 | B42: Есть ли у Заказчика специальные требования (шаблоны) к технической документации? | C42: Да | D42: Используем корпоративные шаблоны; предоставим образцы.

Sheet Оценка сложности задач
A1: Тип задачи | B1: Сложность | C1: Объяснение | D1: Оценка аналитика | E1: Оценка разработчика | F1: Оценка тестирования | G1: Итоговая оценка | H1: А | I1: Р | J1: Т | K1: Дополнительный комментарий | L1: 5
A2: Настройка процесса | B2: Легкая | C2: запуск или завершение процесса, релизация цикла опроцесса, вывод сообщений в модальном окне Базовые действия, Конвертация дат, Диалоговые окна, ОС, Процессы | D2: 4 | E2: 0 | F2: =ROUNDUP((D2+E2)/3,0) -> 2 | G2: =SUM(D2:F2) -> 6 | H2: 1 | I2: =E2/G2 -> 0 | J2: 0 | K2: Здесь сложность может корректироваться доп. Часами зависит от сложности задачи, которую необходимо решить
A3: Настройка процесса | B3: Средняя | C3: исполнение команд / скриптов, настройка процесса обработки ошибок простого или среднего уровня сложности настройка алгоритма, подразумевающего работу с ресурсом "зашифрованная строка" и включающего обработку возможных ошибок | D3: 12 | E3: 0 | F3: =ROUNDUP((D3+E3)/3,0) -> 4 | G3: =SUM(D3:F3) -> 16 | H3: 1 | I3: =E3/G3 -> 0 | J3: 0 | K3: Здесь сложность может корректироваться доп. Часами зависит от сложности задачи, которую необходимо решить
A4: Настройка процесса | B4: Сложная | C4: исполнение скриптов с получением результата, настройка процесса обработки ошибок и алгоритмов, высокой сложности настройка алгоритма, подразумевающего работу с ресурсом "библиотека/скрипт", включающего обработку возможных ошибок и проверку входных данных на соответствие ожидаемым (типы данных) | D4: 24 | E4: 0 | F4: =ROUNDUP((D4+E4)/3,0) -> 8 | G4: =SUM(D4:F4) -> 32 | H4: 1 | I4: =E4/G4 -> 0 | J4: 0 | K4: Здесь сложность может корректироваться доп. Часами зависит от сложности задачи, которую необходимо решить
A5: Обработка web-страницы | B5: Легкая | C5: переходы по странице, авторизация 1) «открыть браузер» и/или «перейти по URL» и/или «закрыть браузер» и/или «получить URL» ИЛИ/И 2) Любые действия, для которых необходимо получать Xpath, - от 1-3 действий в одном шаге процесса И 3) Работа в Google Chrome | D5: 4 | E5: 0 | F5: =ROUNDUP((D5+E5)/3,0) -> 2 | G5: =SUM(D5:F5) -> 6 | H5: 1 | I5: =E5/G5 -> 0 | J5: 0 | K5: Здесь сложность может корректироваться доп. Часами зависит от сложности задачи, которую необходимо решить
A6: Обработка web-страницы | B6: Средняя | C6: использование xpath любой браузер, изменяющиеся xpath 2) Любые действия, для которых необходимо получать Xpath, - от 4 до 8 действий в одном шаге процесса | D6: 10 | E6: 0 | F6: =ROUNDUP((D6+E6)/3,0) -> 4 | G6: =SUM(D6:F6) -> 14 | H6: 1 | I6: =E6/G6 -> 0 | J6: 0 | K6: Действия, в которых из-за особенностей кода Web-страниц приходится прописывать корректный Xpath вручную можно отнести к среднему или сложному уровню сложности в зависимости от кол-ва таких действий на одном шаге процесса. Но, как правило, на этапе оценки еще не известны такие подробности устройства web-страниц. Поэтому оценивать сложность шагов процесса по обработке web-страниц в зависимости от Xpath практически невозможно
A7: Обработка web-страницы | B7: Сложная | C7: xpath с использованием переменных студии, обработка фреймов, данные из таблиц 1) Любые действия, для которых необходимо получать Xpath, - от 8 и более действий в одном шаге процесса 2) Необходимо проверять доступность/наличие (например, если система долго обновляет страницу) нужных полей/кнопок или, заполнены ли некоторые поля нужными данными – от 3х и более проверок И 3) Работа в Google Chrome или Internet Explorer | D7: 24 | E7: 0 | F7: =ROUNDUP((D7+E7)/3,0) -> 8 | G7: =SUM(D7:F7) -> 32 | H7: 1 | I7: =E7/G7 -> 0 | J7: 0 | K7: Здесь сложность может корректироваться доп. Часами зависит от сложности задачи, которую необходимо решить
A8: Обработка ЭФ | B8: Легкая | C8: работа с экранной формой, которая содержит не более 5 полей для взаимодействия | D8: 6 | E8: 0 | F8: =ROUNDUP((D8+E8)/3,0) -> 2 | G8: =SUM(D8:F8) -> 8 | H8: 1 | I8: =E8/G8 -> 0 | J8: 0 | K8: Здесь сложность может корректироваться доп. Часами зависит от сложности задачи, которую необходимо решить
A9: Обработка ЭФ | B9: Средняя | C9: работа с экранной формой, которая содержит от 6 до 10 полей для взаимодействия | D9: 10 | E9: 0 | F9: 3 | G9: =SUM(D9:F9) -> 13 | H9: 1 | I9: =E9/G9 -> 0 | J9: 0 | K9: Здесь сложность может корректироваться доп. Часами зависит от сложности задачи, которую необходимо решить
A10: Обработка ЭФ | B10: Сложная | C10: работа с экранной формой, котрая содержит более 10 полей для взаимодействия | D10: 24 | E10: 0 | F10: =ROUNDUP((D10+E10)/3,0) -> 8 | G10: =SUM(D10:F10) -> 32 | H10: 1 | I10: =E10/G10 -> 0 | J10: 0 | K10: Здесь сложность может корректироваться доп. Часами зависит от сложности задачи, которую необходимо решить
A11: Vision / OCR | B11: Легкая | C11: поиск изображения | D11: 4 | E11: 0 | F11: =ROUNDUP((D11+E11)/3,0) -> 2 | G11: =SUM(D11:F11) -> 6 | H11: 1 | I11: =E11/G11 -> 0 | J11: 0 | K11: Здесь сложность может корректироваться доп. Часами зависит от сложности задачи, которую необходимо решить
A12: Vision / OCR | B12: Средняя | C12: распознование текста с изображения/pdf | D12: 8 | E12: 0 | F12: =ROUNDUP((D12+E12)/3,0) -> 3 | G12: =SUM(D12:F12) -> 11 | H12: 1 | I12: =E12/G12 -> 0 | J12: 0 | K12: Здесь сложность может корректироваться доп. Часами зависит от сложности задачи, которую необходимо решить
A13: Vision / OCR | B13: Сложная | C13: распознование текста по шаблону | D13: 20 | E13: 0 | F13: =ROUNDUP((D13+E13)/3,0) -> 7 | G13: =SUM(D13:F13) -> 27 | H13: 1 | I13: =E13/G13 -> 0 | J13: 0 | K13: Здесь сложность может корректироваться доп. Часами зависит от сложности задачи, которую необходимо решить
A14: Office App | B14: Легкая | C14: заполнение ячеек, копирование данных из ячеек|запись, чтение в файл | D14: 4 | E14: 0 | F14: =ROUNDUP((D14+E14)/3,0) -> 2 | G14: =SUM(D14:F14) -> 6 | H14: 1 | I14: =E14/G14 -> 0 | J14: 0 | K14: Здесь сложность может корректироваться доп. Часами зависит от сложности задачи, которую необходимо решить
A15: Office App | B15: Средняя | C15: работа с таблицами, работа с фильтрами, использование горячих клавиш, изменение структуры файла/фильтрация для Excel | D15: 8 | E15: 0 | F15: =ROUNDUP((D15+E15)/3,0) -> 3 | G15: =SUM(D15:F15) -> 11 | H15: 1 | I15: =E15/G15 -> 0 | J15: 0 | K15: Здесь сложность может корректироваться доп. Часами зависит от сложности задачи, которую необходимо решить
A16: Office App | B16: Сложная | C16: макросы, работа с областями таблицы, работа с формулами | D16: 20 | E16: 0 | F16: =ROUNDUP((D16+E16)/3,0) -> 7 | G16: =SUM(D16:F16) -> 27 | H16: 1 | I16: =E16/G16 -> 0 | J16: 0 | K16: Здесь сложность может корректироваться доп. Часами зависит от сложности задачи, которую необходимо решить
A17: Файлы/Папки/FTP | B17: Легкая | C17: поиск файла, пути до файлов, работа с папками: копирование/удаление/перемещение и т.д. | D17: 4 | E17: 0 | F17: =ROUNDUP((D17+E17)/3,0) -> 2 | G17: =SUM(D17:F17) -> 6 | H17: 1 | I17: =E17/G17 -> 0 | J17: 0 | K17: Здесь сложность может корректироваться доп. Часами зависит от сложности задачи, которую необходимо решить
A18: Файлы/Папки/FTP | B18: Средняя | C18: работа с многочисленными файлами в циклах | D18: 8 | E18: 0 | F18: =ROUNDUP((D18+E18)/3,0) -> 3 | G18: =SUM(D18:F18) -> 11 | H18: 1 | I18: =E18/G18 -> 0 | J18: 0 | K18: Здесь сложность может корректироваться доп. Часами зависит от сложности задачи, которую необходимо решить
A19: Файлы/Папки/FTP | B19: Сложная | C19: ftp | D19: 20 | E19: 0 | F19: =ROUNDUP((D19+E19)/3,0) -> 7 | G19: =SUM(D19:F19) -> 27 | H19: 1 | I19: =E19/G19 -> 0 | J19: 0 | K19: Здесь сложность может корректироваться доп. Часами зависит от сложности задачи, которую необходимо решить
A20: Почта/Outlook | B20: Легкая | C20: 1) «Настройка подключения» + «отправка» и/или + «получение» с 1-3 заполненными пунктами в параметрах ИЛИ 2) Outlook: «получить» и/или «отправить»/ «ответить» с 1-3 заполненными пунктами в параметрах | D20: 4 | E20: 0 | F20: =ROUNDUP((D20+E20)/3,0) -> 2 | G20: =SUM(D20:F20) -> 6 | H20: 1 | I20: =E20/G20 -> 0 | J20: 0 | K20: Здесь сложность может корректироваться доп. Часами зависит от сложности задачи, которую необходимо решить
A21: Почта/Outlook | B21: Средняя | C21: 1) «Настройка подключения» + «отправка» и/или + «получение» с 4 и более заполненными пунктами в параметрах. Некоторые пункты могут быть заполнены переменными ИЛИ 2) Outlook: «получить» и/или «отправить»/ «ответить» с 4 и более заполненными пунктами в параметрах. Некоторые пункты могут быть заполнены переменными 3) Форматирование текста письма при пощи html тегов | D21: 8 | E21: 0 | F21: =ROUNDUP((D21+E21)/3,0) -> 3 | G21: =SUM(D21:F21) -> 11 | H21: 1 | I21: =E21/G21 -> 0 | J21: 0 | K21: Здесь сложность может корректироваться доп. Часами зависит от сложности задачи, которую необходимо решить
... A26: Обработка текста | B26: Легкая | C26: написание регулярных выражений простой сложности | D26: 2 | E26: 0 | F26: =ROUNDUP((D26+E26)/3,0) -> 1 | G26: =SUM(D26:F26) -> 3 | H26: 1 | I26: =E26/G26 -> 0 | J26: 0 | K26: NER, Данные из таблицы, Работа с текстом
A27: Обработка текста | B27: Средняя | C27: написание регулярных выражений средней сложности | D27: 4 | E27: 0 | F27: =ROUNDUP((D27+E27)/3,0) -> 2 | G27: =SUM(D27:F27) -> 6 | H27: 1 | I27: =E27/G27 -> 0 | J27: 0
A28: Обработка текста | B28: Сложная | C28: написание регулярных выражений высокой сложности | D28: 8 | E28: 0 | F28: =ROUNDUP((D28+E28)/3,0) -> 3 | G28: =SUM(D28:F28) -> 11 | H28: 1 | I28: =E28/G28 -> 0 | J28: 0
A29: Flexi Capture/Yandex OCR | B29: Легкая | D29: 16 | E29: 0 | F29: =ROUNDUP((D29+E29)/3,0) -> 6 | G29: =SUM(D29:F29) -> 22 | H29: 1 | I29: =E29/G29 -> 0 | J29: 0 | K29: Flexi Capture
A30: Flexi Capture/Yandex OCR | B30: Средняя | D30: 24 | E30: 0 | F30: =ROUNDUP((D30+E30)/3,0) -> 8 | G30: =SUM(D30:F30) -> 32 | H30: 1 | I30: =E30/G30 -> 0 | J30: 0
A31: Flexi Capture/Yandex OCR | B31: Сложная | D31: 40 | E31: 40 | F31: =ROUNDUP((D31+E31)/3,0) -> 27 | G31: =SUM(D31:F31) -> 107 | H31: 1 | I31: =E31/G31 -> 0.37383178 | J31: 0
A32: REST/SOAP | B32: Легкая | C32: написание простых запросов | D32: 16 | E32: 0 | F32: =ROUNDUP((D32+E32)/3,0) -> 6 | G32: =SUM(D32:F32) -> 22 | H32: 1 | I32: =E32/G32 -> 0 | J32: 0 | K32: REST/SOAP
A33: REST/SOAP | B33: Средняя | C33: Написание запросов средней сложности | D33: 24 | E33: 0 | F33: =ROUNDUP((D33+E33)/3,0) -> 8 | G33: =SUM(D33:F33) -> 32 | H33: 1 | I33: =E33/G33 -> 0 | J33: 0
A34: REST/SOAP | B34: Сложная | C34: Сложные запросы | D34: 40 | E34: 40 | F34: =ROUNDUP((D34+E34)/3,0) -> 27 | G34: =SUM(D34:F34) -> 107 | H34: 1 | I34: =E34/G34 -> 0.37383178 | J34: 0
A35: Интеграции | B35: Легкая | C35: написание простых запросов | D35: 16 | E35: 0 | F35: =ROUNDUP((D35+E35)/3,0) -> 6 | G35: =SUM(D35:F35) -> 22 | H35: 1 | I35: =E35/G35 -> 0 | J35: 0 | K35: Интеграции
A36: Интеграции | B36: Средняя | C36: Написание запросов средней сложности | D36: 24 | E36: 0 | F36: =ROUNDUP((D36+E36)/3,0) -> 8 | G36: =SUM(D36:F36) -> 32 | H36: 1 | I36: =E36/G36 -> 0 | J36: 0
A37: Интеграции | B37: Сложная | C37: Сложные запросы | D37: 40 | E37: 40 | F37: =ROUNDUP((D37+E37)/3,0) -> 27 | G37: =SUM(D37:F37) -> 107 | H37: 1 | I37: =E37/G37 -> 0.37383178 | J37: 0
A38: Базы данных | B38: Легкая | C38: написание простых запросов | D38: 16 | E38: 0 | F38: =ROUNDUP((D38+E38)/3,0) -> 6 | G38: =SUM(D38:F38) -> 22 | H38: 1 | I38: =E38/G38 -> 0 | J38: 0 | K38: Базы данных
A39: Базы данных | B39: Средняя | C39: написание сложных запросов | D39: 24 | E39: 0 | F39: =ROUNDUP((D39+E39)/3,0) -> 8 | G39: =SUM(D39:F39) -> 32 | H39: 1 | I39: =E39/G39 -> 0 | J39: 0
A40: Базы данных | B40: Сложная | C40: написание сложных запросов+ работа с СУБД | D40: 40 | E40: 40 | F40: =ROUNDUP((D40+E40)/3,0) -> 27 | G40: =SUM(D40:F40) -> 107 | H40: 1 | I40: =E40/G40 -> 0.37383178 | J40: 0
A45: Оркестрация
A46: Тип задачи | B46: Сложность | C46: Объяснение | D46: Оценка аналитика | E46: Оценка разработчика | F46: Оценка тестирования | G46: Итоговая оценка
A47: Настройка процессов | B47: Легкая | D47: 8 | E47: 0 | F47: =ROUNDUP((D47+E47)/3,0) -> 3 | G47: =SUM(D47:F47) -> 11 | H47: =D47/G47 -> 0.72727273 | I47: =E47/G47 -> 0 | J47: =F47/G47 -> 0.27272727
A48: Настройка процессов | B48: Средняя | D48: 16 | E48: 8 | F48: =ROUNDUP((D48+E48)/3,0) -> 8 | G48: =SUM(D48:F48) -> 32 | H48: =D48/G48 -> 0.5 | I48: =E48/G48 -> 0.25 | J48: =F48/G48 -> 0.25
A49: Настройка процессов | B49: Сложная | D49: 16 | E49: 16 | F49: =ROUNDUP((D49+E49)/3,0) -> 11 | G49: =SUM(D49:F49) -> 43 | H49: =D49/G49 -> 0.37209302 | I49: =E49/G49 -> 0.37209302 | J49: =F49/G49 -> 0.25581395
A50: Настройка AD | B50: Легкая | D50: 8 | E50: 0 | F50: =ROUNDUP((D50+E50)/3,0) -> 3 | G50: =SUM(D50:F50) -> 11 | H50: =D50/G50 -> 0.72727273 | I50: =E50/G50 -> 0 | J50: =F50/G50 -> 0.27272727
A51: Настройка AD | B51: Средняя | D51: 16 | E51: 8 | F51: =ROUNDUP((D51+E51)/3,0) -> 8 | G51: =SUM(D51:F51) -> 32 | H51: =D51/G51 -> 0.5 | I51: =E51/G51 -> 0.25 | J51: =F51/G51 -> 0.25
A52: Настройка AD | B52: Сложная | D52: 16 | E52: 16 | F52: =ROUNDUP((D52+E52)/3,0) -> 11 | G52: =SUM(D52:F52) -> 43 | H52: =D52/G52 -> 0.37209302 | I52: =E52/G52 -> 0.37209302 | J52: =F52/G52 -> 0.25581395

Sheet Лист2

Sheet FAQ
A1: № | B1: Примечание
A2: 1 | B2: Контейнеры на странице разметки всегда используются стандартные. Их изменение мы пока не делали, сложность не знаем.
A3: 2 | B3: Все измеряется в часах
A4: 3 | B4: Предполагается, что команды работают по скраму и минимум час в день уходит на Scrum активности.
A5: 4

Sheet Справочники
A1: Сложности | B1: Тип задачи | C1: Оркестратор
A2: Легкая | B2: Настройка процесса | C2: Настройка процессов
A3: Средняя | B3: Обработка web-страницы | C3: Настройка AD
A4: Сложная | B4: Обработка ЭФ
A5: Нельзя оценить | B5: Vision / OCR
B6: Office App
B7: Файлы/Папки/FTP
B8: Почта/Outlook
B9: Классификатор
B10: Обработка текста
B11: Flexi Capture/Yandex OCR
B12: REST/SOAP
B13: Интеграции
B14: Базы данных
